Workbook

Sheet Assumptions
A1: Assumptions
A2: Cells in Orange are assumptions | M2: MONTHLY | BV2: YEARLY
A3: Year | M3: 1 | N3: 1 | O3: 1 | P3: 1 | Q3: 1 | R3: 1 | S3: 1 | T3: 1 | U3: 1 | V3: 1 | W3: 1 | X3: 1 | Y3: =X3+1 -> 2 | Z3: =Y3 -> 2 | AA3: =Z3 -> 2 | AB3: =AA3 -> 2 | AC3: =AB3 -> 2 | AD3: =AC3 -> 2 | AE3: =AD3 -> 2 | AF3: =AE3 -> 2 | AG3: =AF3 -> 2 | ... AJ3: =AI3 -> 2 | AK3: 3 | AL3: 3 | AM3: 3 | AN3: 3 | AO3: 3 | AP3: 3 | AQ3: 3 | AR3: 3 | AS3: 3 | AT3: 3 | AU3: 3 | AV3: 3 | AW3: 4 | AX3: 4 | AY3: 4 | AZ3: 4 | BA3: 4 | BB3: 4 | BC3: 4 | BD3: 4 | BE3: 4 | BF3: 4 | BG3: 4 | BH3: 4 | BI3: 5 | BJ3: 5 | BK3: 5 | BL3: 5 | BM3: 5 | BN3: 5 | BO3: 5 | BP3: 5 | BQ3: 5 | BR3: 5 | BS3: 5 | BT3: 5 | BV3: 1 | BW3: 2 | BX3: 3 | BY3: 4 | BZ3: 5
A4: Months | M4: 1 | N4: =M4+1 -> 2 | O4: =N4+1 -> 3 | P4: =O4+1 -> 4 | Q4: =P4+1 -> 5 | R4: =Q4+1 -> 6 | S4: =R4+1 -> 7 | T4: =S4+1 -> 8 | U4: =T4+1 -> 9 | ... BT4: =BS4+1 -> 60 | BV4: 12 | BW4: 24 | BX4: 36 | BY4: 48 | BZ4: 60
A5: Revenue Assumptions
A6: Converation Rate | G6: 0.05 | H6: =G6 -> 0.05 | M6: =G6 -> 0.05 | N6: =M6+($H6-$G6)/COUNT($N$4:$BT$4) -> 0.05 | O6: =N6+($H6-$G6)/COUNT($N$4:$BT$4) -> 0.05 | P6: =O6+($H6-$G6)/COUNT($N$4:$BT$4) -> 0.05 | Q6: =P6+($H6-$G6)/COUNT($N$4:$BT$4) -> 0.05 | R6: =Q6+($H6-$G6)/COUNT($N$4:$BT$4) -> 0.05 | S6: =R6+($H6-$G6)/COUNT($N$4:$BT$4) -> 0.05 | T6: =S6+($H6-$G6)/COUNT($N$4:$BT$4) -> 0.05 | U6: =T6+($H6-$G6)/COUNT($N$4:$BT$4) -> 0.05 | ... BT6: =BS6+($H6-$G6)/COUNT($N$4:$BT$4) -> 0.05
A7: Type 1 SMBs Annual Cost | F7: INR | G7: =10000*12 -> 120000 | H7: =G7 -> 120000 | M7: =G7 -> 120000 | N7: =M7+($H7-$G7)/COUNT($N$4:$BT$4) -> 120000 | O7: =N7+($H7-$G7)/COUNT($N$4:$BT$4) -> 120000 | P7: =O7+($H7-$G7)/COUNT($N$4:$BT$4) -> 120000 | Q7: =P7+($H7-$G7)/COUNT($N$4:$BT$4) -> 120000 | R7: =Q7+($H7-$G7)/COUNT($N$4:$BT$4) -> 120000 | S7: =R7+($H7-$G7)/COUNT($N$4:$BT$4) -> 120000 | T7: =S7+($H7-$G7)/COUNT($N$4:$BT$4) -> 120000 | U7: =T7+($H7-$G7)/COUNT($N$4:$BT$4) -> 120000 | ... BT7: =BS7+($H7-$G7)/COUNT($N$4:$BT$4) -> 120000
A8: Type 2 SMBs Annual Cost | F8: INR | G8: =5000*12 -> 60000 | H8: =G8 -> 60000 | M8: =G8 -> 60000 | N8: =M8+($H8-$G8)/COUNT($N$4:$BT$4) -> 60000 | O8: =N8+($H8-$G8)/COUNT($N$4:$BT$4) -> 60000 | P8: =O8+($H8-$G8)/COUNT($N$4:$BT$4) -> 60000 | Q8: =P8+($H8-$G8)/COUNT($N$4:$BT$4) -> 60000 | R8: =Q8+($H8-$G8)/COUNT($N$4:$BT$4) -> 60000 | S8: =R8+($H8-$G8)/COUNT($N$4:$BT$4) -> 60000 | T8: =S8+($H8-$G8)/COUNT($N$4:$BT$4) -> 60000 | U8: =T8+($H8-$G8)/COUNT($N$4:$BT$4) -> 60000 | ... BT8: =BS8+($H8-$G8)/COUNT($N$4:$BT$4) -> 60000
A9: Duration of Contract | F9: Months | G9: 12 | H9: =G9 -> 12 | M9: =G9 -> 12 | N9: =M9+($H9-$G9)/COUNT($N$4:$BT$4) -> 12 | O9: =N9+($H9-$G9)/COUNT($N$4:$BT$4) -> 12 | P9: =O9+($H9-$G9)/COUNT($N$4:$BT$4) -> 12 | Q9: =P9+($H9-$G9)/COUNT($N$4:$BT$4) -> 12 | R9: =Q9+($H9-$G9)/COUNT($N$4:$BT$4) -> 12 | S9: =R9+($H9-$G9)/COUNT($N$4:$BT$4) -> 12 | T9: =S9+($H9-$G9)/COUNT($N$4:$BT$4) -> 12 | U9: =T9+($H9-$G9)/COUNT($N$4:$BT$4) -> 12 | ... BT9: =BS9+($H9-$G9)/COUNT($N$4:$BT$4) -> 12
A10: Churn & Expansion Revenue
A11: Annual Churn Rate | F11: % | G11: 0.3 | H11: =G11 -> 0.3 | M11: =G11 -> 0.3 | N11: =M11+($H11-$G11)/COUNT($N$4:$BT$4) -> 0.3 | O11: =N11+($H11-$G11)/COUNT($N$4:$BT$4) -> 0.3 | P11: =O11+($H11-$G11)/COUNT($N$4:$BT$4) -> 0.3 | Q11: =P11+($H11-$G11)/COUNT($N$4:$BT$4) -> 0.3 | R11: =Q11+($H11-$G11)/COUNT($N$4:$BT$4) -> 0.3 | S11: =R11+($H11-$G11)/COUNT($N$4:$BT$4) -> 0.3 | T11: =S11+($H11-$G11)/COUNT($N$4:$BT$4) -> 0.3 | U11: =T11+($H11-$G11)/COUNT($N$4:$BT$4) -> 0.3 | ... BT11: =BS11+($H11-$G11)/COUNT($N$4:$BT$4) -> 0.3
A12: Recurring Contracts | F12: % | G12: =1-G11 -> 0.7 | H12: =1-H11 -> 0.7 | M12: =G12 -> 0.7 | N12: =M12+($H12-$G12)/COUNT($N$4:$BT$4) -> 0.7 | O12: =N12+($H12-$G12)/COUNT($N$4:$BT$4) -> 0.7 | P12: =O12+($H12-$G12)/COUNT($N$4:$BT$4) -> 0.7 | Q12: =P12+($H12-$G12)/COUNT($N$4:$BT$4) -> 0.7 | R12: =Q12+($H12-$G12)/COUNT($N$4:$BT$4) -> 0.7 | S12: =R12+($H12-$G12)/COUNT($N$4:$BT$4) -> 0.7 | T12: =S12+($H12-$G12)/COUNT($N$4:$BT$4) -> 0.7 | U12: =T12+($H12-$G12)/COUNT($N$4:$BT$4) -> 0.7 | ... BT12: =BS12+($H12-$G12)/COUNT($N$4:$BT$4) -> 0.7
A13: % Exapansion Added | F13: % | G13: 0.2 | H13: =G13 -> 0.2 | M13: =G13 -> 0.2 | N13: =M13+($H13-$G13)/COUNT($N$4:$BT$4) -> 0.2 | O13: =N13+($H13-$G13)/COUNT($N$4:$BT$4) -> 0.2 | P13: =O13+($H13-$G13)/COUNT($N$4:$BT$4) -> 0.2 | Q13: =P13+($H13-$G13)/COUNT($N$4:$BT$4) -> 0.2 | R13: =Q13+($H13-$G13)/COUNT($N$4:$BT$4) -> 0.2 | S13: =R13+($H13-$G13)/COUNT($N$4:$BT$4) -> 0.2 | T13: =S13+($H13-$G13)/COUNT($N$4:$BT$4) -> 0.2 | U13: =T13+($H13-$G13)/COUNT($N$4:$BT$4) -> 0.2 | ... BT13: =BS13+($H13-$G13)/COUNT($N$4:$BT$4) -> 0.2
A14: Cost Assumptions
A15: Direct Cost
A16: Hosting & Infrastructure Costs
A17: Cloud services (AWS, Google Cloud, Azure) | F17: Monthly Cost | G17: 50000 | H17: =G17*10 -> 500000 | M17: =G17 -> 50000 | N17: =M17+($H17-$G17)/COUNT($N$4:$BT$4) -> 57627.119 | O17: =N17+($H17-$G17)/COUNT($N$4:$BT$4) -> 65254.237 | P17: =O17+($H17-$G17)/COUNT($N$4:$BT$4) -> 72881.356 | Q17: =P17+($H17-$G17)/COUNT($N$4:$BT$4) -> 80508.475 | R17: =Q17+($H17-$G17)/COUNT($N$4:$BT$4) -> 88135.593 | S17: =R17+($H17-$G17)/COUNT($N$4:$BT$4) -> 95762.712 | T17: =S17+($H17-$G17)/COUNT($N$4:$BT$4) -> 103389.83 | U17: =T17+($H17-$G17)/COUNT($N$4:$BT$4) -> 111016.95 | ... BT17: =BS17+($H17-$G17)/COUNT($N$4:$BT$4) -> 500000 | BV17: =SUMIF($M$3:$BT$3,BV$3,$M17:$BT17) -> 1103389.8 | BW17: =SUMIF($M$3:$BT$3,BW$3,$M17:$BT17) -> 2201694.9 | BX17: =SUMIF($M$3:$BT$3,BX$3,$M17:$BT17) -> 3300000 | BY17: =SUMIF($M$3:$BT$3,BY$3,$M17:$BT17) -> 4398305.1 | BZ17: =SUMIF($M$3:$BT$3,BZ$3,$M17:$BT17) -> 5496610.2
A18: Database and storage (Amazon RDS, MongoDB Atlas) | F18: Monthly Cost | G18: 10000 | H18: =G18*10 -> 100000 | M18: =G18 -> 10000 | N18: =M18+($H18-$G18)/COUNT($N$4:$BT$4) -> 11525.424 | O18: =N18+($H18-$G18)/COUNT($N$4:$BT$4) -> 13050.847 | P18: =O18+($H18-$G18)/COUNT($N$4:$BT$4) -> 14576.271 | Q18: =P18+($H18-$G18)/COUNT($N$4:$BT$4) -> 16101.695 | R18: =Q18+($H18-$G18)/COUNT($N$4:$BT$4) -> 17627.119 | S18: =R18+($H18-$G18)/COUNT($N$4:$BT$4) -> 19152.542 | T18: =S18+($H18-$G18)/COUNT($N$4:$BT$4) -> 20677.966 | U18: =T18+($H18-$G18)/COUNT($N$4:$BT$4) -> 22203.39 | ... BT18: =BS18+($H18-$G18)/COUNT($N$4:$BT$4) -> 100000 | BV18: =SUMIF($M$3:$BT$3,BV$3,$M18:$BT18) -> 220677.97 | BW18: =SUMIF($M$3:$BT$3,BW$3,$M18:$BT18) -> 440338.98 | BX18: =SUMIF($M$3:$BT$3,BX$3,$M18:$BT18) -> 660000 | BY18: =SUMIF($M$3:$BT$3,BY$3,$M18:$BT18) -> 879661.02 | BZ18: =SUMIF($M$3:$BT$3,BZ$3,$M18:$BT18) -> 1099322
A19: Content delivery networks (CDN) | F19: Monthly Cost | G19: =30*86 -> 2580 | H19: =G19*5 -> 12900 | M19: =G19 -> 2580 | N19: =M19+($H19-$G19)/COUNT($N$4:$BT$4) -> 2754.9153 | O19: =N19+($H19-$G19)/COUNT($N$4:$BT$4) -> 2929.8305 | P19: =O19+($H19-$G19)/COUNT($N$4:$BT$4) -> 3104.7458 | Q19: =P19+($H19-$G19)/COUNT($N$4:$BT$4) -> 3279.661 | R19: =Q19+($H19-$G19)/COUNT($N$4:$BT$4) -> 3454.5763 | S19: =R19+($H19-$G19)/COUNT($N$4:$BT$4) -> 3629.4915 | T19: =S19+($H19-$G19)/COUNT($N$4:$BT$4) -> 3804.4068 | U19: =T19+($H19-$G19)/COUNT($N$4:$BT$4) -> 3979.322 | ... BT19: =BS19+($H19-$G19)/COUNT($N$4:$BT$4) -> 12900 | BV19: =SUMIF($M$3:$BT$3,BV$3,$M19:$BT19) -> 42504.407 | BW19: =SUMIF($M$3:$BT$3,BW$3,$M19:$BT19) -> 67692.203 | BX19: =SUMIF($M$3:$BT$3,BX$3,$M19:$BT19) -> 92880 | BY19: =SUMIF($M$3:$BT$3,BY$3,$M19:$BT19) -> 118067.8 | BZ19: =SUMIF($M$3:$BT$3,BZ$3,$M19:$BT19) -> 143255.59
A20: Third-Party Software & API Costs
A21: Payment gateway fees (e.g., Stripe, Razorpay) | F21: as a % of bookings | G21: 0.015 | H21: =G21 -> 0.015 | M21: =G21 -> 0.015 | N21: =M21+($H21-$G21)/COUNT($N$4:$BT$4) -> 0.015 | O21: =N21+($H21-$G21)/COUNT($N$4:$BT$4) -> 0.015 | P21: =O21+($H21-$G21)/COUNT($N$4:$BT$4) -> 0.015 | Q21: =P21+($H21-$G21)/COUNT($N$4:$BT$4) -> 0.015 | R21: =Q21+($H21-$G21)/COUNT($N$4:$BT$4) -> 0.015 | S21: =R21+($H21-$G21)/COUNT($N$4:$BT$4) -> 0.015 | T21: =S21+($H21-$G21)/COUNT($N$4:$BT$4) -> 0.015 | U21: =T21+($H21-$G21)/COUNT($N$4:$BT$4) -> 0.015 | ... BT21: =BS21+($H21-$G21)/COUNT($N$4:$BT$4) -> 0.015
A22: Security services (e.g., Cloudflare, Auth0) | F22: Monthly Cost | G22: 5000 | H22: =G22*5 -> 25000 | M22: =G22 -> 5000 | N22: =M22+($H22-$G22)/COUNT($N$4:$BT$4) -> 5338.9831 | O22: =N22+($H22-$G22)/COUNT($N$4:$BT$4) -> 5677.9661 | P22: =O22+($H22-$G22)/COUNT($N$4:$BT$4) -> 6016.9492 | Q22: =P22+($H22-$G22)/COUNT($N$4:$BT$4) -> 6355.9322 | R22: =Q22+($H22-$G22)/COUNT($N$4:$BT$4) -> 6694.9153 | S22: =R22+($H22-$G22)/COUNT($N$4:$BT$4) -> 7033.8983 | T22: =S22+($H22-$G22)/COUNT($N$4:$BT$4) -> 7372.8814 | U22: =T22+($H22-$G22)/COUNT($N$4:$BT$4) -> 7711.8644 | ... BT22: =BS22+($H22-$G22)/COUNT($N$4:$BT$4) -> 25000 | BV22: =SUMIF($M$3:$BT$3,BV$3,$M22:$BT22) -> 82372.881 | BW22: =SUMIF($M$3:$BT$3,BW$3,$M22:$BT22) -> 131186.44 | BX22: =SUMIF($M$3:$BT$3,BX$3,$M22:$BT22) -> 180000 | BY22: =SUMIF($M$3:$BT$3,BY$3,$M22:$BT22) -> 228813.56 | BZ22: =SUMIF($M$3:$BT$3,BZ$3,$M22:$BT22) -> 277627.12
A23: Headcount | BW23: ]
A24: Customer Support | F24: Account/Customer support | G24: 40 | H24: 40 | M24: =G24 -> 40 | N24: =M24+($H24-$G24)/COUNT($N$4:$BT$4) -> 40 | O24: =N24+($H24-$G24)/COUNT($N$4:$BT$4) -> 40 | P24: =O24+($H24-$G24)/COUNT($N$4:$BT$4) -> 40 | Q24: =P24+($H24-$G24)/COUNT($N$4:$BT$4) -> 40 | R24: =Q24+($H24-$G24)/COUNT($N$4:$BT$4) -> 40 | S24: =R24+($H24-$G24)/COUNT($N$4:$BT$4) -> 40 | T24: =S24+($H24-$G24)/COUNT($N$4:$BT$4) -> 40 | U24: =T24+($H24-$G24)/COUNT($N$4:$BT$4) -> 40 | ... BT24: =BS24+($H24-$G24)/COUNT($N$4:$BT$4) -> 40
A25: Customer Support | F25: Monthly Salary/Headcount | G25: 40000 | H25: 0.15 | I25: Annual Increment
A26: Operating Expense
A27: Sales & Marketing Expense
A28: Sales Funnel
A29: Advetising/Marketing Expense Type 1 SMBs Focused | M29: 150000 | N29: =M29 -> 150000 | O29: =N29 -> 150000 | P29: =O29+100000 -> 250000 | Q29: =P29 -> 250000 | R29: =Q29 -> 250000 | S29: =R29*2 -> 500000 | T29: =S29 -> 500000 | U29: =T29 -> 500000 | V29: =U29+250000 -> 750000 | W29: =V29 -> 750000 | X29: =W29 -> 750000 | Y29: =X29+100000 -> 850000 | Z29: =Y29 -> 850000 | AA29: =Z29 -> 850000 | AB29: =AA29+150000 -> 1000000 | AC29: =AB29 -> 1000000 | AD29: =AC29 -> 1000000 | AE29: =AD29*2 -> 2000000 | AF29: =AE29 -> 2000000 | AG29: =AF29 -> 2000000 | AH29: =AG29+200000 -> 2200000 | AI29: =AH29 -> 2200000 | AJ29: =AI29 -> 2200000 | AK29: =AJ29+100000 -> 2300000 | AL29: =AK29 -> 2300000 | AM29: =AL29 -> 2300000 | AN29: =AM29+100000 -> 2400000 | AO29: =AN29 -> 2400000 | AP29: =AO29 -> 2400000 | AQ29: =AP29+100000 -> 2500000 | AR29: =AQ29 -> 2500000 | AS29: =AR29 -> 2500000 | AT29: =AS29+100000 -> 2600000 | AU29: =AT29 -> 2600000 | AV29: =AU29 -> 2600000 | AW29: =AV29+400000 -> 3000000 | AX29: =AW29 -> 3000000 | AY29: =AX29 -> 3000000 | AZ29: =AY29+100000 -> 3100000 | BA29: =AZ29 -> 3100000 | BB29: =BA29 -> 3100000 | BC29: =BB29+100000 -> 3200000 | BD29: =BC29 -> 3200000 | BE29: =BD29 -> 3200000 | BF29: =BE29+100000 -> 3300000 | BG29: =BF29 -> 3300000 | BH29: =BG29 -> 3300000 | BI29: =BH29+400000 -> 3700000 | BJ29: =BI29 -> 3700000 | BK29: =BJ29 -> 3700000 | BL29: =BK29+100000 -> 3800000 | BM29: =BL29 -> 3800000 | BN29: =BM29 -> 3800000 | BO29: =BN29+100000 -> 3900000 | BP29: =BO29 -> 3900000 | BQ29: =BP29 -> 3900000 | BR29: =BQ29+100000 -> 4000000 | BS29: =BR29 -> 4000000 | BT29: =BS29 -> 4000000 | BV29: =SUMIF($M$3:$BT$3,BV$3,$M29:$BT29) -> 4950000 | BW29: =SUMIF($M$3:$BT$3,BW$3,$M29:$BT29) -> 18150000 | BX29: =SUMIF($M$3:$BT$3,BX$3,$M29:$BT29) -> 29400000 | BY29: =SUMIF($M$3:$BT$3,BY$3,$M29:$BT29) -> 37800000 | BZ29: =SUMIF($M$3:$BT$3,BZ$3,$M29:$BT29) -> 46200000
A30: Advetising/Marketing Expense Type 2 SMBs Focused | M30: 75000 | N30: 75000 | O30: 75000 | P30: 125000 | Q30: 125000 | R30: 125000 | S30: 250000 | T30: 250000 | U30: 250000 | V30: 375000 | W30: 375000 | X30: 375000 | Y30: 425000 | Z30: 425000 | AA30: 425000 | AB30: 500000 | AC30: 500000 | AD30: 500000 | AE30: 1000000 | AF30: 1000000 | AG30: 1000000 | AH30: 1100000 | AI30: 1100000 | AJ30: 1100000 | AK30: 1150000 | AL30: 1150000 | AM30: 1150000 | AN30: 1200000 | AO30: 1200000 | AP30: 1200000 | AQ30: 1250000 | AR30: 1250000 | AS30: 1250000 | AT30: 1300000 | AU30: 1300000 | AV30: 1300000 | AW30: =AV30+1300000 -> 2600000 | AX30: =AW30 -> 2600000 | AY30: =AX30 -> 2600000 | AZ30: =AY30+200000 -> 2800000 | BA30: =AZ30 -> 2800000 | BB30: =BA30 -> 2800000 | BC30: =BB30+200000 -> 3000000 | BD30: =BC30 -> 3000000 | BE30: =BD30 -> 3000000 | BF30: =BE30+200000 -> 3200000 | BG30: =BF30 -> 3200000 | BH30: =BG30 -> 3200000 | BI30: =BH30+800000 -> 4000000 | BJ30: =BI30 -> 4000000 | BK30: =BJ30 -> 4000000 | BL30: =BK30+100000 -> 4100000 | BM30: =BL30 -> 4100000 | BN30: =BM30 -> 4100000 | BO30: =BN30+100000 -> 4200000 | BP30: =BO30 -> 4200000 | BQ30: =BP30 -> 4200000 | BR30: =BQ30+100000 -> 4300000 | BS30: =BR30 -> 4300000 | BT30: =BS30 -> 4300000
A31: Cost/Lead Type 1 | G31: 2000 | H31: =G31 -> 2000 | M31: =G31 -> 2000 | N31: =M31+($H31-$G31)/COUNT($N$4:$BT$4) -> 2000 | O31: =N31+($H31-$G31)/COUNT($N$4:$BT$4) -> 2000 | P31: =O31+($H31-$G31)/COUNT($N$4:$BT$4) -> 2000 | Q31: =P31+($H31-$G31)/COUNT($N$4:$BT$4) -> 2000 | R31: =Q31+($H31-$G31)/COUNT($N$4:$BT$4) -> 2000 | S31: =R31+($H31-$G31)/COUNT($N$4:$BT$4) -> 2000 | T31: =S31+($H31-$G31)/COUNT($N$4:$BT$4) -> 2000 | U31: =T31+($H31-$G31)/COUNT($N$4:$BT$4) -> 2000 | ... BT31: =BS31+($H31-$G31)/COUNT($N$4:$BT$4) -> 2000
A32: Cost/Lead Type 2 | G32: 1000 | H32: =G32 -> 1000 | M32: =G32 -> 1000 | N32: =M32+($H32-$G32)/COUNT($N$4:$BT$4) -> 1000 | O32: =N32+($H32-$G32)/COUNT($N$4:$BT$4) -> 1000 | P32: =O32+($H32-$G32)/COUNT($N$4:$BT$4) -> 1000 | Q32: =P32+($H32-$G32)/COUNT($N$4:$BT$4) -> 1000 | R32: =Q32+($H32-$G32)/COUNT($N$4:$BT$4) -> 1000 | S32: =R32+($H32-$G32)/COUNT($N$4:$BT$4) -> 1000 | T32: =S32+($H32-$G32)/COUNT($N$4:$BT$4) -> 1000 | U32: =T32+($H32-$G32)/COUNT($N$4:$BT$4) -> 1000 | ... BT32: =BS32+($H32-$G32)/COUNT($N$4:$BT$4) -> 1000
A33: Sales Commission %
A34: New Bookings | F34: as a % repective bookings | G34: 0.1 | H34: =G34 -> 0.1 | M34: =G34 -> 0.1 | N34: =M34+($H34-$G34)/COUNT($N$4:$BT$4) -> 0.1 | O34: =N34+($H34-$G34)/COUNT($N$4:$BT$4) -> 0.1 | P34: =O34+($H34-$G34)/COUNT($N$4:$BT$4) -> 0.1 | Q34: =P34+($H34-$G34)/COUNT($N$4:$BT$4) -> 0.1 | R34: =Q34+($H34-$G34)/COUNT($N$4:$BT$4) -> 0.1 | S34: =R34+($H34-$G34)/COUNT($N$4:$BT$4) -> 0.1 | T34: =S34+($H34-$G34)/COUNT($N$4:$BT$4) -> 0.1 | U34: =T34+($H34-$G34)/COUNT($N$4:$BT$4) -> 0.1 | ... BT34: =BS34+($H34-$G34)/COUNT($N$4:$BT$4) -> 0.1
A35: Renewals | F35: as a % repective bookings | G35: 0.025 | H35: =G35 -> 0.025 | M35: =G35 -> 0.025 | N35: =M35+($H35-$G35)/COUNT($N$4:$BT$4) -> 0.025 | O35: =N35+($H35-$G35)/COUNT($N$4:$BT$4) -> 0.025 | P35: =O35+($H35-$G35)/COUNT($N$4:$BT$4) -> 0.025 | Q35: =P35+($H35-$G35)/COUNT($N$4:$BT$4) -> 0.025 | R35: =Q35+($H35-$G35)/COUNT($N$4:$BT$4) -> 0.025 | S35: =R35+($H35-$G35)/COUNT($N$4:$BT$4) -> 0.025 | T35: =S35+($H35-$G35)/COUNT($N$4:$BT$4) -> 0.025 | U35: =T35+($H35-$G35)/COUNT($N$4:$BT$4) -> 0.025 | ... BT35: =BS35+($H35-$G35)/COUNT($N$4:$BT$4) -> 0.025
A36: Expansion | F36: as a % repective bookings | G36: 0.05 | H36: =G36 -> 0.05 | M36: =G36 -> 0.05 | N36: =M36+($H36-$G36)/COUNT($N$4:$BT$4) -> 0.05 | O36: =N36+($H36-$G36)/COUNT($N$4:$BT$4) -> 0.05 | P36: =O36+($H36-$G36)/COUNT($N$4:$BT$4) -> 0.05 | Q36: =P36+($H36-$G36)/COUNT($N$4:$BT$4) -> 0.05 | R36: =Q36+($H36-$G36)/COUNT($N$4:$BT$4) -> 0.05 | S36: =R36+($H36-$G36)/COUNT($N$4:$BT$4) -> 0.05 | T36: =S36+($H36-$G36)/COUNT($N$4:$BT$4) -> 0.05 | U36: =T36+($H36-$G36)/COUNT($N$4:$BT$4) -> 0.05 | ... BT36: =BS36+($H36-$G36)/COUNT($N$4:$BT$4) -> 0.05
A37: Headcount
A38: Sales (SDR) | F38: Leads/Sales Agent/Month | G38: 50 | H38: =G38 -> 50 | M38: =G38 -> 50 | N38: =M38+($H38-$G38)/COUNT($N$4:$BT$4) -> 50 | O38: =N38+($H38-$G38)/COUNT($N$4:$BT$4) -> 50 | P38: =O38+($H38-$G38)/COUNT($N$4:$BT$4) -> 50 | Q38: =P38+($H38-$G38)/COUNT($N$4:$BT$4) -> 50 | R38: =Q38+($H38-$G38)/COUNT($N$4:$BT$4) -> 50 | S38: =R38+($H38-$G38)/COUNT($N$4:$BT$4) -> 50 | T38: =S38+($H38-$G38)/COUNT($N$4:$BT$4) -> 50 | U38: =T38+($H38-$G38)/COUNT($N$4:$BT$4) -> 50 | ... BT38: =BS38+($H38-$G38)/COUNT($N$4:$BT$4) -> 50
A39: Sales Manager | F39: Sales Agents/Sales Manager | G39: 10 | H39: =G39 -> 10 | M39: =G39 -> 10 | N39: =M39+($H39-$G39)/COUNT($N$4:$BT$4) -> 10 | O39: =N39+($H39-$G39)/COUNT($N$4:$BT$4) -> 10 | P39: =O39+($H39-$G39)/COUNT($N$4:$BT$4) -> 10 | Q39: =P39+($H39-$G39)/COUNT($N$4:$BT$4) -> 10 | R39: =Q39+($H39-$G39)/COUNT($N$4:$BT$4) -> 10 | S39: =R39+($H39-$G39)/COUNT($N$4:$BT$4) -> 10 | T39: =S39+($H39-$G39)/COUNT($N$4:$BT$4) -> 10 | U39: =T39+($H39-$G39)/COUNT($N$4:$BT$4) -> 10 | ... BT39: =BS39+($H39-$G39)/COUNT($N$4:$BT$4) -> 10
A40: Sales Team Salary
A41: Sales (SDR) | F41: Monthly Salary/Headcount | G41: 50000 | H41: 0.15 | I41: Annual Increment
A42: Sales Manager | F42: Monthly Salary/Headcount | G42: 70000 | H42: 0.15 | I42: Annual Increment
A44: Marketing Team Roles & Headcount
A45: Head of Marketing | F45: Monthly Salary/Headcount | G45: 100000 | H45: 0.15 | I45: Annual Increment | M45: 0 | N45: =M45 -> 0 | O45: =N45 -> 0 | P45: =O45 -> 0 | Q45: =P45 -> 0 | R45: =Q45 -> 0 | S45: =R45 -> 0 | T45: =S45 -> 0 | U45: =T45 -> 0 | ... AD45: =AC45 -> 0 | AE45: 1 | AF45: =AE45 -> 1 | AG45: =AF45 -> 1 | AH45: =AG45 -> 1 | AI45: =AH45 -> 1 | AJ45: =AI45 -> 1 | AK45: 1 | AL45: =AK45 -> 1 | AM45: =AL45 -> 1 | AN45: =AM45 -> 1 | AO45: =AN45 -> 1 | AP45: =AO45 -> 1 | AQ45: =AP45 -> 1 | AR45: =AQ45 -> 1 | AS45: =AR45 -> 1 | ... BT45: =BS45 -> 1
A46: Growth | F46: Monthly Salary/Headcount | G46: 75000 | H46: 0.15 | I46: Annual Increment | M46: 1 | N46: =M46 -> 1 | O46: =N46 -> 1 | P46: =O46 -> 1 | Q46: =P46 -> 1 | R46: =Q46 -> 1 | S46: =R46 -> 1 | T46: =S46 -> 1 | U46: =T46 -> 1 | ... X46: =W46 -> 1 | Y46: 2 | Z46: =Y46 -> 2 | AA46: =Z46 -> 2 | AB46: =AA46 -> 2 | AC46: =AB46 -> 2 | AD46: =AC46 -> 2 | AE46: =AD46 -> 2 | AF46: =AE46 -> 2 | AG46: =AF46 -> 2 | ... AJ46: =AI46 -> 2 | AK46: 4 | AL46: =AK46 -> 4 | AM46: =AL46 -> 4 | AN46: =AM46 -> 4 | AO46: =AN46 -> 4 | AP46: =AO46 -> 4 | AQ46: =AP46 -> 4 | AR46: =AQ46 -> 4 | AS46: =AR46 -> 4 | ... BT46: =BS46 -> 4
A47: Branding | F47: Monthly Salary/Headcount | G47: 50000 | H47: 0.15 | I47: Annual Increment | M47: 0 | N47: =M47 -> 0 | O47: =N47 -> 0 | P47: =O47 -> 0 | Q47: =P47 -> 0 | R47: =Q47 -> 0 | S47: =R47 -> 0 | T47: =S47 -> 0 | U47: =T47 -> 0 | ... AD47: =AC47 -> 0 | AE47: 1 | AF47: =AE47 -> 1 | AG47: =AF47 -> 1 | AH47: =AG47 -> 1 | AI47: =AH47 -> 1 | AJ47: =AI47 -> 1 | AK47: 2 | AL47: =AK47 -> 2 | AM47: =AL47 -> 2 | AN47: =AM47 -> 2 | AO47: =AN47 -> 2 | AP47: =AO47 -> 2 | AQ47: =AP47 -> 2 | AR47: =AQ47 -> 2 | AS47: =AR47 -> 2 | ... BT47: =BS47 -> 2
A48: Content & Creative | F48: Monthly Salary/Headcount | G48: 50000 | H48: 0.15 | I48: Annual Increment | M48: 1 | N48: =M48 -> 1 | O48: =N48 -> 1 | P48: =O48 -> 1 | Q48: =P48 -> 1 | R48: =Q48 -> 1 | S48: =R48 -> 1 | T48: =S48 -> 1 | U48: =T48 -> 1 | ... AD48: =AC48 -> 1 | AE48: 2 | AF48: =AE48 -> 2 | AG48: =AF48 -> 2 | AH48: =AG48 -> 2 | AI48: =AH48 -> 2 | AJ48: =AI48 -> 2 | AK48: 3 | AL48: =AK48 -> 3 | AM48: =AL48 -> 3 | AN48: =AM48 -> 3 | AO48: =AN48 -> 3 | AP48: =AO48 -> 3 | AQ48: =AP48 -> 3 | AR48: =AQ48 -> 3 | AS48: =AR48 -> 3 | ... BT48: =BS48 -> 3
A49: G&A
A50: Office Rent | F50: Chair/Empoloyee/Monthly | G50: 7000 | H50: =G50*(1+6%)^5 -> 9367.579 | M50: =G50 -> 7000 | N50: =M50+($H50-$G50)/COUNT($N$4:$BT$4) -> 7040.1285 | O50: =N50+($H50-$G50)/COUNT($N$4:$BT$4) -> 7080.2569 | P50: =O50+($H50-$G50)/COUNT($N$4:$BT$4) -> 7120.3854 | Q50: =P50+($H50-$G50)/COUNT($N$4:$BT$4) -> 7160.5138 | R50: =Q50+($H50-$G50)/COUNT($N$4:$BT$4) -> 7200.6423 | S50: =R50+($H50-$G50)/COUNT($N$4:$BT$4) -> 7240.7708 | T50: =S50+($H50-$G50)/COUNT($N$4:$BT$4) -> 7280.8992 | U50: =T50+($H50-$G50)/COUNT($N$4:$BT$4) -> 7321.0277 | ... BT50: =BS50+($H50-$G50)/COUNT($N$4:$BT$4) -> 9367.579 | BV50: =SUMIF($M$3:$BT$3,BV$3,$M50:$BT50) -> 86648.478 | BW50: =SUMIF($M$3:$BT$3,BW$3,$M50:$BT50) -> 92426.976 | BX50: =SUMIF($M$3:$BT$3,BX$3,$M50:$BT50) -> 98205.474 | BY50: =SUMIF($M$3:$BT$3,BY$3,$M50:$BT50) -> 103983.97 | BZ50: =SUMIF($M$3:$BT$3,BZ$3,$M50:$BT50) -> 109762.47
A51: Utilities | F51: Emp/Monthly | G51: 2000 | H51: =G51*(1+6%)^5 -> 2676.4512 | M51: =G51 -> 2000 | N51: =M51+($H51-$G51)/COUNT($N$4:$BT$4) -> 2011.4653 | O51: =N51+($H51-$G51)/COUNT($N$4:$BT$4) -> 2022.9305 | P51: =O51+($H51-$G51)/COUNT($N$4:$BT$4) -> 2034.3958 | Q51: =P51+($H51-$G51)/COUNT($N$4:$BT$4) -> 2045.8611 | R51: =Q51+($H51-$G51)/COUNT($N$4:$BT$4) -> 2057.3264 | S51: =R51+($H51-$G51)/COUNT($N$4:$BT$4) -> 2068.7916 | T51: =S51+($H51-$G51)/COUNT($N$4:$BT$4) -> 2080.2569 | U51: =T51+($H51-$G51)/COUNT($N$4:$BT$4) -> 2091.7222 | ... BT51: =BS51+($H51-$G51)/COUNT($N$4:$BT$4) -> 2676.4512 | BV51: =SUMIF($M$3:$BT$3,BV$3,$M51:$BT51) -> 24756.708 | BW51: =SUMIF($M$3:$BT$3,BW$3,$M51:$BT51) -> 26407.708 | BX51: =SUMIF($M$3:$BT$3,BX$3,$M51:$BT51) -> 28058.707 | BY51: =SUMIF($M$3:$BT$3,BY$3,$M51:$BT51) -> 29709.706 | BZ51: =SUMIF($M$3:$BT$3,BZ$3,$M51:$BT51) -> 31360.706
A52: G&A Team Roles & Headcount
A53: Account & Finance | F53: Monthly Salary/Headcount | G53: 40000 | H53: 0.15 | I53: Annual Increment | M53: 1 | N53: =M53 -> 1 | O53: =N53 -> 1 | P53: =O53 -> 1 | Q53: =P53 -> 1 | R53: =Q53 -> 1 | S53: =R53 -> 1 | T53: =S53 -> 1 | U53: =T53 -> 1 | ... X53: =W53 -> 1 | Y53: 2 | Z53: =Y53 -> 2 | AA53: =Z53 -> 2 | AB53: =AA53 -> 2 | AC53: =AB53 -> 2 | AD53: =AC53 -> 2 | AE53: =AD53 -> 2 | AF53: =AE53 -> 2 | AG53: =AF53 -> 2 | ... BT53: =BS53 -> 2
A54: Legal | F54: Monthly Salary/Headcount | G54: 50000 | H54: 0.15 | I54: Annual Increment | M54: 0 | N54: =M54 -> 0 | O54: =N54 -> 0 | P54: =O54 -> 0 | Q54: =P54 -> 0 | R54: =Q54 -> 0 | S54: =R54 -> 0 | T54: =S54 -> 0 | U54: =T54 -> 0 | ... X54: =W54 -> 0 | Y54: 0 | Z54: =Y54 -> 0 | AA54: =Z54 -> 0 | AB54: =AA54 -> 0 | AC54: =AB54 -> 0 | AD54: =AC54 -> 0 | AE54: =AD54 -> 0 | AF54: =AE54 -> 0 | AG54: =AF54 -> 0 | ... AJ54: =AI54 -> 0 | AK54: 1 | AL54: =AK54 -> 1 | AM54: =AL54 -> 1 | AN54: =AM54 -> 1 | AO54: =AN54 -> 1 | AP54: =AO54 -> 1 | AQ54: =AP54 -> 1 | AR54: =AQ54 -> 1 | AS54: =AR54 -> 1 | ... BT54: =BS54 -> 1
A55: HR | F55: Monthly Salary/Headcount | G55: 60000 | H55: 0.15 | I55: Annual Increment | M55: 0 | N55: =M55 -> 0 | O55: =N55 -> 0 | P55: =O55 -> 0 | Q55: =P55 -> 0 | R55: =Q55 -> 0 | S55: =R55 -> 0 | T55: =S55 -> 0 | U55: =T55 -> 0 | ... X55: =W55 -> 0 | Y55: 1 | Z55: =Y55 -> 1 | AA55: =Z55 -> 1 | AB55: =AA55 -> 1 | AC55: =AB55 -> 1 | AD55: =AC55 -> 1 | AE55: =AD55 -> 1 | AF55: =AE55 -> 1 | AG55: =AF55 -> 1 | ... AJ55: =AI55 -> 1 | AK55: 2 | AL55: =AK55 -> 2 | AM55: =AL55 -> 2 | AN55: =AM55 -> 2 | AO55: =AN55 -> 2 | AP55: =AO55 -> 2 | AQ55: =AP55 -> 2 | AR55: =AQ55 -> 2 | AS55: =AR55 -> 2 | ... BT55: =BS55 -> 2
A56: Product Development Expense
A57: Infrastructure | G57: 10000 | H57: =G57*10 -> 100000 | M57: =G57 -> 10000 | N57: =M57+($H57-$G57)/COUNT($N$4:$BT$4) -> 11525.424 | O57: =N57+($H57-$G57)/COUNT($N$4:$BT$4) -> 13050.847 | P57: =O57+($H57-$G57)/COUNT($N$4:$BT$4) -> 14576.271 | Q57: =P57+($H57-$G57)/COUNT($N$4:$BT$4) -> 16101.695 | R57: =Q57+($H57-$G57)/COUNT($N$4:$BT$4) -> 17627.119 | S57: =R57+($H57-$G57)/COUNT($N$4:$BT$4) -> 19152.542 | T57: =S57+($H57-$G57)/COUNT($N$4:$BT$4) -> 20677.966 | U57: =T57+($H57-$G57)/COUNT($N$4:$BT$4) -> 22203.39 | ... BT57: =BS57+($H57-$G57)/COUNT($N$4:$BT$4) -> 100000 | BV57: =SUMIF($M$3:$BT$3,BV$3,$M57:$BT57) -> 220677.97 | BW57: =SUMIF($M$3:$BT$3,BW$3,$M57:$BT57) -> 440338.98 | BX57: =SUMIF($M$3:$BT$3,BX$3,$M57:$BT57) -> 660000 | BY57: =SUMIF($M$3:$BT$3,BY$3,$M57:$BT57) -> 879661.02 | BZ57: =SUMIF($M$3:$BT$3,BZ$3,$M57:$BT57) -> 1099322
A58: Product Development Team Roles & Headcount
A59: Product Developemt Team | F59: Monthly Salary/Headcount | G59: 60000 | H59: 0.15 | I59: Annual Increment | M59: 4 | N59: =M59 -> 4 | O59: =N59 -> 4 | P59: =O59 -> 4 | Q59: =P59 -> 4 | R59: =Q59 -> 4 | S59: 5 | T59: =S59 -> 5 | U59: =T59 -> 5 | V59: =U59 -> 5 | W59: =V59 -> 5 | X59: =W59 -> 5 | Y59: 7 | Z59: =Y59 -> 7 | AA59: =Z59 -> 7 | AB59: =AA59 -> 7 | AC59: =AB59 -> 7 | AD59: =AC59 -> 7 | AE59: =AD59 -> 7 | AF59: =AE59 -> 7 | AG59: =AF59 -> 7 | ... AJ59: =AI59 -> 7 | AK59: 10 | AL59: =AK59 -> 10 | AM59: =AL59 -> 10 | AN59: =AM59 -> 10 | AO59: =AN59 -> 10 | AP59: =AO59 -> 10 | AQ59: =AP59 -> 10 | AR59: =AQ59 -> 10 | AS59: =AR59 -> 10 | ... BT59: =BS59 -> 10

Sheet Revenue Buildup
A1: Revenue Buildup
A2: Cells in Orange are assumptions | M2: MONTHLY | BV2: YEARLY
A3: Year | M3: 1 | N3: 1 | O3: 1 | P3: 1 | Q3: 1 | R3: 1 | S3: 1 | T3: 1 | U3: 1 | V3: 1 | W3: 1 | X3: 1 | Y3: =X3+1 -> 2 | Z3: =Y3 -> 2 | AA3: =Z3 -> 2 | AB3: =AA3 -> 2 | AC3: =AB3 -> 2 | AD3: =AC3 -> 2 | AE3: =AD3 -> 2 | AF3: =AE3 -> 2 | AG3: =AF3 -> 2 | ... AJ3: =AI3 -> 2 | AK3: 3 | AL3: 3 | AM3: 3 | AN3: 3 | AO3: 3 | AP3: 3 | AQ3: 3 | AR3: 3 | AS3: 3 | AT3: 3 | AU3: 3 | AV3: 3 | AW3: 4 | AX3: 4 | AY3: 4 | AZ3: 4 | BA3: 4 | BB3: 4 | BC3: 4 | BD3: 4 | BE3: 4 | BF3: 4 | BG3: 4 | BH3: 4 | BI3: 5 | BJ3: 5 | BK3: 5 | BL3: 5 | BM3: 5 | BN3: 5 | BO3: 5 | BP3: 5 | BQ3: 5 | BR3: 5 | BS3: 5 | BT3: 5 | BV3: 1 | BW3: 2 | BX3: 3 | BY3: 4 | BZ3: 5
A4: Months | M4: 1 | N4: =M4+1 -> 2 | O4: =N4+1 -> 3 | P4: =O4+1 -> 4 | Q4: =P4+1 -> 5 | R4: =Q4+1 -> 6 | S4: =R4+1 -> 7 | T4: =S4+1 -> 8 | U4: =T4+1 -> 9 | ... BT4: =BS4+1 -> 60 | BV4: 12 | BW4: 24 | BX4: 36 | BY4: 48 | BZ4: 60
A5: Type 1 SMB's
A6: Active Customers
A7: New Clients | M7: =ROUND('Cost Buildup'!M26*Assumptions!M6,0) -> 4 | N7: =ROUND('Cost Buildup'!N26*Assumptions!N6,0) -> 4 | O7: =ROUND('Cost Buildup'!O26*Assumptions!O6,0) -> 4 | P7: =ROUND('Cost Buildup'!P26*Assumptions!P6,0) -> 6 | Q7: =ROUND('Cost Buildup'!Q26*Assumptions!Q6,0) -> 6 | R7: =ROUND('Cost Buildup'!R26*Assumptions!R6,0) -> 6 | S7: =ROUND('Cost Buildup'!S26*Assumptions!S6,0) -> 13 | T7: =ROUND('Cost Buildup'!T26*Assumptions!T6,0) -> 13 | ... BT7: =ROUND('Cost Buildup'!BT26*Assumptions!BT6,0) -> 100 | BV7: =SUMIF($M$3:$BT$3,BV$3,$M7:$BT7) -> 126 | BW7: =SUMIF($M$3:$BT$3,BW$3,$M7:$BT7) -> 453 | BX7: =SUMIF($M$3:$BT$3,BX$3,$M7:$BT7) -> 738 | BY7: =SUMIF($M$3:$BT$3,BY$3,$M7:$BT7) -> 948 | BZ7: =SUMIF($M$3:$BT$3,BZ$3,$M7:$BT7) -> 1158
A8: Existing Clients | M8: 41 | N8: =M10 -> 45 | O8: =N10 -> 49 | P8: =O10 -> 53 | Q8: =P10 -> 59 | R8: =Q10 -> 65 | S8: =R10 -> 71 | T8: =S10 -> 84 | U8: =T10 -> 97 | ... BT8: =BS10 -> 2705 | BV8: =M8 -> 41 | BW8: =BV10 -> 167 | BX8: =BW10 -> 581 | BY8: =BX10 -> 1181 | BZ8: =BY10 -> 1907
A9: Churned | Y9: =-ROUND(M7*Assumptions!Y11,0) -> -1 | Z9: =-ROUND(N7*Assumptions!Z11,0) -> -1 | AA9: =-ROUND(O7*Assumptions!AA11,0) -> -1 | AB9: =-ROUND(P7*Assumptions!AB11,0) -> -2 | AC9: =-ROUND(Q7*Assumptions!AC11,0) -> -2 | AD9: =-ROUND(R7*Assumptions!AD11,0) -> -2 | AE9: =-ROUND(S7*Assumptions!AE11,0) -> -4 | AF9: =-ROUND(T7*Assumptions!AF11,0) -> -4 | ... BT9: =-ROUND(BH7*Assumptions!BT11,0) -> -25 | BV9: =SUMIF($M$3:$BT$3,BV$3,$M9:$BT9) -> 0 | BW9: =SUMIF($M$3:$BT$3,BW$3,$M9:$BT9) -> -39 | BX9: =SUMIF($M$3:$BT$3,BX$3,$M9:$BT9) -> -138 | BY9: =SUMIF($M$3:$BT$3,BY$3,$M9:$BT9) -> -222 | BZ9: =SUMIF($M$3:$BT$3,BZ$3,$M9:$BT9) -> -285
A10: Total Clinets | M10: =SUM(M7:M9) -> 45 | N10: =SUM(N7:N9) -> 49 | O10: =SUM(O7:O9) -> 53 | P10: =SUM(P7:P9) -> 59 | Q10: =SUM(Q7:Q9) -> 65 | R10: =SUM(R7:R9) -> 71 | S10: =SUM(S7:S9) -> 84 | T10: =SUM(T7:T9) -> 97 | ... BT10: =SUM(BT7:BT9) -> 2780 | BV10: =SUM(BV7:BV9) -> 167 | BW10: =SUM(BW7:BW9) -> 581 | BX10: =SUM(BX7:BX9) -> 1181 | BY10: =SUM(BY7:BY9) -> 1907 | BZ10: =SUM(BZ7:BZ9) -> 2780
A11: Bookings
A12: New Bookings | M12: =M7*Assumptions!M7 -> 480000 | N12: =N7*Assumptions!N7 -> 480000 | O12: =O7*Assumptions!O7 -> 480000 | P12: =P7*Assumptions!P7 -> 720000 | Q12: =Q7*Assumptions!Q7 -> 720000 | R12: =R7*Assumptions!R7 -> 720000 | S12: =S7*Assumptions!S7 -> 1560000 | T12: =T7*Assumptions!T7 -> 1560000 | ... BT12: =BT7*Assumptions!BT7 -> 12000000 | BV12: =SUMIF($M$3:$BT$3,BV$3,$M12:$BT12) -> 15120000 | BW12: =SUMIF($M$3:$BT$3,BW$3,$M12:$BT12) -> 54360000 | BX12: =SUMIF($M$3:$BT$3,BX$3,$M12:$BT12) -> 88560000 | BY12: =SUMIF($M$3:$BT$3,BY$3,$M12:$BT12) -> 113760000 | BZ12: =SUMIF($M$3:$BT$3,BZ$3,$M12:$BT12) -> 138960000
A13: Recurring Bookings
A14: Renewal | Y14: =(M7+Y9)*Assumptions!Y7 -> 360000 | Z14: =(N7+Z9)*Assumptions!Z7 -> 360000 | AA14: =(O7+AA9)*Assumptions!AA7 -> 360000 | AB14: =(P7+AB9)*Assumptions!AB7 -> 480000 | AC14: =(Q7+AC9)*Assumptions!AC7 -> 480000 | AD14: =(R7+AD9)*Assumptions!AD7 -> 480000 | AE14: =(S7+AE9)*Assumptions!AE7 -> 1080000 | AF14: =(T7+AF9)*Assumptions!AF7 -> 1080000 | ... BT14: =(BH7+BT9)*Assumptions!BT7 -> 6960000 | BV14: =SUMIF($M$3:$BT$3,BV$3,$M14:$BT14) -> 0 | BW14: =SUMIF($M$3:$BT$3,BW$3,$M14:$BT14) -> 10440000 | BX14: =SUMIF($M$3:$BT$3,BX$3,$M14:$BT14) -> 37800000 | BY14: =SUMIF($M$3:$BT$3,BY$3,$M14:$BT14) -> 61920000 | BZ14: =SUMIF($M$3:$BT$3,BZ$3,$M14:$BT14) -> 79560000
A15: Expansion | Y15: =Y14*Assumptions!Y13 -> 72000 | Z15: =Z14*Assumptions!Z13 -> 72000 | AA15: =AA14*Assumptions!AA13 -> 72000 | AB15: =AB14*Assumptions!AB13 -> 96000 | AC15: =AC14*Assumptions!AC13 -> 96000 | AD15: =AD14*Assumptions!AD13 -> 96000 | AE15: =AE14*Assumptions!AE13 -> 216000 | AF15: =AF14*Assumptions!AF13 -> 216000 | ... BT15: =BT14*Assumptions!BT13 -> 1392000 | BV15: =SUMIF($M$3:$BT$3,BV$3,$M15:$BT15) -> 0 | BW15: =SUMIF($M$3:$BT$3,BW$3,$M15:$BT15) -> 2088000 | BX15: =SUMIF($M$3:$BT$3,BX$3,$M15:$BT15) -> 7560000 | BY15: =SUMIF($M$3:$BT$3,BY$3,$M15:$BT15) -> 12384000 | BZ15: =SUMIF($M$3:$BT$3,BZ$3,$M15:$BT15) -> 15912000
A16: Total Recurring Bookings | M16: =SUM(M14:M15) -> 0 | N16: =SUM(N14:N15) -> 0 | O16: =SUM(O14:O15) -> 0 | P16: =SUM(P14:P15) -> 0 | Q16: =SUM(Q14:Q15) -> 0 | R16: =SUM(R14:R15) -> 0 | S16: =SUM(S14:S15) -> 0 | T16: =SUM(T14:T15) -> 0 | ... BT16: =SUM(BT14:BT15) -> 8352000 | BV16: =SUMIF($M$3:$BT$3,BV$3,$M16:$BT16) -> 0 | BW16: =SUMIF($M$3:$BT$3,BW$3,$M16:$BT16) -> 12528000 | BX16: =SUMIF($M$3:$BT$3,BX$3,$M16:$BT16) -> 45360000 | BY16: =SUMIF($M$3:$BT$3,BY$3,$M16:$BT16) -> 74304000 | BZ16: =SUMIF($M$3:$BT$3,BZ$3,$M16:$BT16) -> 95472000
A18: Total Bookings | M18: =M12+M16 -> 480000 | N18: =N12+N16 -> 480000 | O18: =O12+O16 -> 480000 | P18: =P12+P16 -> 720000 | Q18: =Q12+Q16 -> 720000 | R18: =R12+R16 -> 720000 | S18: =S12+S16 -> 1560000 | T18: =T12+T16 -> 1560000 | ... BT18: =BT12+BT16 -> 20352000 | BV18: =SUMIF($M$3:$BT$3,BV$3,$M18:$BT18) -> 15120000 | BW18: =SUMIF($M$3:$BT$3,BW$3,$M18:$BT18) -> 66888000 | BX18: =SUMIF($M$3:$BT$3,BX$3,$M18:$BT18) -> 133920000 | BY18: =SUMIF($M$3:$BT$3,BY$3,$M18:$BT18) -> 188064000 | BZ18: =SUMIF($M$3:$BT$3,BZ$3,$M18:$BT18) -> 234432000
A19: Revenue
A20: Revenue (MRR) | M20: =SUM('Revenue Buildup'!$M$18:M18)/Assumptions!M9 -> 40000 | N20: =SUM('Revenue Buildup'!$M$18:N18)/Assumptions!N9 -> 80000 | O20: =SUM('Revenue Buildup'!$M$18:O18)/Assumptions!O9 -> 120000 | P20: =SUM('Revenue Buildup'!$M$18:P18)/Assumptions!P9 -> 180000 | Q20: =SUM('Revenue Buildup'!$M$18:Q18)/Assumptions!Q9 -> 240000 | R20: =SUM('Revenue Buildup'!$M$18:R18)/Assumptions!R9 -> 300000 | S20: =SUM('Revenue Buildup'!$M$18:S18)/Assumptions!S9 -> 430000 | T20: =SUM('Revenue Buildup'!$M$18:T18)/Assumptions!T9 -> 560000 | ... W20: =SUM('Revenue Buildup'!$M$18:W18)/Assumptions!W9 -> 1070000 | X20: =SUM('Revenue Buildup'!M18:X18)/Assumptions!X9 -> 1260000 | Y20: =SUM('Revenue Buildup'!N18:Y18)/Assumptions!Y9 -> 1466000 | Z20: =SUM('Revenue Buildup'!O18:Z18)/Assumptions!Z9 -> 1672000 | AA20: =SUM('Revenue Buildup'!P18:AA18)/Assumptions!AA9 -> 1878000 | AB20: =SUM('Revenue Buildup'!Q18:AB18)/Assumptions!AB9 -> 2116000 | AC20: =SUM('Revenue Buildup'!R18:AC18)/Assumptions!AC9 -> 2354000 | AD20: =SUM('Revenue Buildup'!S18:AD18)/Assumptions!AD9 -> 2592000 | AE20: =SUM('Revenue Buildup'!T18:AE18)/Assumptions!AE9 -> 3070000 | ... BT20: =SUM('Revenue Buildup'!BI18:BT18)/Assumptions!BT9 -> 19536000 | BV20: =SUMIF($M$3:$BT$3,BV$3,$M20:$BT20) -> 5850000 | BW20: =SUMIF($M$3:$BT$3,BW$3,$M20:$BT20) -> 37896000 | BX20: =SUMIF($M$3:$BT$3,BX$3,$M20:$BT20) -> 105024000 | BY20: =SUMIF($M$3:$BT$3,BY$3,$M20:$BT20) -> 167100000 | BZ20: =SUMIF($M$3:$BT$3,BZ$3,$M20:$BT20) -> 213000000
A21: ARR | M21: =M20*12 -> 480000 | N21: =N20*12 -> 960000 | O21: =O20*12 -> 1440000 | P21: =P20*12 -> 2160000 | Q21: =Q20*12 -> 2880000 | R21: =R20*12 -> 3600000 | S21: =S20*12 -> 5160000 | T21: =T20*12 -> 6720000 | ... BT21: =BT20*12 -> 234432000
A22: Type 2 SMB's
A23: Active Customers
A24: New Clients | M24: =ROUND('Cost Buildup'!M27*Assumptions!M6,0) -> 4 | N24: =ROUND('Cost Buildup'!N27*Assumptions!N6,0) -> 4 | O24: =ROUND('Cost Buildup'!O27*Assumptions!O6,0) -> 4 | P24: =ROUND('Cost Buildup'!P27*Assumptions!P6,0) -> 6 | Q24: =ROUND('Cost Buildup'!Q27*Assumptions!Q6,0) -> 6 | R24: =ROUND('Cost Buildup'!R27*Assumptions!R6,0) -> 6 | S24: =ROUND('Cost Buildup'!S27*Assumptions!S6,0) -> 13 | T24: =ROUND('Cost Buildup'!T27*Assumptions!T6,0) -> 13 | ... BT24: =ROUND('Cost Buildup'!BT27*Assumptions!BT6,0) -> 215 | BV24: =SUMIF($M$3:$BT$3,BV$3,$M24:$BT24) -> 126 | BW24: =SUMIF($M$3:$BT$3,BW$3,$M24:$BT24) -> 453 | BX24: =SUMIF($M$3:$BT$3,BX$3,$M24:$BT24) -> 738 | BY24: =SUMIF($M$3:$BT$3,BY$3,$M24:$BT24) -> 1740 | BZ24: =SUMIF($M$3:$BT$3,BZ$3,$M24:$BT24) -> 2490
A25: Existing Clients | M25: 0 | N25: =M27 -> 4 | O25: =N27 -> 8 | P25: =O27 -> 12 | Q25: =P27 -> 18 | R25: =Q27 -> 24 | S25: =R27 -> 30 | T25: =S27 -> 43 | U25: =T27 -> 56 | ... BT25: =BS27 -> 5332 | BV25: =M25 -> 0 | BW25: =BV27 -> 126 | BX25: =BW27 -> 579 | BY25: =BX27 -> 1317 | BZ25: =BY27 -> 3057
A26: Churned | Y26: =-ROUND(M24*Assumptions!Y28,0) -> 0 | Z26: =-ROUND(N24*Assumptions!Z28,0) -> 0 | AA26: =-ROUND(O24*Assumptions!AA28,0) -> 0 | AB26: =-ROUND(P24*Assumptions!AB28,0) -> 0 | AC26: =-ROUND(Q24*Assumptions!AC28,0) -> 0 | AD26: =-ROUND(R24*Assumptions!AD28,0) -> 0 | AE26: =-ROUND(S24*Assumptions!AE28,0) -> 0 | AF26: =-ROUND(T24*Assumptions!AF28,0) -> 0 | ... BT26: =-ROUND(BH24*Assumptions!BT28,0) -> 0 | BV26: =SUMIF($M$3:$BT$3,BV$3,$M26:$BT26) -> 0 | BW26: =SUMIF($M$3:$BT$3,BW$3,$M26:$BT26) -> 0 | BX26: =SUMIF($M$3:$BT$3,BX$3,$M26:$BT26) -> 0 | BY26: =SUMIF($M$3:$BT$3,BY$3,$M26:$BT26) -> 0 | BZ26: =SUMIF($M$3:$BT$3,BZ$3,$M26:$BT26) -> 0
A27: Total Clinets | M27: =SUM(M24:M26) -> 4 | N27: =SUM(N24:N26) -> 8 | O27: =SUM(O24:O26) -> 12 | P27: =SUM(P24:P26) -> 18 | Q27: =SUM(Q24:Q26) -> 24 | R27: =SUM(R24:R26) -> 30 | S27: =SUM(S24:S26) -> 43 | T27: =SUM(T24:T26) -> 56 | ... BT27: =SUM(BT24:BT26) -> 5547 | BV27: =SUM(BV24:BV26) -> 126 | BW27: =SUM(BW24:BW26) -> 579 | BX27: =SUM(BX24:BX26) -> 1317 | BY27: =SUM(BY24:BY26) -> 3057 | BZ27: =SUM(BZ24:BZ26) -> 5547
A28: Bookings
A29: New Bookings | M29: =M24*Assumptions!M8 -> 240000 | N29: =N24*Assumptions!N8 -> 240000 | O29: =O24*Assumptions!O8 -> 240000 | P29: =P24*Assumptions!P8 -> 360000 | Q29: =Q24*Assumptions!Q8 -> 360000 | R29: =R24*Assumptions!R8 -> 360000 | S29: =S24*Assumptions!S8 -> 780000 | T29: =T24*Assumptions!T8 -> 780000 | ... BT29: =BT24*Assumptions!BT8 -> 12900000 | BV29: =SUMIF($M$3:$BT$3,BV$3,$M29:$BT29) -> 7560000 | BW29: =SUMIF($M$3:$BT$3,BW$3,$M29:$BT29) -> 27180000 | BX29: =SUMIF($M$3:$BT$3,BX$3,$M29:$BT29) -> 44280000 | BY29: =SUMIF($M$3:$BT$3,BY$3,$M29:$BT29) -> 104400000 | BZ29: =SUMIF($M$3:$BT$3,BZ$3,$M29:$BT29) -> 149400000
A30: Recurring Bookings
A31: Renewal | Y31: =(M24+Y26)*Assumptions!Y8 -> 240000 | Z31: =(N24+Z26)*Assumptions!Z8 -> 240000 | AA31: =(O24+AA26)*Assumptions!AA8 -> 240000 | AB31: =(P24+AB26)*Assumptions!AB8 -> 360000 | AC31: =(Q24+AC26)*Assumptions!AC8 -> 360000 | AD31: =(R24+AD26)*Assumptions!AD8 -> 360000 | AE31: =(S24+AE26)*Assumptions!AE8 -> 780000 | AF31: =(T24+AF26)*Assumptions!AF8 -> 780000 | ... BT31: =(BH24+BT26)*Assumptions!BT8 -> 9600000 | BV31: =SUMIF($M$3:$BT$3,BV$3,$M31:$BT31) -> 0 | BW31: =SUMIF($M$3:$BT$3,BW$3,$M31:$BT31) -> 7560000 | BX31: =SUMIF($M$3:$BT$3,BX$3,$M31:$BT31) -> 27180000 | BY31: =SUMIF($M$3:$BT$3,BY$3,$M31:$BT31) -> 44280000 | BZ31: =SUMIF($M$3:$BT$3,BZ$3,$M31:$BT31) -> 104400000
A32: Expansion | Y32: =Y31*Assumptions!Y13 -> 48000 | Z32: =Z31*Assumptions!Z13 -> 48000 | AA32: =AA31*Assumptions!AA13 -> 48000 | AB32: =AB31*Assumptions!AB13 -> 72000 | AC32: =AC31*Assumptions!AC13 -> 72000 | AD32: =AD31*Assumptions!AD13 -> 72000 | AE32: =AE31*Assumptions!AE13 -> 156000 | AF32: =AF31*Assumptions!AF13 -> 156000 | ... BT32: =BT31*Assumptions!BT13 -> 1920000 | BV32: =SUMIF($M$3:$BT$3,BV$3,$M32:$BT32) -> 0 | BW32: =SUMIF($M$3:$BT$3,BW$3,$M32:$BT32) -> 1512000 | BX32: =SUMIF($M$3:$BT$3,BX$3,$M32:$BT32) -> 5436000 | BY32: =SUMIF($M$3:$BT$3,BY$3,$M32:$BT32) -> 8856000 | BZ32: =SUMIF($M$3:$BT$3,BZ$3,$M32:$BT32) -> 20880000
A33: Total Recurring Bookings | M33: =SUM(M31:M32) -> 0 | N33: =SUM(N31:N32) -> 0 | O33: =SUM(O31:O32) -> 0 | P33: =SUM(P31:P32) -> 0 | Q33: =SUM(Q31:Q32) -> 0 | R33: =SUM(R31:R32) -> 0 | S33: =SUM(S31:S32) -> 0 | T33: =SUM(T31:T32) -> 0 | ... BT33: =SUM(BT31:BT32) -> 11520000 | BV33: =SUMIF($M$3:$BT$3,BV$3,$M33:$BT33) -> 0 | BW33: =SUMIF($M$3:$BT$3,BW$3,$M33:$BT33) -> 9072000 | BX33: =SUMIF($M$3:$BT$3,BX$3,$M33:$BT33) -> 32616000 | BY33: =SUMIF($M$3:$BT$3,BY$3,$M33:$BT33) -> 53136000 | BZ33: =SUMIF($M$3:$BT$3,BZ$3,$M33:$BT33) -> 125280000
A35: Total Bookings | M35: =M29+M33 -> 240000 | N35: =N29+N33 -> 240000 | O35: =O29+O33 -> 240000 | P35: =P29+P33 -> 360000 | Q35: =Q29+Q33 -> 360000 | R35: =R29+R33 -> 360000 | S35: =S29+S33 -> 780000 | T35: =T29+T33 -> 780000 | ... BT35: =BT29+BT33 -> 24420000 | BV35: =SUMIF($M$3:$BT$3,BV$3,$M35:$BT35) -> 7560000 | BW35: =SUMIF($M$3:$BT$3,BW$3,$M35:$BT35) -> 36252000 | BX35: =SUMIF($M$3:$BT$3,BX$3,$M35:$BT35) -> 76896000 | BY35: =SUMIF($M$3:$BT$3,BY$3,$M35:$BT35) -> 157536000 | BZ35: =SUMIF($M$3:$BT$3,BZ$3,$M35:$BT35) -> 274680000
A36: Revenue
A37: Revenue (MRR) | M37: =SUM('Revenue Buildup'!$M35:M$35)/Assumptions!M9 -> 20000 | N37: =SUM('Revenue Buildup'!$M35:N$35)/Assumptions!N9 -> 40000 | O37: =SUM('Revenue Buildup'!$M35:O$35)/Assumptions!O9 -> 60000 | P37: =SUM('Revenue Buildup'!$M35:P$35)/Assumptions!P9 -> 90000 | Q37: =SUM('Revenue Buildup'!$M35:Q$35)/Assumptions!Q9 -> 120000 | R37: =SUM('Revenue Buildup'!$M35:R$35)/Assumptions!R9 -> 150000 | S37: =SUM('Revenue Buildup'!$M35:S$35)/Assumptions!S9 -> 215000 | T37: =SUM('Revenue Buildup'!$M35:T$35)/Assumptions!T9 -> 280000 | ... W37: =SUM('Revenue Buildup'!$M35:W$35)/Assumptions!W9 -> 535000 | X37: =SUM('Revenue Buildup'!M35:X35)/Assumptions!X9 -> 630000 | Y37: =SUM('Revenue Buildup'!N35:Y35)/Assumptions!Y9 -> 739000 | Z37: =SUM('Revenue Buildup'!O35:Z35)/Assumptions!Z9 -> 848000 | AA37: =SUM('Revenue Buildup'!P35:AA35)/Assumptions!AA9 -> 957000 | AB37: =SUM('Revenue Buildup'!Q35:AB35)/Assumptions!AB9 -> 1088000 | AC37: =SUM('Revenue Buildup'!R35:AC35)/Assumptions!AC9 -> 1219000 | AD37: =SUM('Revenue Buildup'!S35:AD35)/Assumptions!AD9 -> 1350000 | AE37: =SUM('Revenue Buildup'!T35:AE35)/Assumptions!AE9 -> 1613000 | ... BT37: =SUM('Revenue Buildup'!BI35:BT35)/Assumptions!BT9 -> 22890000 | BV37: =SUMIF($M$3:$BT$3,BV$3,$M37:$BT37) -> 2925000 | BW37: =SUMIF($M$3:$BT$3,BW$3,$M37:$BT37) -> 20010000 | BX37: =SUMIF($M$3:$BT$3,BX$3,$M37:$BT37) -> 58560000 | BY37: =SUMIF($M$3:$BT$3,BY$3,$M37:$BT37) -> 121647000 | BZ37: =SUMIF($M$3:$BT$3,BZ$3,$M37:$BT37) -> 220062000
A38: ARR | M38: =M37*12 -> 240000 | N38: =N37*12 -> 480000 | O38: =O37*12 -> 720000 | P38: =P37*12 -> 1080000 | Q38: =Q37*12 -> 1440000 | R38: =R37*12 -> 1800000 | S38: =S37*12 -> 2580000 | T38: =T37*12 -> 3360000 | ... BT38: =BT37*12 -> 274680000
A39: Type 1 & 2 SMBs
A40: New Clients | M40: =M7+M24 -> 8 | N40: =N7+N24 -> 8 | O40: =O7+O24 -> 8 | P40: =P7+P24 -> 12 | Q40: =Q7+Q24 -> 12 | R40: =R7+R24 -> 12 | S40: =S7+S24 -> 26 | T40: =T7+T24 -> 26 | ... BT40: =BT7+BT24 -> 315
A41: Existing Clients | M41: =M8+M25 -> 41 | N41: =M43 -> 49 | O41: =N43 -> 57 | P41: =O43 -> 65 | Q41: =P43 -> 77 | R41: =Q43 -> 89 | S41: =R43 -> 101 | T41: =S43 -> 127 | U41: =T43 -> 153 | ... BT41: =BS43 -> 8037
A42: Churned | Y42: =Y9+Y26 -> -1 | Z42: =Z9+Z26 -> -1 | AA42: =AA9+AA26 -> -1 | AB42: =AB9+AB26 -> -2 | AC42: =AC9+AC26 -> -2 | AD42: =AD9+AD26 -> -2 | AE42: =AE9+AE26 -> -4 | AF42: =AF9+AF26 -> -4 | ... BT42: =BT9+BT26 -> -25
A43: Total Clinets | M43: =SUM(M40:M42) -> 49 | N43: =SUM(N40:N42) -> 57 | O43: =SUM(O40:O42) -> 65 | P43: =SUM(P40:P42) -> 77 | Q43: =SUM(Q40:Q42) -> 89 | R43: =SUM(R40:R42) -> 101 | S43: =SUM(S40:S42) -> 127 | T43: =SUM(T40:T42) -> 153 | ... BT43: =SUM(BT40:BT42) -> 8327
A44: Bookings
A45: New Bookings | M45: =M12+M29 -> 720000 | N45: =N12+N29 -> 720000 | O45: =O12+O29 -> 720000 | P45: =P12+P29 -> 1080000 | Q45: =Q12+Q29 -> 1080000 | R45: =R12+R29 -> 1080000 | S45: =S12+S29 -> 2340000 | T45: =T12+T29 -> 2340000 | ... BT45: =BT12+BT29 -> 24900000
A46: Recurring Bookings
A47: Renewal | Y47: =Y14+Y31 -> 600000 | Z47: =Z14+Z31 -> 600000 | AA47: =AA14+AA31 -> 600000 | AB47: =AB14+AB31 -> 840000 | AC47: =AC14+AC31 -> 840000 | AD47: =AD14+AD31 -> 840000 | AE47: =AE14+AE31 -> 1860000 | AF47: =AF14+AF31 -> 1860000 | ... BT47: =BT14+BT31 -> 16560000
A48: Expansion | Y48: =Y15+Y32 -> 120000 | Z48: =Z15+Z32 -> 120000 | AA48: =AA15+AA32 -> 120000 | AB48: =AB15+AB32 -> 168000 | AC48: =AC15+AC32 -> 168000 | AD48: =AD15+AD32 -> 168000 | AE48: =AE15+AE32 -> 372000 | AF48: =AF15+AF32 -> 372000 | ... BT48: =BT15+BT32 -> 3312000
A49: Total Recurring Bookings | M49: =SUM(M47:M48) -> 0 | N49: =SUM(N47:N48) -> 0 | O49: =SUM(O47:O48) -> 0 | P49: =SUM(P47:P48) -> 0 | Q49: =SUM(Q47:Q48) -> 0 | R49: =SUM(R47:R48) -> 0 | S49: =SUM(S47:S48) -> 0 | T49: =SUM(T47:T48) -> 0 | ... BT49: =SUM(BT47:BT48) -> 19872000
A51: Total Bookings | M51: =M45+M49 -> 720000 | N51: =N45+N49 -> 720000 | O51: =O45+O49 -> 720000 | P51: =P45+P49 -> 1080000 | Q51: =Q45+Q49 -> 1080000 | R51: =R45+R49 -> 1080000 | S51: =S45+S49 -> 2340000 | T51: =T45+T49 -> 2340000 | ... BT51: =BT45+BT49 -> 44772000
A52: Total MRR | M52: =M20+M37 -> 60000 | N52: =N20+N37 -> 120000 | O52: =O20+O37 -> 180000 | P52: =P20+P37 -> 270000 | Q52: =Q20+Q37 -> 360000 | R52: =R20+R37 -> 450000 | S52: =S20+S37 -> 645000 | T52: =T20+T37 -> 840000 | ... BT52: =BT20+BT37 -> 42426000 | BV52: =SUMIF($M$3:$BT$3,BV$3,$M52:$BT52) -> 8775000 | BW52: =SUMIF($M$3:$BT$3,BW$3,$M52:$BT52) -> 57906000 | BX52: =SUMIF($M$3:$BT$3,BX$3,$M52:$BT52) -> 163584000 | BY52: =SUMIF($M$3:$BT$3,BY$3,$M52:$BT52) -> 288747000 | BZ52: =SUMIF($M$3:$BT$3,BZ$3,$M52:$BT52) -> 433062000
A53: Total ARR | M53: =M52*12 -> 720000 | N53: =N52*12 -> 1440000 | O53: =O52*12 -> 2160000 | P53: =P52*12 -> 3240000 | Q53: =Q52*12 -> 4320000 | R53: =R52*12 -> 5400000 | S53: =S52*12 -> 7740000 | T53: =T52*12 -> 10080000 | ... BT53: =BT52*12 -> 509112000

Sheet Cost Buildup
A1: Cost Buildup
A2: Cells in Orange are assumptions | M2: MONTHLY | BV2: YEARLY
A3: Year | M3: 1 | N3: 1 | O3: 1 | P3: 1 | Q3: 1 | R3: 1 | S3: 1 | T3: 1 | U3: 1 | V3: 1 | W3: 1 | X3: 1 | Y3: =X3+1 -> 2 | Z3: =Y3 -> 2 | AA3: =Z3 -> 2 | AB3: =AA3 -> 2 | AC3: =AB3 -> 2 | AD3: =AC3 -> 2 | AE3: =AD3 -> 2 | AF3: =AE3 -> 2 | AG3: =AF3 -> 2 | ... AJ3: =AI3 -> 2 | AK3: 3 | AL3: 3 | AM3: 3 | AN3: 3 | AO3: 3 | AP3: 3 | AQ3: 3 | AR3: 3 | AS3: 3 | AT3: 3 | AU3: 3 | AV3: 3 | AW3: 4 | AX3: 4 | AY3: 4 | AZ3: 4 | BA3: 4 | BB3: 4 | BC3: 4 | BD3: 4 | BE3: 4 | BF3: 4 | BG3: 4 | BH3: 4 | BI3: 5 | BJ3: 5 | BK3: 5 | BL3: 5 | BM3: 5 | BN3: 5 | BO3: 5 | BP3: 5 | BQ3: 5 | BR3: 5 | BS3: 5 | BT3: 5 | BV3: 1 | BW3: 2 | BX3: 3 | BY3: 4 | BZ3: 5
A4: Months | M4: 1 | N4: =M4+1 -> 2 | O4: =N4+1 -> 3 | P4: =O4+1 -> 4 | Q4: =P4+1 -> 5 | R4: =Q4+1 -> 6 | S4: =R4+1 -> 7 | T4: =S4+1 -> 8 | U4: =T4+1 -> 9 | ... BT4: =BS4+1 -> 60 | BV4: 12 | BW4: 24 | BX4: 36 | BY4: 48 | BZ4: 60
A5: =Assumptions!A15 -> Direct Cost
A6: =Assumptions!A16 -> Hosting & Infrastructure Costs | M6: =SUM(M7:M9) -> 62580 | N6: =SUM(N7:N9) -> 71907.458 | O6: =SUM(O7:O9) -> 81234.915 | P6: =SUM(P7:P9) -> 90562.373 | Q6: =SUM(Q7:Q9) -> 99889.831 | R6: =SUM(R7:R9) -> 109217.29 | S6: =SUM(S7:S9) -> 118544.75 | T6: =SUM(T7:T9) -> 127872.2 | ... BT6: =SUM(BT7:BT9) -> 612900 | BV6: =SUMIF($M$3:$BT$3,BV$3,$M6:$BT6) -> 1366572.2 | BW6: =SUMIF($M$3:$BT$3,BW$3,$M6:$BT6) -> 2709726.1 | BX6: =SUMIF($M$3:$BT$3,BX$3,$M6:$BT6) -> 4052880 | BY6: =SUMIF($M$3:$BT$3,BY$3,$M6:$BT6) -> 5396033.9 | BZ6: =SUMIF($M$3:$BT$3,BZ$3,$M6:$BT6) -> 6739187.8
A7: =Assumptions!A17 -> Cloud services (AWS, Google Cloud, Azure) | M7: =Assumptions!M17 -> 50000 | N7: =Assumptions!N17 -> 57627.119 | O7: =Assumptions!O17 -> 65254.237 | P7: =Assumptions!P17 -> 72881.356 | Q7: =Assumptions!Q17 -> 80508.475 | R7: =Assumptions!R17 -> 88135.593 | S7: =Assumptions!S17 -> 95762.712 | T7: =Assumptions!T17 -> 103389.83 | ... BT7: =Assumptions!BT17 -> 500000 | BV7: =SUMIF($M$3:$BT$3,BV$3,$M7:$BT7) -> 1103389.8 | BW7: =SUMIF($M$3:$BT$3,BW$3,$M7:$BT7) -> 2201694.9 | BX7: =SUMIF($M$3:$BT$3,BX$3,$M7:$BT7) -> 3300000 | BY7: =SUMIF($M$3:$BT$3,BY$3,$M7:$BT7) -> 4398305.1 | BZ7: =SUMIF($M$3:$BT$3,BZ$3,$M7:$BT7) -> 5496610.2
A8: =Assumptions!A18 -> Database and storage (Amazon RDS, MongoDB Atlas) | M8: =Assumptions!M18 -> 10000 | N8: =Assumptions!N18 -> 11525.424 | O8: =Assumptions!O18 -> 13050.847 | P8: =Assumptions!P18 -> 14576.271 | Q8: =Assumptions!Q18 -> 16101.695 | R8: =Assumptions!R18 -> 17627.119 | S8: =Assumptions!S18 -> 19152.542 | T8: =Assumptions!T18 -> 20677.966 | ... BT8: =Assumptions!BT18 -> 100000 | BV8: =SUMIF($M$3:$BT$3,BV$3,$M8:$BT8) -> 220677.97 | BW8: =SUMIF($M$3:$BT$3,BW$3,$M8:$BT8) -> 440338.98 | BX8: =SUMIF($M$3:$BT$3,BX$3,$M8:$BT8) -> 660000 | BY8: =SUMIF($M$3:$BT$3,BY$3,$M8:$BT8) -> 879661.02 | BZ8: =SUMIF($M$3:$BT$3,BZ$3,$M8:$BT8) -> 1099322
A9: =Assumptions!A19 -> Content delivery networks (CDN) | M9: =Assumptions!M19 -> 2580 | N9: =Assumptions!N19 -> 2754.9153 | O9: =Assumptions!O19 -> 2929.8305 | P9: =Assumptions!P19 -> 3104.7458 | Q9: =Assumptions!Q19 -> 3279.661 | R9: =Assumptions!R19 -> 3454.5763 | S9: =Assumptions!S19 -> 3629.4915 | T9: =Assumptions!T19 -> 3804.4068 | ... BT9: =Assumptions!BT19 -> 12900 | BV9: =SUMIF($M$3:$BT$3,BV$3,$M9:$BT9) -> 42504.407 | BW9: =SUMIF($M$3:$BT$3,BW$3,$M9:$BT9) -> 67692.203 | BX9: =SUMIF($M$3:$BT$3,BX$3,$M9:$BT9) -> 92880 | BY9: =SUMIF($M$3:$BT$3,BY$3,$M9:$BT9) -> 118067.8 | BZ9: =SUMIF($M$3:$BT$3,BZ$3,$M9:$BT9) -> 143255.59
A10: =Assumptions!A20 -> Third-Party Software & API Costs | M10: =SUM(M11:M12) -> 12200 | N10: =SUM(N11:N12) -> 12538.983 | O10: =SUM(O11:O12) -> 12877.966 | P10: =SUM(P11:P12) -> 16816.949 | Q10: =SUM(Q11:Q12) -> 17155.932 | R10: =SUM(R11:R12) -> 17494.915 | S10: =SUM(S11:S12) -> 30433.898 | T10: =SUM(T11:T12) -> 30772.881 | ... BT10: =SUM(BT11:BT12) -> 330280 | BV10: =SUMIF($M$3:$BT$3,BV$3,$M10:$BT10) -> 309172.88 | BW10: =SUMIF($M$3:$BT$3,BW$3,$M10:$BT10) -> 1134506.4 | BX10: =SUMIF($M$3:$BT$3,BX$3,$M10:$BT10) -> 2188800 | BY10: =SUMIF($M$3:$BT$3,BY$3,$M10:$BT10) -> 3049773.6 | BZ10: =SUMIF($M$3:$BT$3,BZ$3,$M10:$BT10) -> 3794107.1
A11: =Assumptions!A21 -> Payment gateway fees (e.g., Stripe, Razorpay) | F11: =Assumptions!F21 -> as a % of bookings | M11: ='Revenue Buildup'!M18*Assumptions!M21 -> 7200 | N11: ='Revenue Buildup'!N18*Assumptions!N21 -> 7200 | O11: ='Revenue Buildup'!O18*Assumptions!O21 -> 7200 | P11: ='Revenue Buildup'!P18*Assumptions!P21 -> 10800 | Q11: ='Revenue Buildup'!Q18*Assumptions!Q21 -> 10800 | R11: ='Revenue Buildup'!R18*Assumptions!R21 -> 10800 | S11: ='Revenue Buildup'!S18*Assumptions!S21 -> 23400 | T11: ='Revenue Buildup'!T18*Assumptions!T21 -> 23400 | ... BT11: ='Revenue Buildup'!BT18*Assumptions!BT21 -> 305280 | BV11: =SUMIF($M$3:$BT$3,BV$3,$M11:$BT11) -> 226800 | BW11: =SUMIF($M$3:$BT$3,BW$3,$M11:$BT11) -> 1003320 | BX11: =SUMIF($M$3:$BT$3,BX$3,$M11:$BT11) -> 2008800 | BY11: =SUMIF($M$3:$BT$3,BY$3,$M11:$BT11) -> 2820960 | BZ11: =SUMIF($M$3:$BT$3,BZ$3,$M11:$BT11) -> 3516480
A12: =Assumptions!A22 -> Security services (e.g., Cloudflare, Auth0) | M12: =Assumptions!M22 -> 5000 | N12: =Assumptions!N22 -> 5338.9831 | O12: =Assumptions!O22 -> 5677.9661 | P12: =Assumptions!P22 -> 6016.9492 | Q12: =Assumptions!Q22 -> 6355.9322 | R12: =Assumptions!R22 -> 6694.9153 | S12: =Assumptions!S22 -> 7033.8983 | T12: =Assumptions!T22 -> 7372.8814 | ... BT12: =Assumptions!BT22 -> 25000 | BV12: =SUMIF($M$3:$BT$3,BV$3,$M12:$BT12) -> 82372.881 | BW12: =SUMIF($M$3:$BT$3,BW$3,$M12:$BT12) -> 131186.44 | BX12: =SUMIF($M$3:$BT$3,BX$3,$M12:$BT12) -> 180000 | BY12: =SUMIF($M$3:$BT$3,BY$3,$M12:$BT12) -> 228813.56 | BZ12: =SUMIF($M$3:$BT$3,BZ$3,$M12:$BT12) -> 277627.12
A13: =Assumptions!A23 -> Headcount
A14: =Assumptions!A24 -> Customer Support | C14: Base | F14: =Assumptions!F24 -> Account/Customer support | G14: =Assumptions!G24 -> 40 | H14: =Assumptions!H24 -> 40 | M14: =Assumptions!M24 -> 40 | N14: =Assumptions!N24 -> 40 | O14: =Assumptions!O24 -> 40 | P14: =Assumptions!P24 -> 40 | Q14: =Assumptions!Q24 -> 40 | R14: =Assumptions!R24 -> 40 | S14: =Assumptions!S24 -> 40 | T14: =Assumptions!T24 -> 40 | ... BT14: =Assumptions!BT24 -> 40
A15: Customer Support Headcount | M15: =ROUND('Revenue Buildup'!M10/Assumptions!M24,0) -> 1 | N15: =ROUND('Revenue Buildup'!N10/Assumptions!N24,0) -> 1 | O15: =ROUND('Revenue Buildup'!O10/Assumptions!O24,0) -> 1 | P15: =ROUND('Revenue Buildup'!P10/Assumptions!P24,0) -> 1 | Q15: =ROUND('Revenue Buildup'!Q10/Assumptions!Q24,0) -> 2 | R15: =ROUND('Revenue Buildup'!R10/Assumptions!R24,0) -> 2 | S15: =ROUND('Revenue Buildup'!S10/Assumptions!S24,0) -> 2 | T15: =ROUND('Revenue Buildup'!T10/Assumptions!T24,0) -> 2 | ... BT15: =ROUND('Revenue Buildup'!BT10/Assumptions!BT24,0) -> 70
A16: Customer Support Team Salary
A17: =Assumptions!A25 -> Customer Support | F17: =Assumptions!F25 -> Monthly Salary/Headcount | G17: =Assumptions!G25 -> 40000 | H17: 0.1 | I17: =Assumptions!I25 -> Annual Increment | M17: =(M15*$G$17)*(1+$H$17)^(M$3-1) -> 40000 | N17: =(N15*$G$17)*(1+$H$17)^(N$3-1) -> 40000 | O17: =(O15*$G$17)*(1+$H$17)^(O$3-1) -> 40000 | P17: =(P15*$G$17)*(1+$H$17)^(P$3-1) -> 40000 | Q17: =(Q15*$G$17)*(1+$H$17)^(Q$3-1) -> 80000 | R17: =(R15*$G$17)*(1+$H$17)^(R$3-1) -> 80000 | S17: =(S15*$G$17)*(1+$H$17)^(S$3-1) -> 80000 | T17: =(T15*$G$17)*(1+$H$17)^(T$3-1) -> 80000 | ... BT17: =(BT15*$G$17)*(1+$H$17)^(BT$3-1) -> 4099480 | BV17: =SUMIF($M$3:$BT$3,BV$3,$M17:$BT17) -> 1040000 | BW17: =SUMIF($M$3:$BT$3,BW$3,$M17:$BT17) -> 4664000 | BX17: =SUMIF($M$3:$BT$3,BX$3,$M17:$BT17) -> 13261600 | BY17: =SUMIF($M$3:$BT$3,BY$3,$M17:$BT17) -> 25022800 | BZ17: =SUMIF($M$3:$BT$3,BZ$3,$M17:$BT17) -> 41756132
A18: Total Direct Cost | M18: =SUM(M7:M9,M11:M12,M17) -> 114780 | N18: =SUM(N7:N9,N11:N12,N17) -> 124446.44 | O18: =SUM(O7:O9,O11:O12,O17) -> 134112.88 | P18: =SUM(P7:P9,P11:P12,P17) -> 147379.32 | Q18: =SUM(Q7:Q9,Q11:Q12,Q17) -> 197045.76 | R18: =SUM(R7:R9,R11:R12,R17) -> 206712.2 | S18: =SUM(S7:S9,S11:S12,S17) -> 228978.64 | T18: =SUM(T7:T9,T11:T12,T17) -> 238645.08 | ... BT18: =SUM(BT7:BT9,BT11:BT12,BT17) -> 5042660 | BV18: =SUMIF($M$3:$BT$3,BV$3,$M18:$BT18) -> 2715745.1 | BW18: =SUMIF($M$3:$BT$3,BW$3,$M18:$BT18) -> 8508232.5 | BX18: =SUMIF($M$3:$BT$3,BX$3,$M18:$BT18) -> 19503280 | BY18: =SUMIF($M$3:$BT$3,BY$3,$M18:$BT18) -> 33468607 | BZ18: =SUMIF($M$3:$BT$3,BZ$3,$M18:$BT18) -> 52289427
A19: =Assumptions!A26 -> Operating Expense
A20: =Assumptions!A27 -> Sales & Marketing Expense
A21: =Assumptions!A28 -> Sales Funnel
A22: =Assumptions!A29 -> Advetising/Marketing Expense Type 1 SMBs Focused | M22: =Assumptions!M29 -> 150000 | N22: =Assumptions!N29 -> 150000 | O22: =Assumptions!O29 -> 150000 | P22: =Assumptions!P29 -> 250000 | Q22: =Assumptions!Q29 -> 250000 | R22: =Assumptions!R29 -> 250000 | S22: =Assumptions!S29 -> 500000 | T22: =Assumptions!T29 -> 500000 | ... BT22: =Assumptions!BT29 -> 4000000 | BV22: =SUMIF($M$3:$BT$3,BV$3,$M22:$BT22) -> 4950000 | BW22: =SUMIF($M$3:$BT$3,BW$3,$M22:$BT22) -> 18150000 | BX22: =SUMIF($M$3:$BT$3,BX$3,$M22:$BT22) -> 29400000 | BY22: =SUMIF($M$3:$BT$3,BY$3,$M22:$BT22) -> 37800000 | BZ22: =SUMIF($M$3:$BT$3,BZ$3,$M22:$BT22) -> 46200000
A23: =Assumptions!A30 -> Advetising/Marketing Expense Type 2 SMBs Focused | M23: =Assumptions!M30 -> 75000 | N23: =Assumptions!N30 -> 75000 | O23: =Assumptions!O30 -> 75000 | P23: =Assumptions!P30 -> 125000 | Q23: =Assumptions!Q30 -> 125000 | R23: =Assumptions!R30 -> 125000 | S23: =Assumptions!S30 -> 250000 | T23: =Assumptions!T30 -> 250000 | ... BT23: =Assumptions!BT30 -> 4300000
A24: =Assumptions!A31 -> Cost/Lead Type 1 | G24: =Assumptions!G31 -> 2000 | H24: =Assumptions!H31 -> 2000 | M24: =Assumptions!M31 -> 2000 | N24: =Assumptions!N31 -> 2000 | O24: =Assumptions!O31 -> 2000 | P24: =Assumptions!P31 -> 2000 | Q24: =Assumptions!Q31 -> 2000 | R24: =Assumptions!R31 -> 2000 | S24: =Assumptions!S31 -> 2000 | T24: =Assumptions!T31 -> 2000 | ... BT24: =Assumptions!BT31 -> 2000
A25: =Assumptions!A32 -> Cost/Lead Type 2 | G25: =Assumptions!G32 -> 1000 | H25: =Assumptions!H32 -> 1000 | M25: =Assumptions!M32 -> 1000 | N25: =Assumptions!N32 -> 1000 | O25: =Assumptions!O32 -> 1000 | P25: =Assumptions!P32 -> 1000 | Q25: =Assumptions!Q32 -> 1000 | R25: =Assumptions!R32 -> 1000 | S25: =Assumptions!S32 -> 1000 | T25: =Assumptions!T32 -> 1000 | ... BT25: =Assumptions!BT32 -> 1000
A26: Leads | M26: =ROUND(M22/M24,0) -> 75 | N26: =ROUND(N22/N24,0) -> 75 | O26: =ROUND(O22/O24,0) -> 75 | P26: =ROUND(P22/P24,0) -> 125 | Q26: =ROUND(Q22/Q24,0) -> 125 | R26: =ROUND(R22/R24,0) -> 125 | S26: =ROUND(S22/S24,0) -> 250 | T26: =ROUND(T22/T24,0) -> 250 | ... BT26: =ROUND(BT22/BT24,0) -> 2000 | BV26: =SUMIF($M$3:$BT$3,BV$3,$M26:$BT26) -> 2475 | BW26: =SUMIF($M$3:$BT$3,BW$3,$M26:$BT26) -> 9075 | BX26: =SUMIF($M$3:$BT$3,BX$3,$M26:$BT26) -> 14700 | BY26: =SUMIF($M$3:$BT$3,BY$3,$M26:$BT26) -> 18900 | BZ26: =SUMIF($M$3:$BT$3,BZ$3,$M26:$BT26) -> 23100
A27: Leads | M27: =ROUND(M23/M25,0) -> 75 | N27: =ROUND(N23/N25,0) -> 75 | O27: =ROUND(O23/O25,0) -> 75 | P27: =ROUND(P23/P25,0) -> 125 | Q27: =ROUND(Q23/Q25,0) -> 125 | R27: =ROUND(R23/R25,0) -> 125 | S27: =ROUND(S23/S25,0) -> 250 | T27: =ROUND(T23/T25,0) -> 250 | ... BT27: =ROUND(BT23/BT25,0) -> 4300
A28: =Assumptions!A33 -> Sales Commission %
A29: =Assumptions!A34 -> New Bookings | M29: =Assumptions!M34*'Revenue Buildup'!M12 -> 48000 | N29: =Assumptions!N34*'Revenue Buildup'!N12 -> 48000 | O29: =Assumptions!O34*'Revenue Buildup'!O12 -> 48000 | P29: =Assumptions!P34*'Revenue Buildup'!P12 -> 72000 | Q29: =Assumptions!Q34*'Revenue Buildup'!Q12 -> 72000 | R29: =Assumptions!R34*'Revenue Buildup'!R12 -> 72000 | S29: =Assumptions!S34*'Revenue Buildup'!S12 -> 156000 | T29: =Assumptions!T34*'Revenue Buildup'!T12 -> 156000 | ... BT29: =Assumptions!BT34*'Revenue Buildup'!BT12 -> 1200000 | BV29: =SUMIF($M$3:$BT$3,BV$3,$M29:$BT29) -> 1512000 | BW29: =SUMIF($M$3:$BT$3,BW$3,$M29:$BT29) -> 5436000 | BX29: =SUMIF($M$3:$BT$3,BX$3,$M29:$BT29) -> 8856000 | BY29: =SUMIF($M$3:$BT$3,BY$3,$M29:$BT29) -> 11376000 | BZ29: =SUMIF($M$3:$BT$3,BZ$3,$M29:$BT29) -> 13896000
A30: =Assumptions!A35 -> Renewals | M30: =Assumptions!M35*'Revenue Buildup'!M14 -> 0 | N30: =Assumptions!N35*'Revenue Buildup'!N14 -> 0 | O30: =Assumptions!O35*'Revenue Buildup'!O14 -> 0 | P30: =Assumptions!P35*'Revenue Buildup'!P14 -> 0 | Q30: =Assumptions!Q35*'Revenue Buildup'!Q14 -> 0 | R30: =Assumptions!R35*'Revenue Buildup'!R14 -> 0 | S30: =Assumptions!S35*'Revenue Buildup'!S14 -> 0 | T30: =Assumptions!T35*'Revenue Buildup'!T14 -> 0 | ... BT30: =Assumptions!BT35*'Revenue Buildup'!BT14 -> 174000 | BV30: =SUMIF($M$3:$BT$3,BV$3,$M30:$BT30) -> 0 | BW30: =SUMIF($M$3:$BT$3,BW$3,$M30:$BT30) -> 261000 | BX30: =SUMIF($M$3:$BT$3,BX$3,$M30:$BT30) -> 945000 | BY30: =SUMIF($M$3:$BT$3,BY$3,$M30:$BT30) -> 1548000 | BZ30: =SUMIF($M$3:$BT$3,BZ$3,$M30:$BT30) -> 1989000
A31: =Assumptions!A36 -> Expansion | M31: =Assumptions!M36*'Revenue Buildup'!M15 -> 0 | N31: =Assumptions!N36*'Revenue Buildup'!N15 -> 0 | O31: =Assumptions!O36*'Revenue Buildup'!O15 -> 0 | P31: =Assumptions!P36*'Revenue Buildup'!P15 -> 0 | Q31: =Assumptions!Q36*'Revenue Buildup'!Q15 -> 0 | R31: =Assumptions!R36*'Revenue Buildup'!R15 -> 0 | S31: =Assumptions!S36*'Revenue Buildup'!S15 -> 0 | T31: =Assumptions!T36*'Revenue Buildup'!T15 -> 0 | ... BT31: =Assumptions!BT36*'Revenue Buildup'!BT15 -> 69600 | BV31: =SUMIF($M$3:$BT$3,BV$3,$M31:$BT31) -> 0 | BW31: =SUMIF($M$3:$BT$3,BW$3,$M31:$BT31) -> 104400 | BX31: =SUMIF($M$3:$BT$3,BX$3,$M31:$BT31) -> 378000 | BY31: =SUMIF($M$3:$BT$3,BY$3,$M31:$BT31) -> 619200 | BZ31: =SUMIF($M$3:$BT$3,BZ$3,$M31:$BT31) -> 795600
A32: Total Commissions | M32: =SUM(M29:M31) -> 48000 | N32: =SUM(N29:N31) -> 48000 | O32: =SUM(O29:O31) -> 48000 | P32: =SUM(P29:P31) -> 72000 | Q32: =SUM(Q29:Q31) -> 72000 | R32: =SUM(R29:R31) -> 72000 | S32: =SUM(S29:S31) -> 156000 | T32: =SUM(T29:T31) -> 156000 | ... BT32: =SUM(BT29:BT31) -> 1443600
A33: =Assumptions!A37 -> Headcount
A34: =Assumptions!A38 -> Sales (SDR) | C34: Base | F34: =Assumptions!F38 -> Leads/Sales Agent/Month | G34: =Assumptions!G38 -> 50 | H34: =Assumptions!H38 -> 50 | M34: =Assumptions!M38 -> 50 | N34: =Assumptions!N38 -> 50 | O34: =Assumptions!O38 -> 50 | P34: =Assumptions!P38 -> 50 | Q34: =Assumptions!Q38 -> 50 | R34: =Assumptions!R38 -> 50 | S34: =Assumptions!S38 -> 50 | T34: =Assumptions!T38 -> 50 | ... BT34: =Assumptions!BT38 -> 50
A35: =Assumptions!A39 -> Sales Manager | C35: Base | F35: =Assumptions!F39 -> Sales Agents/Sales Manager | G35: =Assumptions!G39 -> 10 | H35: =Assumptions!H39 -> 10 | M35: =Assumptions!M39 -> 10 | N35: =Assumptions!N39 -> 10 | O35: =Assumptions!O39 -> 10 | P35: =Assumptions!P39 -> 10 | Q35: =Assumptions!Q39 -> 10 | R35: =Assumptions!R39 -> 10 | S35: =Assumptions!S39 -> 10 | T35: =Assumptions!T39 -> 10 | ... BT35: =Assumptions!BT39 -> 10
A36: Sales (SDR) Headcount | M36: =ROUND(M26/M34,0) -> 2 | N36: =ROUND(N26/N34,0) -> 2 | O36: =ROUND(O26/O34,0) -> 2 | P36: =ROUND(P26/P34,0) -> 3 | Q36: =ROUND(Q26/Q34,0) -> 3 | R36: =ROUND(R26/R34,0) -> 3 | S36: =ROUND(S26/S34,0) -> 5 | T36: =ROUND(T26/T34,0) -> 5 | ... BT36: =ROUND(BT26/BT34,0) -> 40
A37: Sales Manager Headcount | M37: =ROUND(M36/M35,0) -> 0 | N37: =ROUND(N36/N35,0) -> 0 | O37: =ROUND(O36/O35,0) -> 0 | P37: =ROUND(P36/P35,0) -> 0 | Q37: =ROUND(Q36/Q35,0) -> 0 | R37: =ROUND(R36/R35,0) -> 0 | S37: =ROUND(S36/S35,0) -> 1 | T37: =ROUND(T36/T35,0) -> 1 | ... BT37: =ROUND(BT36/BT35,0) -> 4
A38: =Assumptions!A40 -> Sales Team Salary
A39: =Assumptions!A41 -> Sales (SDR) | F39: =Assumptions!F41 -> Monthly Salary/Headcount | G39: =Assumptions!G41 -> 50000 | H39: =Assumptions!H41 -> 0.15 | I39: =Assumptions!I41 -> Annual Increment | M39: =($G39*M36)*(1+$H39)^(M$3-1) -> 100000 | N39: =($G39*N36)*(1+$H39)^(N$3-1) -> 100000 | O39: =($G39*O36)*(1+$H39)^(O$3-1) -> 100000 | P39: =($G39*P36)*(1+$H39)^(P$3-1) -> 150000 | Q39: =($G39*Q36)*(1+$H39)^(Q$3-1) -> 150000 | R39: =($G39*R36)*(1+$H39)^(R$3-1) -> 150000 | S39: =($G39*S36)*(1+$H39)^(S$3-1) -> 250000 | T39: =($G39*T36)*(1+$H39)^(T$3-1) -> 250000 | ... BT39: =($G39*BT36)*(1+$H39)^(BT$3-1) -> 3498012.5 | BV39: =SUMIF($M$3:$BT$3,BV$3,$M39:$BT39) -> 2700000 | BW39: =SUMIF($M$3:$BT$3,BW$3,$M39:$BT39) -> 10522500 | BX39: =SUMIF($M$3:$BT$3,BX$3,$M39:$BT39) -> 19440750 | BY39: =SUMIF($M$3:$BT$3,BY$3,$M39:$BT39) -> 28744537 | BZ39: =SUMIF($M$3:$BT$3,BZ$3,$M39:$BT39) -> 40402044
A40: =Assumptions!A42 -> Sales Manager | F40: =Assumptions!F42 -> Monthly Salary/Headcount | G40: 70000 | H40: =Assumptions!H42 -> 0.15 | I40: =Assumptions!I42 -> Annual Increment | M40: =($G40*M37)*(1+$H40)^(M$3-1) -> 0 | N40: =($G40*N37)*(1+$H40)^(N$3-1) -> 0 | O40: =($G40*O37)*(1+$H40)^(O$3-1) -> 0 | P40: =($G40*P37)*(1+$H40)^(P$3-1) -> 0 | Q40: =($G40*Q37)*(1+$H40)^(Q$3-1) -> 0 | R40: =($G40*R37)*(1+$H40)^(R$3-1) -> 0 | S40: =($G40*S37)*(1+$H40)^(S$3-1) -> 70000 | T40: =($G40*T37)*(1+$H40)^(T$3-1) -> 70000 | ... BT40: =($G40*BT37)*(1+$H40)^(BT$3-1) -> 489721.75 | BV40: =SUMIF($M$3:$BT$3,BV$3,$M40:$BT40) -> 420000 | BW40: =SUMIF($M$3:$BT$3,BW$3,$M40:$BT40) -> 1449000 | BX40: =SUMIF($M$3:$BT$3,BX$3,$M40:$BT40) -> 2777250 | BY40: =SUMIF($M$3:$BT$3,BY$3,$M40:$BT40) -> 3832605 | BZ40: =SUMIF($M$3:$BT$3,BZ$3,$M40:$BT40) -> 5876661
A41: Total Sales Salary | M41: =SUM(M39:M40) -> 100000 | N41: =SUM(N39:N40) -> 100000 | O41: =SUM(O39:O40) -> 100000 | P41: =SUM(P39:P40) -> 150000 | Q41: =SUM(Q39:Q40) -> 150000 | R41: =SUM(R39:R40) -> 150000 | S41: =SUM(S39:S40) -> 320000 | T41: =SUM(T39:T40) -> 320000 | ... BT41: =SUM(BT39:BT40) -> 3987734.2 | BV41: =SUMIF($M$3:$BT$3,BV$3,$M41:$BT41) -> 3120000 | BW41: =SUMIF($M$3:$BT$3,BW$3,$M41:$BT41) -> 11971500 | BX41: =SUMIF($M$3:$BT$3,BX$3,$M41:$BT41) -> 22218000 | BY41: =SUMIF($M$3:$BT$3,BY$3,$M41:$BT41) -> 32577142 | BZ41: =SUMIF($M$3:$BT$3,BZ$3,$M41:$BT41) -> 46278705
A42: Total Sales Expenses | M42: =SUM(M22,M29:M31,M39:M40) -> 298000 | N42: =SUM(N22,N29:N31,N39:N40) -> 298000 | O42: =SUM(O22,O29:O31,O39:O40) -> 298000 | P42: =SUM(P22,P29:P31,P39:P40) -> 472000 | Q42: =SUM(Q22,Q29:Q31,Q39:Q40) -> 472000 | R42: =SUM(R22,R29:R31,R39:R40) -> 472000 | S42: =SUM(S22,S29:S31,S39:S40) -> 976000 | T42: =SUM(T22,T29:T31,T39:T40) -> 976000 | ... BT42: =SUM(BT22,BT29:BT31,BT39:BT40) -> 9431334.2 | BV42: =SUMIF($M$3:$BT$3,BV$3,$M42:$BT42) -> 9582000 | BW42: =SUMIF($M$3:$BT$3,BW$3,$M42:$BT42) -> 35922900 | BX42: =SUMIF($M$3:$BT$3,BX$3,$M42:$BT42) -> 61797000 | BY42: =SUMIF($M$3:$BT$3,BY$3,$M42:$BT42) -> 83920342 | BZ42: =SUMIF($M$3:$BT$3,BZ$3,$M42:$BT42) -> 1.0915931e+08
A44: =Assumptions!A44 -> Marketing Team Roles & Headcount
A45: =Assumptions!A45 -> Head of Marketing | F45: =Assumptions!F45 -> Monthly Salary/Headcount | G45: =Assumptions!G45 -> 100000 | H45: =Assumptions!H45 -> 0.15 | I45: =Assumptions!I45 -> Annual Increment | M45: =($G45*Assumptions!M45)*(1+'Cost Buildup'!$H45)^(M$3-1) -> 0 | N45: =($G45*Assumptions!N45)*(1+'Cost Buildup'!$H45)^(N$3-1) -> 0 | O45: =($G45*Assumptions!O45)*(1+'Cost Buildup'!$H45)^(O$3-1) -> 0 | P45: =($G45*Assumptions!P45)*(1+'Cost Buildup'!$H45)^(P$3-1) -> 0 | Q45: =($G45*Assumptions!Q45)*(1+'Cost Buildup'!$H45)^(Q$3-1) -> 0 | R45: =($G45*Assumptions!R45)*(1+'Cost Buildup'!$H45)^(R$3-1) -> 0 | S45: =($G45*Assumptions!S45)*(1+'Cost Buildup'!$H45)^(S$3-1) -> 0 | T45: =($G45*Assumptions!T45)*(1+'Cost Buildup'!$H45)^(T$3-1) -> 0 | ... BT45: =($G45*Assumptions!BT45)*(1+'Cost Buildup'!$H45)^(BT$3-1) -> 174900.62 | BV45: =SUMIF($M$3:$BT$3,BV$3,$M45:$BT45) -> 0 | BW45: =SUMIF($M$3:$BT$3,BW$3,$M45:$BT45) -> 690000 | BX45: =SUMIF($M$3:$BT$3,BX$3,$M45:$BT45) -> 1587000 | BY45: =SUMIF($M$3:$BT$3,BY$3,$M45:$BT45) -> 1825050 | BZ45: =SUMIF($M$3:$BT$3,BZ$3,$M45:$BT45) -> 2098807.5
A46: =Assumptions!A46 -> Growth | F46: =Assumptions!F46 -> Monthly Salary/Headcount | G46: =Assumptions!G46 -> 75000 | H46: =Assumptions!H46 -> 0.15 | I46: =Assumptions!I46 -> Annual Increment | M46: =($G46*Assumptions!M46)*(1+'Cost Buildup'!$H46)^(M$3-1) -> 75000 | N46: =($G46*Assumptions!N46)*(1+'Cost Buildup'!$H46)^(N$3-1) -> 75000 | O46: =($G46*Assumptions!O46)*(1+'Cost Buildup'!$H46)^(O$3-1) -> 75000 | P46: =($G46*Assumptions!P46)*(1+'Cost Buildup'!$H46)^(P$3-1) -> 75000 | Q46: =($G46*Assumptions!Q46)*(1+'Cost Buildup'!$H46)^(Q$3-1) -> 75000 | R46: =($G46*Assumptions!R46)*(1+'Cost Buildup'!$H46)^(R$3-1) -> 75000 | S46: =($G46*Assumptions!S46)*(1+'Cost Buildup'!$H46)^(S$3-1) -> 75000 | T46: =($G46*Assumptions!T46)*(1+'Cost Buildup'!$H46)^(T$3-1) -> 75000 | ... BT46: =($G46*Assumptions!BT46)*(1+'Cost Buildup'!$H46)^(BT$3-1) -> 524701.87 | BV46: =SUMIF($M$3:$BT$3,BV$3,$M46:$BT46) -> 900000 | BW46: =SUMIF($M$3:$BT$3,BW$3,$M46:$BT46) -> 2070000 | BX46: =SUMIF($M$3:$BT$3,BX$3,$M46:$BT46) -> 4761000 | BY46: =SUMIF($M$3:$BT$3,BY$3,$M46:$BT46) -> 5475150 | BZ46: =SUMIF($M$3:$BT$3,BZ$3,$M46:$BT46) -> 6296422.5
A47: =Assumptions!A47 -> Branding | F47: =Assumptions!F47 -> Monthly Salary/Headcount | G47: =Assumptions!G47 -> 50000 | H47: =Assumptions!H47 -> 0.15 | I47: =Assumptions!I47 -> Annual Increment | M47: =($G47*Assumptions!M47)*(1+'Cost Buildup'!$H47)^(M$3-1) -> 0 | N47: =($G47*Assumptions!N47)*(1+'Cost Buildup'!$H47)^(N$3-1) -> 0 | O47: =($G47*Assumptions!O47)*(1+'Cost Buildup'!$H47)^(O$3-1) -> 0 | P47: =($G47*Assumptions!P47)*(1+'Cost Buildup'!$H47)^(P$3-1) -> 0 | Q47: =($G47*Assumptions!Q47)*(1+'Cost Buildup'!$H47)^(Q$3-1) -> 0 | R47: =($G47*Assumptions!R47)*(1+'Cost Buildup'!$H47)^(R$3-1) -> 0 | S47: =($G47*Assumptions!S47)*(1+'Cost Buildup'!$H47)^(S$3-1) -> 0 | T47: =($G47*Assumptions!T47)*(1+'Cost Buildup'!$H47)^(T$3-1) -> 0 | ... BT47: =($G47*Assumptions!BT47)*(1+'Cost Buildup'!$H47)^(BT$3-1) -> 174900.62 | BV47: =SUMIF($M$3:$BT$3,BV$3,$M47:$BT47) -> 0 | BW47: =SUMIF($M$3:$BT$3,BW$3,$M47:$BT47) -> 345000 | BX47: =SUMIF($M$3:$BT$3,BX$3,$M47:$BT47) -> 1587000 | BY47: =SUMIF($M$3:$BT$3,BY$3,$M47:$BT47) -> 1825050 | BZ47: =SUMIF($M$3:$BT$3,BZ$3,$M47:$BT47) -> 2098807.5
A48: =Assumptions!A48 -> Content & Creative | F48: =Assumptions!F48 -> Monthly Salary/Headcount | G48: =Assumptions!G48 -> 50000 | H48: =Assumptions!H48 -> 0.15 | I48: =Assumptions!I48 -> Annual Increment | M48: =($G48*Assumptions!M48)*(1+'Cost Buildup'!$H48)^(M$3-1) -> 50000 | N48: =($G48*Assumptions!N48)*(1+'Cost Buildup'!$H48)^(N$3-1) -> 50000 | O48: =($G48*Assumptions!O48)*(1+'Cost Buildup'!$H48)^(O$3-1) -> 50000 | P48: =($G48*Assumptions!P48)*(1+'Cost Buildup'!$H48)^(P$3-1) -> 50000 | Q48: =($G48*Assumptions!Q48)*(1+'Cost Buildup'!$H48)^(Q$3-1) -> 50000 | R48: =($G48*Assumptions!R48)*(1+'Cost Buildup'!$H48)^(R$3-1) -> 50000 | S48: =($G48*Assumptions!S48)*(1+'Cost Buildup'!$H48)^(S$3-1) -> 50000 | T48: =($G48*Assumptions!T48)*(1+'Cost Buildup'!$H48)^(T$3-1) -> 50000 | ... BT48: =($G48*Assumptions!BT48)*(1+'Cost Buildup'!$H48)^(BT$3-1) -> 262350.94 | BV48: =SUMIF($M$3:$BT$3,BV$3,$M48:$BT48) -> 600000 | BW48: =SUMIF($M$3:$BT$3,BW$3,$M48:$BT48) -> 1035000 | BX48: =SUMIF($M$3:$BT$3,BX$3,$M48:$BT48) -> 2380500 | BY48: =SUMIF($M$3:$BT$3,BY$3,$M48:$BT48) -> 2737575 | BZ48: =SUMIF($M$3:$BT$3,BZ$3,$M48:$BT48) -> 3148211.2
A49: Total Marketing Salary | M49: =SUM(M45:M48) -> 125000 | N49: =SUM(N45:N48) -> 125000 | O49: =SUM(O45:O48) -> 125000 | P49: =SUM(P45:P48) -> 125000 | Q49: =SUM(Q45:Q48) -> 125000 | R49: =SUM(R45:R48) -> 125000 | S49: =SUM(S45:S48) -> 125000 | T49: =SUM(T45:T48) -> 125000 | ... BT49: =SUM(BT45:BT48) -> 1136854.1 | BV49: =SUMIF($M$3:$BT$3,BV$3,$M49:$BT49) -> 1500000 | BW49: =SUMIF($M$3:$BT$3,BW$3,$M49:$BT49) -> 4140000 | BX49: =SUMIF($M$3:$BT$3,BX$3,$M49:$BT49) -> 10315500 | BY49: =SUMIF($M$3:$BT$3,BY$3,$M49:$BT49) -> 11862825 | BZ49: =SUMIF($M$3:$BT$3,BZ$3,$M49:$BT49) -> 13642249
A50: Total Marketing Expense | M50: =M49 -> 125000 | N50: =N49 -> 125000 | O50: =O49 -> 125000 | P50: =P49 -> 125000 | Q50: =Q49 -> 125000 | R50: =R49 -> 125000 | S50: =S49 -> 125000 | T50: =T49 -> 125000 | ... BT50: =BT49 -> 1136854.1 | BV50: =SUMIF($M$3:$BT$3,BV$3,$M50:$BT50) -> 1500000 | BW50: =SUMIF($M$3:$BT$3,BW$3,$M50:$BT50) -> 4140000 | BX50: =SUMIF($M$3:$BT$3,BX$3,$M50:$BT50) -> 10315500 | BY50: =SUMIF($M$3:$BT$3,BY$3,$M50:$BT50) -> 11862825 | BZ50: =SUMIF($M$3:$BT$3,BZ$3,$M50:$BT50) -> 13642249
A51: =Assumptions!A49 -> G&A
A52: =Assumptions!A50 -> Office Rent | F52: =Assumptions!F50 -> Chair/Empoloyee/Monthly | G52: =Assumptions!G50 -> 7000 | H52: =Assumptions!H50 -> 9367.579 | M52: =Assumptions!M50*M82 -> 70000 | N52: =Assumptions!N50*N82 -> 70401.285 | O52: =Assumptions!O50*O82 -> 70802.569 | P52: =Assumptions!P50*P82 -> 78324.239 | Q52: =Assumptions!Q50*Q82 -> 85926.166 | R52: =Assumptions!R50*R82 -> 86407.708 | S52: =Assumptions!S50*S82 -> 115852.33 | T52: =Assumptions!T50*T82 -> 116494.39 | ... BT52: =Assumptions!BT50*BT82 -> 1302093.5 | BV52: =SUMIF($M$3:$BT$3,BV$3,$M52:$BT52) -> 1277585.9 | BW52: =SUMIF($M$3:$BT$3,BW$3,$M52:$BT52) -> 3721735.6 | BX52: =SUMIF($M$3:$BT$3,BX$3,$M52:$BT52) -> 7358794.2 | BY52: =SUMIF($M$3:$BT$3,BY$3,$M52:$BT52) -> 10270466 | BZ52: =SUMIF($M$3:$BT$3,BZ$3,$M52:$BT52) -> 13943267
A53: =Assumptions!A51 -> Utilities | F53: =Assumptions!F51 -> Emp/Monthly | G53: =Assumptions!G51 -> 2000 | H53: =Assumptions!H51 -> 2676.4512 | M53: =Assumptions!M51*M82 -> 20000 | N53: =Assumptions!N51*N82 -> 20114.653 | O53: =Assumptions!O51*O82 -> 20229.305 | P53: =Assumptions!P51*P82 -> 22378.354 | Q53: =Assumptions!Q51*Q82 -> 24550.333 | R53: =Assumptions!R51*R82 -> 24687.916 | S53: =Assumptions!S51*S82 -> 33100.666 | T53: =Assumptions!T51*T82 -> 33284.111 | ... BT53: =Assumptions!BT51*BT82 -> 372026.71 | BV53: =SUMIF($M$3:$BT$3,BV$3,$M53:$BT53) -> 365024.55 | BW53: =SUMIF($M$3:$BT$3,BW$3,$M53:$BT53) -> 1063353 | BX53: =SUMIF($M$3:$BT$3,BX$3,$M53:$BT53) -> 2102512.6 | BY53: =SUMIF($M$3:$BT$3,BY$3,$M53:$BT53) -> 2934418.9 | BZ53: =SUMIF($M$3:$BT$3,BZ$3,$M53:$BT53) -> 3983790.6
A54: =Assumptions!A52 -> G&A Team Roles & Headcount
A55: =Assumptions!A53 -> Account & Finance | F55: =Assumptions!F53 -> Monthly Salary/Headcount | G55: =Assumptions!G53 -> 40000 | H55: =Assumptions!H53 -> 0.15 | I55: =Assumptions!I53 -> Annual Increment | M55: =($G55*Assumptions!M53)*(1+'Cost Buildup'!$H55)^(M$3-1) -> 40000 | N55: =($G55*Assumptions!N53)*(1+'Cost Buildup'!$H55)^(N$3-1) -> 40000 | O55: =($G55*Assumptions!O53)*(1+'Cost Buildup'!$H55)^(O$3-1) -> 40000 | P55: =($G55*Assumptions!P53)*(1+'Cost Buildup'!$H55)^(P$3-1) -> 40000 | Q55: =($G55*Assumptions!Q53)*(1+'Cost Buildup'!$H55)^(Q$3-1) -> 40000 | R55: =($G55*Assumptions!R53)*(1+'Cost Buildup'!$H55)^(R$3-1) -> 40000 | S55: =($G55*Assumptions!S53)*(1+'Cost Buildup'!$H55)^(S$3-1) -> 40000 | T55: =($G55*Assumptions!T53)*(1+'Cost Buildup'!$H55)^(T$3-1) -> 40000 | ... BT55: =($G55*Assumptions!BT53)*(1+'Cost Buildup'!$H55)^(BT$3-1) -> 139920.5 | BV55: =SUMIF($M$3:$BT$3,BV$3,$M55:$BT55) -> 480000 | BW55: =SUMIF($M$3:$BT$3,BW$3,$M55:$BT55) -> 1104000 | BX55: =SUMIF($M$3:$BT$3,BX$3,$M55:$BT55) -> 1269600 | BY55: =SUMIF($M$3:$BT$3,BY$3,$M55:$BT55) -> 1460040 | BZ55: =SUMIF($M$3:$BT$3,BZ$3,$M55:$BT55) -> 1679046
A56: =Assumptions!A54 -> Legal | F56: =Assumptions!F54 -> Monthly Salary/Headcount | G56: =Assumptions!G54 -> 50000 | H56: =Assumptions!H54 -> 0.15 | I56: =Assumptions!I54 -> Annual Increment | M56: =($G56*Assumptions!M54)*(1+'Cost Buildup'!$H56)^(M$3-1) -> 0 | N56: =($G56*Assumptions!N54)*(1+'Cost Buildup'!$H56)^(N$3-1) -> 0 | O56: =($G56*Assumptions!O54)*(1+'Cost Buildup'!$H56)^(O$3-1) -> 0 | P56: =($G56*Assumptions!P54)*(1+'Cost Buildup'!$H56)^(P$3-1) -> 0 | Q56: =($G56*Assumptions!Q54)*(1+'Cost Buildup'!$H56)^(Q$3-1) -> 0 | R56: =($G56*Assumptions!R54)*(1+'Cost Buildup'!$H56)^(R$3-1) -> 0 | S56: =($G56*Assumptions!S54)*(1+'Cost Buildup'!$H56)^(S$3-1) -> 0 | T56: =($G56*Assumptions!T54)*(1+'Cost Buildup'!$H56)^(T$3-1) -> 0 | ... BT56: =($G56*Assumptions!BT54)*(1+'Cost Buildup'!$H56)^(BT$3-1) -> 87450.312 | BV56: =SUMIF($M$3:$BT$3,BV$3,$M56:$BT56) -> 0 | BW56: =SUMIF($M$3:$BT$3,BW$3,$M56:$BT56) -> 0 | BX56: =SUMIF($M$3:$BT$3,BX$3,$M56:$BT56) -> 793500 | BY56: =SUMIF($M$3:$BT$3,BY$3,$M56:$BT56) -> 912525 | BZ56: =SUMIF($M$3:$BT$3,BZ$3,$M56:$BT56) -> 1049403.7
A57: =Assumptions!A55 -> HR | F57: =Assumptions!F55 -> Monthly Salary/Headcount | G57: =Assumptions!G55 -> 60000 | H57: =Assumptions!H55 -> 0.15 | I57: =Assumptions!I55 -> Annual Increment | M57: =($G57*Assumptions!M55)*(1+'Cost Buildup'!$H57)^(M$3-1) -> 0 | N57: =($G57*Assumptions!N55)*(1+'Cost Buildup'!$H57)^(N$3-1) -> 0 | O57: =($G57*Assumptions!O55)*(1+'Cost Buildup'!$H57)^(O$3-1) -> 0 | P57: =($G57*Assumptions!P55)*(1+'Cost Buildup'!$H57)^(P$3-1) -> 0 | Q57: =($G57*Assumptions!Q55)*(1+'Cost Buildup'!$H57)^(Q$3-1) -> 0 | R57: =($G57*Assumptions!R55)*(1+'Cost Buildup'!$H57)^(R$3-1) -> 0 | S57: =($G57*Assumptions!S55)*(1+'Cost Buildup'!$H57)^(S$3-1) -> 0 | T57: =($G57*Assumptions!T55)*(1+'Cost Buildup'!$H57)^(T$3-1) -> 0 | ... BT57: =($G57*Assumptions!BT55)*(1+'Cost Buildup'!$H57)^(BT$3-1) -> 209880.75 | BV57: =SUMIF($M$3:$BT$3,BV$3,$M57:$BT57) -> 0 | BW57: =SUMIF($M$3:$BT$3,BW$3,$M57:$BT57) -> 828000 | BX57: =SUMIF($M$3:$BT$3,BX$3,$M57:$BT57) -> 1904400 | BY57: =SUMIF($M$3:$BT$3,BY$3,$M57:$BT57) -> 2190060 | BZ57: =SUMIF($M$3:$BT$3,BZ$3,$M57:$BT57) -> 2518569
A58: Total G&A Salary | M58: =SUM(M55:M57) -> 40000 | N58: =SUM(N55:N57) -> 40000 | O58: =SUM(O55:O57) -> 40000 | P58: =SUM(P55:P57) -> 40000 | Q58: =SUM(Q55:Q57) -> 40000 | R58: =SUM(R55:R57) -> 40000 | S58: =SUM(S55:S57) -> 40000 | T58: =SUM(T55:T57) -> 40000 | ... BT58: =SUM(BT55:BT57) -> 437251.56 | BV58: =SUMIF($M$3:$BT$3,BV$3,$M58:$BT58) -> 480000 | BW58: =SUMIF($M$3:$BT$3,BW$3,$M58:$BT58) -> 1932000 | BX58: =SUMIF($M$3:$BT$3,BX$3,$M58:$BT58) -> 3967500 | BY58: =SUMIF($M$3:$BT$3,BY$3,$M58:$BT58) -> 4562625 | BZ58: =SUMIF($M$3:$BT$3,BZ$3,$M58:$BT58) -> 5247018.7
A59: Total G&A Expense | M59: =M52+M53+M58 -> 130000 | N59: =N52+N53+N58 -> 130515.94 | O59: =O52+O53+O58 -> 131031.87 | P59: =P52+P53+P58 -> 140702.59 | Q59: =Q52+Q53+Q58 -> 150476.5 | R59: =R52+R53+R58 -> 151095.62 | S59: =S52+S53+S58 -> 188953 | T59: =T52+T53+T58 -> 189778.5 | ... BT59: =BT52+BT53+BT58 -> 2111371.8 | BV59: =SUMIF($M$3:$BT$3,BV$3,$M59:$BT59) -> 2122610.5 | BW59: =SUMIF($M$3:$BT$3,BW$3,$M59:$BT59) -> 6717088.6 | BX59: =SUMIF($M$3:$BT$3,BX$3,$M59:$BT59) -> 13428807 | BY59: =SUMIF($M$3:$BT$3,BY$3,$M59:$BT59) -> 17767510 | BZ59: =SUMIF($M$3:$BT$3,BZ$3,$M59:$BT59) -> 23174076
A60: =Assumptions!A56 -> Product Development Expense
A61: =Assumptions!A57 -> Infrastructure | M61: =Assumptions!M57 -> 10000 | N61: =Assumptions!N57 -> 11525.424 | O61: =Assumptions!O57 -> 13050.847 | P61: =Assumptions!P57 -> 14576.271 | Q61: =Assumptions!Q57 -> 16101.695 | R61: =Assumptions!R57 -> 17627.119 | S61: =Assumptions!S57 -> 19152.542 | T61: =Assumptions!T57 -> 20677.966 | ... BT61: =Assumptions!BT57 -> 100000 | BV61: =SUMIF($M$3:$BT$3,BV$3,$M61:$BT61) -> 220677.97 | BW61: =SUMIF($M$3:$BT$3,BW$3,$M61:$BT61) -> 440338.98 | BX61: =SUMIF($M$3:$BT$3,BX$3,$M61:$BT61) -> 660000 | BY61: =SUMIF($M$3:$BT$3,BY$3,$M61:$BT61) -> 879661.02 | BZ61: =SUMIF($M$3:$BT$3,BZ$3,$M61:$BT61) -> 1099322
A62: =Assumptions!A58 -> Product Development Team Roles & Headcount
A63: =Assumptions!A59 -> Product Developemt Team | F63: =Assumptions!F59 -> Monthly Salary/Headcount | G63: =Assumptions!G59 -> 60000 | H63: =Assumptions!H59 -> 0.15 | I63: =Assumptions!I59 -> Annual Increment | M63: =($G63*Assumptions!M59)*(1+'Cost Buildup'!$H63)^(M$3-1) -> 240000 | N63: =($G63*Assumptions!N59)*(1+'Cost Buildup'!$H63)^(N$3-1) -> 240000 | O63: =($G63*Assumptions!O59)*(1+'Cost Buildup'!$H63)^(O$3-1) -> 240000 | P63: =($G63*Assumptions!P59)*(1+'Cost Buildup'!$H63)^(P$3-1) -> 240000 | Q63: =($G63*Assumptions!Q59)*(1+'Cost Buildup'!$H63)^(Q$3-1) -> 240000 | R63: =($G63*Assumptions!R59)*(1+'Cost Buildup'!$H63)^(R$3-1) -> 240000 | S63: =($G63*Assumptions!S59)*(1+'Cost Buildup'!$H63)^(S$3-1) -> 300000 | T63: =($G63*Assumptions!T59)*(1+'Cost Buildup'!$H63)^(T$3-1) -> 300000 | ... BT63: =($G63*Assumptions!BT59)*(1+'Cost Buildup'!$H63)^(BT$3-1) -> 1049403.7 | BV63: =SUMIF($M$3:$BT$3,BV$3,$M63:$BT63) -> 3240000 | BW63: =SUMIF($M$3:$BT$3,BW$3,$M63:$BT63) -> 5796000 | BX63: =SUMIF($M$3:$BT$3,BX$3,$M63:$BT63) -> 9522000 | BY63: =SUMIF($M$3:$BT$3,BY$3,$M63:$BT63) -> 10950300 | BZ63: =SUMIF($M$3:$BT$3,BZ$3,$M63:$BT63) -> 12592845
A64: Total Product Development Expense | M64: =M61+M63 -> 250000 | N64: =N61+N63 -> 251525.42 | O64: =O61+O63 -> 253050.85 | P64: =P61+P63 -> 254576.27 | Q64: =Q61+Q63 -> 256101.69 | R64: =R61+R63 -> 257627.12 | S64: =S61+S63 -> 319152.54 | T64: =T61+T63 -> 320677.97 | ... BT64: =BT61+BT63 -> 1149403.8 | BV64: =SUMIF($M$3:$BT$3,BV$3,$M64:$BT64) -> 3460678 | BW64: =SUMIF($M$3:$BT$3,BW$3,$M64:$BT64) -> 6236339 | BX64: =SUMIF($M$3:$BT$3,BX$3,$M64:$BT64) -> 10182000 | BY64: =SUMIF($M$3:$BT$3,BY$3,$M64:$BT64) -> 11829961 | BZ64: =SUMIF($M$3:$BT$3,BZ$3,$M64:$BT64) -> 13692167
A65: Empolyees Benefit Expense
A66: Head Count
A67: Sales | M67: =SUM(M68:M69) -> 2 | N67: =SUM(N68:N69) -> 2 | O67: =SUM(O68:O69) -> 2 | P67: =SUM(P68:P69) -> 3 | Q67: =SUM(Q68:Q69) -> 3 | R67: =SUM(R68:R69) -> 3 | S67: =SUM(S68:S69) -> 6 | T67: =SUM(T68:T69) -> 6 | ... BT67: =SUM(BT68:BT69) -> 44
A68: =A36 -> Sales (SDR) Headcount | M68: =M36 -> 2 | N68: =N36 -> 2 | O68: =O36 -> 2 | P68: =P36 -> 3 | Q68: =Q36 -> 3 | R68: =R36 -> 3 | S68: =S36 -> 5 | T68: =T36 -> 5 | ... BT68: =BT36 -> 40
A69: =A37 -> Sales Manager Headcount | M69: =M37 -> 0 | N69: =N37 -> 0 | O69: =O37 -> 0 | P69: =P37 -> 0 | Q69: =Q37 -> 0 | R69: =R37 -> 0 | S69: =S37 -> 1 | T69: =T37 -> 1 | ... BT69: =BT37 -> 4
A70: Marketing | M70: =SUM(M71:M74) -> 2 | N70: =SUM(N71:N74) -> 2 | O70: =SUM(O71:O74) -> 2 | P70: =SUM(P71:P74) -> 2 | Q70: =SUM(Q71:Q74) -> 2 | R70: =SUM(R71:R74) -> 2 | S70: =SUM(S71:S74) -> 2 | T70: =SUM(T71:T74) -> 2 | ... BT70: =SUM(BT71:BT74) -> 10
A71: =Assumptions!A45 -> Head of Marketing | M71: =Assumptions!M45 -> 0 | N71: =Assumptions!N45 -> 0 | O71: =Assumptions!O45 -> 0 | P71: =Assumptions!P45 -> 0 | Q71: =Assumptions!Q45 -> 0 | R71: =Assumptions!R45 -> 0 | S71: =Assumptions!S45 -> 0 | T71: =Assumptions!T45 -> 0 | ... BT71: =Assumptions!BT45 -> 1
A72: =Assumptions!A46 -> Growth | M72: =Assumptions!M46 -> 1 | N72: =Assumptions!N46 -> 1 | O72: =Assumptions!O46 -> 1 | P72: =Assumptions!P46 -> 1 | Q72: =Assumptions!Q46 -> 1 | R72: =Assumptions!R46 -> 1 | S72: =Assumptions!S46 -> 1 | T72: =Assumptions!T46 -> 1 | ... BT72: =Assumptions!BT46 -> 4
A73: =Assumptions!A47 -> Branding | M73: =Assumptions!M47 -> 0 | N73: =Assumptions!N47 -> 0 | O73: =Assumptions!O47 -> 0 | P73: =Assumptions!P47 -> 0 | Q73: =Assumptions!Q47 -> 0 | R73: =Assumptions!R47 -> 0 | S73: =Assumptions!S47 -> 0 | T73: =Assumptions!T47 -> 0 | ... BT73: =Assumptions!BT47 -> 2
A74: =Assumptions!A48 -> Content & Creative | M74: =Assumptions!M48 -> 1 | N74: =Assumptions!N48 -> 1 | O74: =Assumptions!O48 -> 1 | P74: =Assumptions!P48 -> 1 | Q74: =Assumptions!Q48 -> 1 | R74: =Assumptions!R48 -> 1 | S74: =Assumptions!S48 -> 1 | T74: =Assumptions!T48 -> 1 | ... BT74: =Assumptions!BT48 -> 3
A75: G&A | M75: =SUM(M76:M78) -> 1 | N75: =SUM(N76:N78) -> 1 | O75: =SUM(O76:O78) -> 1 | P75: =SUM(P76:P78) -> 1 | Q75: =SUM(Q76:Q78) -> 1 | R75: =SUM(R76:R78) -> 1 | S75: =SUM(S76:S78) -> 1 | T75: =SUM(T76:T78) -> 1 | ... BT75: =SUM(BT76:BT78) -> 5
A76: =Assumptions!A53 -> Account & Finance | M76: =Assumptions!M53 -> 1 | N76: =Assumptions!N53 -> 1 | O76: =Assumptions!O53 -> 1 | P76: =Assumptions!P53 -> 1 | Q76: =Assumptions!Q53 -> 1 | R76: =Assumptions!R53 -> 1 | S76: =Assumptions!S53 -> 1 | T76: =Assumptions!T53 -> 1 | ... BT76: =Assumptions!BT53 -> 2
A77: =Assumptions!A54 -> Legal | M77: =Assumptions!M54 -> 0 | N77: =Assumptions!N54 -> 0 | O77: =Assumptions!O54 -> 0 | P77: =Assumptions!P54 -> 0 | Q77: =Assumptions!Q54 -> 0 | R77: =Assumptions!R54 -> 0 | S77: =Assumptions!S54 -> 0 | T77: =Assumptions!T54 -> 0 | ... BT77: =Assumptions!BT54 -> 1
A78: =Assumptions!A55 -> HR | M78: =Assumptions!M55 -> 0 | N78: =Assumptions!N55 -> 0 | O78: =Assumptions!O55 -> 0 | P78: =Assumptions!P55 -> 0 | Q78: =Assumptions!Q55 -> 0 | R78: =Assumptions!R55 -> 0 | S78: =Assumptions!S55 -> 0 | T78: =Assumptions!T55 -> 0 | ... BT78: =Assumptions!BT55 -> 2
A79: Product Development | M79: =SUM(M80) -> 4 | N79: =SUM(N80) -> 4 | O79: =SUM(O80) -> 4 | P79: =SUM(P80) -> 4 | Q79: =SUM(Q80) -> 4 | R79: =SUM(R80) -> 4 | S79: =SUM(S80) -> 5 | T79: =SUM(T80) -> 5 | ... BT79: =SUM(BT80) -> 10
A80: =Assumptions!A59 -> Product Developemt Team | M80: =Assumptions!M59 -> 4 | N80: =Assumptions!N59 -> 4 | O80: =Assumptions!O59 -> 4 | P80: =Assumptions!P59 -> 4 | Q80: =Assumptions!Q59 -> 4 | R80: =Assumptions!R59 -> 4 | S80: =Assumptions!S59 -> 5 | T80: =Assumptions!T59 -> 5 | ... BT80: =Assumptions!BT59 -> 10
A81: Customer Support Team | M81: =M15 -> 1 | N81: =N15 -> 1 | O81: =O15 -> 1 | P81: =P15 -> 1 | Q81: =Q15 -> 2 | R81: =R15 -> 2 | S81: =S15 -> 2 | T81: =T15 -> 2 | ... BT81: =BT15 -> 70
A82: Total Headcount | M82: =M67+M70+M75+M79+M81 -> 10 | N82: =N67+N70+N75+N79+N81 -> 10 | O82: =O67+O70+O75+O79+O81 -> 10 | P82: =P67+P70+P75+P79+P81 -> 11 | Q82: =Q67+Q70+Q75+Q79+Q81 -> 12 | R82: =R67+R70+R75+R79+R81 -> 12 | S82: =S67+S70+S75+S79+S81 -> 16 | T82: =T67+T70+T75+T79+T81 -> 16 | ... BT82: =BT67+BT70+BT75+BT79+BT81 -> 139

Sheet FAS
A1: Fixed Asset Schedule
A2: Cells in Orange are assumptions | M2: MONTHLY | BV2: YEARLY
A3: Year | M3: 1 | N3: 1 | O3: 1 | P3: 1 | Q3: 1 | R3: 1 | S3: 1 | T3: 1 | U3: 1 | V3: 1 | W3: 1 | X3: 1 | Y3: =X3+1 -> 2 | Z3: =Y3 -> 2 | AA3: =Z3 -> 2 | AB3: =AA3 -> 2 | AC3: =AB3 -> 2 | AD3: =AC3 -> 2 | AE3: =AD3 -> 2 | AF3: =AE3 -> 2 | AG3: =AF3 -> 2 | ... AJ3: =AI3 -> 2 | AK3: 3 | AL3: 3 | AM3: 3 | AN3: 3 | AO3: 3 | AP3: 3 | AQ3: 3 | AR3: 3 | AS3: 3 | AT3: 3 | AU3: 3 | AV3: 3 | AW3: 4 | AX3: 4 | AY3: 4 | AZ3: 4 | BA3: 4 | BB3: 4 | BC3: 4 | BD3: 4 | BE3: 4 | BF3: 4 | BG3: 4 | BH3: 4 | BI3: 5 | BJ3: 5 | BK3: 5 | BL3: 5 | BM3: 5 | BN3: 5 | BO3: 5 | BP3: 5 | BQ3: 5 | BR3: 5 | BS3: 5 | BT3: 5 | BV3: 1 | BW3: 2 | BX3: 3 | BY3: 4 | BZ3: 5
A4: Months | M4: 1 | N4: =M4+1 -> 2 | O4: =N4+1 -> 3 | P4: =O4+1 -> 4 | Q4: =P4+1 -> 5 | R4: =Q4+1 -> 6 | S4: =R4+1 -> 7 | T4: =S4+1 -> 8 | U4: =T4+1 -> 9 | ... BT4: =BS4+1 -> 60 | BV4: 12 | BW4: 24 | BX4: 36 | BY4: 48 | BZ4: 60

Sheet IS
A1: Income Statement
A2: Cells in Orange are assumptions | M2: MONTHLY | BV2: YEARLY | CB2: Commonsize Statement
A3: Year | M3: 1 | N3: 1 | O3: 1 | P3: 1 | Q3: 1 | R3: 1 | S3: 1 | T3: 1 | U3: 1 | V3: 1 | W3: 1 | X3: 1 | Y3: =X3+1 -> 2 | Z3: =Y3 -> 2 | AA3: =Z3 -> 2 | AB3: =AA3 -> 2 | AC3: =AB3 -> 2 | AD3: =AC3 -> 2 | AE3: =AD3 -> 2 | AF3: =AE3 -> 2 | AG3: =AF3 -> 2 | ... AJ3: =AI3 -> 2 | AK3: 3 | AL3: 3 | AM3: 3 | AN3: 3 | AO3: 3 | AP3: 3 | AQ3: 3 | AR3: 3 | AS3: 3 | AT3: 3 | AU3: 3 | AV3: 3 | AW3: 4 | AX3: 4 | AY3: 4 | AZ3: 4 | BA3: 4 | BB3: 4 | BC3: 4 | BD3: 4 | BE3: 4 | BF3: 4 | BG3: 4 | BH3: 4 | BI3: 5 | BJ3: 5 | BK3: 5 | BL3: 5 | BM3: 5 | BN3: 5 | BO3: 5 | BP3: 5 | BQ3: 5 | BR3: 5 | BS3: 5 | BT3: 5 | BV3: 1 | BW3: 2 | BX3: 3 | BY3: 4 | BZ3: 5 | CB3: 1 | CC3: 2 | CD3: 3 | CE3: 4 | CF3: 5
A4: Months | M4: 1 | N4: =M4+1 -> 2 | O4: =N4+1 -> 3 | P4: =O4+1 -> 4 | Q4: =P4+1 -> 5 | R4: =Q4+1 -> 6 | S4: =R4+1 -> 7 | T4: =S4+1 -> 8 | U4: =T4+1 -> 9 | ... BT4: =BS4+1 -> 60 | BV4: 12 | BW4: 24 | BX4: 36 | BY4: 48 | BZ4: 60 | CB4: 12 | CC4: 24 | CD4: 36 | CE4: 48 | CF4: 60
A5: Revenues
B6: Bookings | M6: ='Revenue Buildup'!M18 -> 480000 | N6: ='Revenue Buildup'!N18 -> 480000 | O6: ='Revenue Buildup'!O18 -> 480000 | P6: ='Revenue Buildup'!P18 -> 720000 | Q6: ='Revenue Buildup'!Q18 -> 720000 | R6: ='Revenue Buildup'!R18 -> 720000 | S6: ='Revenue Buildup'!S18 -> 1560000 | T6: ='Revenue Buildup'!T18 -> 1560000 | ... BT6: ='Revenue Buildup'!BT18 -> 20352000 | BV6: =SUMIF($M$3:$BT$3,BV$3,$M6:$BT6) -> 15120000 | BW6: =SUMIF($M$3:$BT$3,BW$3,$M6:$BT6) -> 66888000 | BX6: =SUMIF($M$3:$BT$3,BX$3,$M6:$BT6) -> 133920000 | BY6: =SUMIF($M$3:$BT$3,BY$3,$M6:$BT6) -> 188064000 | BZ6: =SUMIF($M$3:$BT$3,BZ$3,$M6:$BT6) -> 234432000
A7: [+] | B7: Revenue | M7: ='Revenue Buildup'!M20 -> 40000 | N7: ='Revenue Buildup'!N20 -> 80000 | O7: ='Revenue Buildup'!O20 -> 120000 | P7: ='Revenue Buildup'!P20 -> 180000 | Q7: ='Revenue Buildup'!Q20 -> 240000 | R7: ='Revenue Buildup'!R20 -> 300000 | S7: ='Revenue Buildup'!S20 -> 430000 | T7: ='Revenue Buildup'!T20 -> 560000 | ... BT7: ='Revenue Buildup'!BT20 -> 19536000 | BV7: =SUMIF($M$3:$BT$3,BV$3,$M7:$BT7) -> 5850000 | BW7: =SUMIF($M$3:$BT$3,BW$3,$M7:$BT7) -> 37896000 | BX7: =SUMIF($M$3:$BT$3,BX$3,$M7:$BT7) -> 105024000 | BY7: =SUMIF($M$3:$BT$3,BY$3,$M7:$BT7) -> 167100000 | BZ7: =SUMIF($M$3:$BT$3,BZ$3,$M7:$BT7) -> 213000000 | CB7: =BV7/BV$7 -> 1 | CC7: =BW7/BW$7 -> 1 | CD7: =BX7/BX$7 -> 1 | CE7: =BY7/BY$7 -> 1 | CF7: =BZ7/BZ$7 -> 1
A8: Direct Expenses | BW8: =BW7/BV7-1 -> 5.4779487 | BX8: =BX7/BW7-1 -> 1.7713743 | BY8: =BY7/BX7-1 -> 0.5910649 | BZ8: =BZ7/BY7-1 -> 0.27468582
A9: [-] | B9: ='Cost Buildup'!A6 -> Hosting & Infrastructure Costs | M9: ='Cost Buildup'!M6 -> 62580 | N9: ='Cost Buildup'!N6 -> 71907.458 | O9: ='Cost Buildup'!O6 -> 81234.915 | P9: ='Cost Buildup'!P6 -> 90562.373 | Q9: ='Cost Buildup'!Q6 -> 99889.831 | R9: ='Cost Buildup'!R6 -> 109217.29 | S9: ='Cost Buildup'!S6 -> 118544.75 | T9: ='Cost Buildup'!T6 -> 127872.2 | ... BT9: ='Cost Buildup'!BT6 -> 612900 | BV9: =SUMIF($M$3:$BT$3,BV$3,$M9:$BT9) -> 1366572.2 | BW9: =SUMIF($M$3:$BT$3,BW$3,$M9:$BT9) -> 2709726.1 | BX9: =SUMIF($M$3:$BT$3,BX$3,$M9:$BT9) -> 4052880 | BY9: =SUMIF($M$3:$BT$3,BY$3,$M9:$BT9) -> 5396033.9 | BZ9: =SUMIF($M$3:$BT$3,BZ$3,$M9:$BT9) -> 6739187.8 | CB9: =BV9/BV$7 -> 0.23360209 | CC9: =BW9/BW$7 -> 0.071504278 | CD9: =BX9/BX$7 -> 0.038590037 | CE9: =BY9/BY$7 -> 0.032292244 | CF9: =BZ9/BZ$7 -> 0.031639379
A10: [-] | B10: ='Cost Buildup'!A10 -> Third-Party Software & API Costs | M10: ='Cost Buildup'!M10 -> 12200 | N10: ='Cost Buildup'!N10 -> 12538.983 | O10: ='Cost Buildup'!O10 -> 12877.966 | P10: ='Cost Buildup'!P10 -> 16816.949 | Q10: ='Cost Buildup'!Q10 -> 17155.932 | R10: ='Cost Buildup'!R10 -> 17494.915 | S10: ='Cost Buildup'!S10 -> 30433.898 | T10: ='Cost Buildup'!T10 -> 30772.881 | ... BT10: ='Cost Buildup'!BT10 -> 330280 | BV10: =SUMIF($M$3:$BT$3,BV$3,$M10:$BT10) -> 309172.88 | BW10: =SUMIF($M$3:$BT$3,BW$3,$M10:$BT10) -> 1134506.4 | BX10: =SUMIF($M$3:$BT$3,BX$3,$M10:$BT10) -> 2188800 | BY10: =SUMIF($M$3:$BT$3,BY$3,$M10:$BT10) -> 3049773.6 | BZ10: =SUMIF($M$3:$BT$3,BZ$3,$M10:$BT10) -> 3794107.1 | CB10: =BV10/BV$7 -> 0.052850065 | CC10: =BW10/BW$7 -> 0.029937366 | CD10: =BX10/BX$7 -> 0.020840951 | CE10: =BY10/BY$7 -> 0.018251188 | CF10: =BZ10/BZ$7 -> 0.017812709
A11: [-] | B11: ='Cost Buildup'!A17 -> Customer Support | M11: ='Cost Buildup'!M17 -> 40000 | N11: ='Cost Buildup'!N17 -> 40000 | O11: ='Cost Buildup'!O17 -> 40000 | P11: ='Cost Buildup'!P17 -> 40000 | Q11: ='Cost Buildup'!Q17 -> 80000 | R11: ='Cost Buildup'!R17 -> 80000 | S11: ='Cost Buildup'!S17 -> 80000 | T11: ='Cost Buildup'!T17 -> 80000 | ... BT11: ='Cost Buildup'!BT17 -> 4099480 | BV11: =SUMIF($M$3:$BT$3,BV$3,$M11:$BT11) -> 1040000 | BW11: =SUMIF($M$3:$BT$3,BW$3,$M11:$BT11) -> 4664000 | BX11: =SUMIF($M$3:$BT$3,BX$3,$M11:$BT11) -> 13261600 | BY11: =SUMIF($M$3:$BT$3,BY$3,$M11:$BT11) -> 25022800 | BZ11: =SUMIF($M$3:$BT$3,BZ$3,$M11:$BT11) -> 41756132 | CB11: =BV11/BV$7 -> 0.17777778 | CC11: =BW11/BW$7 -> 0.12307368 | CD11: =BX11/BX$7 -> 0.12627209 | CE11: =BY11/BY$7 -> 0.14974746 | CF11: =BZ11/BZ$7 -> 0.19603818
A12: COGS | M12: =SUM(M9:M11) -> 114780 | N12: =SUM(N9:N11) -> 124446.44 | O12: =SUM(O9:O11) -> 134112.88 | P12: =SUM(P9:P11) -> 147379.32 | Q12: =SUM(Q9:Q11) -> 197045.76 | R12: =SUM(R9:R11) -> 206712.2 | S12: =SUM(S9:S11) -> 228978.64 | T12: =SUM(T9:T11) -> 238645.08 | ... BT12: =SUM(BT9:BT11) -> 5042660 | BV12: =SUMIF($M$3:$BT$3,BV$3,$M12:$BT12) -> 2715745.1 | BW12: =SUMIF($M$3:$BT$3,BW$3,$M12:$BT12) -> 8508232.5 | BX12: =SUMIF($M$3:$BT$3,BX$3,$M12:$BT12) -> 19503280 | BY12: =SUMIF($M$3:$BT$3,BY$3,$M12:$BT12) -> 33468607 | BZ12: =SUMIF($M$3:$BT$3,BZ$3,$M12:$BT12) -> 52289427 | CB12: =BV12/BV$7 -> 0.46422993 | CC12: =BW12/BW$7 -> 0.22451532 | CD12: =BX12/BX$7 -> 0.18570308 | CE12: =BY12/BY$7 -> 0.20029089 | CF12: =BZ12/BZ$7 -> 0.24549027
B13: Gross Profit | M13: =M7-M12 -> -74780 | N13: =N7-N12 -> -44446.441 | O13: =O7-O12 -> -14112.881 | P13: =P7-P12 -> 32620.678 | Q13: =Q7-Q12 -> 42954.237 | R13: =R7-R12 -> 93287.797 | S13: =S7-S12 -> 201021.36 | T13: =T7-T12 -> 321354.92 | ... BT13: =BT7-BT12 -> 14493340 | BV13: =BV7-BV12 -> 3134254.9 | BW13: =BW7-BW12 -> 29387767 | BX13: =BX7-BX12 -> 85520720 | BY13: =BY7-BY12 -> 1.3363139e+08 | BZ13: =BZ7-BZ12 -> 1.6071057e+08 | CB13: =BV13/BV$7 -> 0.53577007 | CC13: =BW13/BW$7 -> 0.77548468 | CD13: =BX13/BX$7 -> 0.81429692 | CE13: =BY13/BY$7 -> 0.79970911 | CF13: =BZ13/BZ$7 -> 0.75450973
B14: Gross Profit % | M14: =M13/M$7 -> -1.8695 | N14: =N13/N$7 -> -0.55558051 | O14: =O13/O$7 -> -0.11760734 | P14: =P13/P$7 -> 0.18122599 | Q14: =Q13/Q$7 -> 0.17897599 | R14: =R13/R$7 -> 0.31095932 | S14: =S13/S$7 -> 0.46749153 | T14: =T13/T$7 -> 0.57384806 | ... BT14: =BT13/BT$7 -> 0.74187858 | BV14: =BV13/BV$7 -> 0.53577007 | BW14: =BW13/BW$7 -> 0.77548468 | BX14: =BX13/BX$7 -> 0.81429692 | BY14: =BY13/BY$7 -> 0.79970911 | BZ14: =BZ13/BZ$7 -> 0.75450973
A15: Operating Expenses
A16: [+] | B16: Sales & Marketing | M16: ='Cost Buildup'!M22+'Cost Buildup'!M32 -> 198000 | N16: ='Cost Buildup'!N22+'Cost Buildup'!N32 -> 198000 | O16: ='Cost Buildup'!O22+'Cost Buildup'!O32 -> 198000 | P16: ='Cost Buildup'!P22+'Cost Buildup'!P32 -> 322000 | Q16: ='Cost Buildup'!Q22+'Cost Buildup'!Q32 -> 322000 | R16: ='Cost Buildup'!R22+'Cost Buildup'!R32 -> 322000 | S16: ='Cost Buildup'!S22+'Cost Buildup'!S32 -> 656000 | T16: ='Cost Buildup'!T22+'Cost Buildup'!T32 -> 656000 | ... BT16: ='Cost Buildup'!BT22+'Cost Buildup'!BT32 -> 5443600 | BV16: =SUMIF($M$3:$BT$3,BV$3,$M16:$BT16) -> 6462000 | BW16: =SUMIF($M$3:$BT$3,BW$3,$M16:$BT16) -> 23951400 | BX16: =SUMIF($M$3:$BT$3,BX$3,$M16:$BT16) -> 39579000 | BY16: =SUMIF($M$3:$BT$3,BY$3,$M16:$BT16) -> 51343200 | BZ16: =SUMIF($M$3:$BT$3,BZ$3,$M16:$BT16) -> 62880600 | CB16: =BV16/BV$7 -> 1.1046154 | CC16: =BW16/BW$7 -> 0.63202977 | CD16: =BX16/BX$7 -> 0.37685672 | CE16: =BY16/BY$7 -> 0.30726032 | CF16: =BZ16/BZ$7 -> 0.29521408
A17: [+] | B17: G&A | M17: =SUM('Cost Buildup'!M52:M53) -> 90000 | N17: =SUM('Cost Buildup'!N52:N53) -> 90515.937 | O17: =SUM('Cost Buildup'!O52:O53) -> 91031.875 | P17: =SUM('Cost Buildup'!P52:P53) -> 100702.59 | Q17: =SUM('Cost Buildup'!Q52:Q53) -> 110476.5 | R17: =SUM('Cost Buildup'!R52:R53) -> 111095.62 | S17: =SUM('Cost Buildup'!S52:S53) -> 148953 | T17: =SUM('Cost Buildup'!T52:T53) -> 149778.5 | ... BT17: =SUM('Cost Buildup'!BT52:BT53) -> 1674120.2 | BV17: =SUMIF($M$3:$BT$3,BV$3,$M17:$BT17) -> 1642610.5 | BW17: =SUMIF($M$3:$BT$3,BW$3,$M17:$BT17) -> 4785088.6 | BX17: =SUMIF($M$3:$BT$3,BX$3,$M17:$BT17) -> 9461306.8 | BY17: =SUMIF($M$3:$BT$3,BY$3,$M17:$BT17) -> 13204885 | BZ17: =SUMIF($M$3:$BT$3,BZ$3,$M17:$BT17) -> 17927058 | CB17: =BV17/BV$7 -> 0.28078812 | CC17: =BW17/BW$7 -> 0.12626896 | CD17: =BX17/BX$7 -> 0.090087093 | CE17: =BY17/BY$7 -> 0.079023849 | CF17: =BZ17/BZ$7 -> 0.08416459
A18: [+] | B18: Product Development | M18: ='Cost Buildup'!M61 -> 10000 | N18: ='Cost Buildup'!N61 -> 11525.424 | O18: ='Cost Buildup'!O61 -> 13050.847 | P18: ='Cost Buildup'!P61 -> 14576.271 | Q18: ='Cost Buildup'!Q61 -> 16101.695 | R18: ='Cost Buildup'!R61 -> 17627.119 | S18: ='Cost Buildup'!S61 -> 19152.542 | T18: ='Cost Buildup'!T61 -> 20677.966 | ... BT18: ='Cost Buildup'!BT61 -> 100000 | BV18: =SUMIF($M$3:$BT$3,BV$3,$M18:$BT18) -> 220677.97 | BW18: =SUMIF($M$3:$BT$3,BW$3,$M18:$BT18) -> 440338.98 | BX18: =SUMIF($M$3:$BT$3,BX$3,$M18:$BT18) -> 660000 | BY18: =SUMIF($M$3:$BT$3,BY$3,$M18:$BT18) -> 879661.02 | BZ18: =SUMIF($M$3:$BT$3,BZ$3,$M18:$BT18) -> 1099322 | CB18: =BV18/BV$7 -> 0.037722729 | CC18: =BW18/BW$7 -> 0.011619669 | CD18: =BX18/BX$7 -> 0.0062842779 | CE18: =BY18/BY$7 -> 0.005264279 | CF18: =BZ18/BZ$7 -> 0.0051611363
A19: [+] | B19: Empolyees Benefit Expense | M19: =SUM(M20:M23) -> 505000 | N19: =SUM(N20:N23) -> 505000 | O19: =SUM(O20:O23) -> 505000 | P19: =SUM(P20:P23) -> 555000 | Q19: =SUM(Q20:Q23) -> 555000 | R19: =SUM(R20:R23) -> 555000 | S19: =SUM(S20:S23) -> 785000 | T19: =SUM(T20:T23) -> 785000 | ... BT19: =SUM(BT20:BT23) -> 6611243.6 | BV19: =SUMIF($M$3:$BT$3,BV$3,$M19:$BT19) -> 8340000 | BW19: =SUMIF($M$3:$BT$3,BW$3,$M19:$BT19) -> 23839500 | BX19: =SUMIF($M$3:$BT$3,BX$3,$M19:$BT19) -> 46023000 | BY19: =SUMIF($M$3:$BT$3,BY$3,$M19:$BT19) -> 59952892 | BZ19: =SUMIF($M$3:$BT$3,BZ$3,$M19:$BT19) -> 77760818 | CB19: =BV19/BV$7 -> 1.425641 | CC19: =BW19/BW$7 -> 0.62907695 | CD19: =BX19/BX$7 -> 0.43821412 | CE19: =BY19/BY$7 -> 0.35878452 | CF19: =BZ19/BZ$7 -> 0.36507426
A20: [+] | B20: Sales | M20: ='Cost Buildup'!M41 -> 100000 | N20: ='Cost Buildup'!N41 -> 100000 | O20: ='Cost Buildup'!O41 -> 100000 | P20: ='Cost Buildup'!P41 -> 150000 | Q20: ='Cost Buildup'!Q41 -> 150000 | R20: ='Cost Buildup'!R41 -> 150000 | S20: ='Cost Buildup'!S41 -> 320000 | T20: ='Cost Buildup'!T41 -> 320000 | ... BT20: ='Cost Buildup'!BT41 -> 3987734.2 | BV20: =SUMIF($M$3:$BT$3,BV$3,$M20:$BT20) -> 3120000 | BW20: =SUMIF($M$3:$BT$3,BW$3,$M20:$BT20) -> 11971500 | BX20: =SUMIF($M$3:$BT$3,BX$3,$M20:$BT20) -> 22218000 | BY20: =SUMIF($M$3:$BT$3,BY$3,$M20:$BT20) -> 32577142 | BZ20: =SUMIF($M$3:$BT$3,BZ$3,$M20:$BT20) -> 46278705 | CB20: =BV20/BV$7 -> 0.53333333 | CC20: =BW20/BW$7 -> 0.31590405 | CD20: =BX20/BX$7 -> 0.21155165 | CE20: =BY20/BY$7 -> 0.19495597 | CF20: =BZ20/BZ$7 -> 0.21727092
A21: [+] | B21: Marketing | M21: ='Cost Buildup'!M49 -> 125000 | N21: ='Cost Buildup'!N49 -> 125000 | O21: ='Cost Buildup'!O49 -> 125000 | P21: ='Cost Buildup'!P49 -> 125000 | Q21: ='Cost Buildup'!Q49 -> 125000 | R21: ='Cost Buildup'!R49 -> 125000 | S21: ='Cost Buildup'!S49 -> 125000 | T21: ='Cost Buildup'!T49 -> 125000 | ... BT21: ='Cost Buildup'!BT49 -> 1136854.1 | BV21: =SUMIF($M$3:$BT$3,BV$3,$M21:$BT21) -> 1500000 | BW21: =SUMIF($M$3:$BT$3,BW$3,$M21:$BT21) -> 4140000 | BX21: =SUMIF($M$3:$BT$3,BX$3,$M21:$BT21) -> 10315500 | BY21: =SUMIF($M$3:$BT$3,BY$3,$M21:$BT21) -> 11862825 | BZ21: =SUMIF($M$3:$BT$3,BZ$3,$M21:$BT21) -> 13642249 | CB21: =BV21/BV$7 -> 0.25641026 | CC21: =BW21/BW$7 -> 0.10924636 | CD21: =BX21/BX$7 -> 0.098220407 | CE21: =BY21/BY$7 -> 0.07099237 | CF21: =BZ21/BZ$7 -> 0.064048116
A22: [+] | B22: G&A | M22: ='Cost Buildup'!M58 -> 40000 | N22: ='Cost Buildup'!N58 -> 40000 | O22: ='Cost Buildup'!O58 -> 40000 | P22: ='Cost Buildup'!P58 -> 40000 | Q22: ='Cost Buildup'!Q58 -> 40000 | R22: ='Cost Buildup'!R58 -> 40000 | S22: ='Cost Buildup'!S58 -> 40000 | T22: ='Cost Buildup'!T58 -> 40000 | ... BT22: ='Cost Buildup'!BT58 -> 437251.56 | BV22: =SUMIF($M$3:$BT$3,BV$3,$M22:$BT22) -> 480000 | BW22: =SUMIF($M$3:$BT$3,BW$3,$M22:$BT22) -> 1932000 | BX22: =SUMIF($M$3:$BT$3,BX$3,$M22:$BT22) -> 3967500 | BY22: =SUMIF($M$3:$BT$3,BY$3,$M22:$BT22) -> 4562625 | BZ22: =SUMIF($M$3:$BT$3,BZ$3,$M22:$BT22) -> 5247018.7 | CB22: =BV22/BV$7 -> 0.082051282 | CC22: =BW22/BW$7 -> 0.050981634 | CD22: =BX22/BX$7 -> 0.03777708 | CE22: =BY22/BY$7 -> 0.027304758 | CF22: =BZ22/BZ$7 -> 0.024633891
A23: [+] | B23: Product Development | M23: ='Cost Buildup'!M63 -> 240000 | N23: ='Cost Buildup'!N63 -> 240000 | O23: ='Cost Buildup'!O63 -> 240000 | P23: ='Cost Buildup'!P63 -> 240000 | Q23: ='Cost Buildup'!Q63 -> 240000 | R23: ='Cost Buildup'!R63 -> 240000 | S23: ='Cost Buildup'!S63 -> 300000 | T23: ='Cost Buildup'!T63 -> 300000 | ... BT23: ='Cost Buildup'!BT63 -> 1049403.7 | BV23: =SUMIF($M$3:$BT$3,BV$3,$M23:$BT23) -> 3240000 | BW23: =SUMIF($M$3:$BT$3,BW$3,$M23:$BT23) -> 5796000 | BX23: =SUMIF($M$3:$BT$3,BX$3,$M23:$BT23) -> 9522000 | BY23: =SUMIF($M$3:$BT$3,BY$3,$M23:$BT23) -> 10950300 | BZ23: =SUMIF($M$3:$BT$3,BZ$3,$M23:$BT23) -> 12592845 | CB23: =BV23/BV$7 -> 0.55384615 | CC23: =BW23/BW$7 -> 0.1529449 | CD23: =BX23/BX$7 -> 0.090664991 | CE23: =BY23/BY$7 -> 0.065531418 | CF23: =BZ23/BZ$7 -> 0.059121338
A24: Total Operating Expense | M24: =SUM(M16:M19) -> 803000 | N24: =SUM(N16:N19) -> 805041.36 | O24: =SUM(O16:O19) -> 807082.72 | P24: =SUM(P16:P19) -> 992278.86 | Q24: =SUM(Q16:Q19) -> 1003578.2 | R24: =SUM(R16:R19) -> 1005722.7 | S24: =SUM(S16:S19) -> 1609105.5 | T24: =SUM(T16:T19) -> 1611456.5 | ... BT24: =SUM(BT16:BT19) -> 13828964 | BV24: =SUMIF($M$3:$BT$3,BV$3,$M24:$BT24) -> 16665288 | BW24: =SUMIF($M$3:$BT$3,BW$3,$M24:$BT24) -> 53016328 | BX24: =SUMIF($M$3:$BT$3,BX$3,$M24:$BT24) -> 95723307 | BY24: =SUMIF($M$3:$BT$3,BY$3,$M24:$BT24) -> 1.2538064e+08 | BZ24: =SUMIF($M$3:$BT$3,BZ$3,$M24:$BT24) -> 1.596678e+08 | CB24: =BV24/BV$7 -> 2.8487673 | CC24: =BW24/BW$7 -> 1.3989953 | CD24: =BX24/BX$7 -> 0.91144221 | CE24: =BY24/BY$7 -> 0.75033297 | CF24: =BZ24/BZ$7 -> 0.74961407
B26: EBITDA | M26: =M13-M24 -> -877780 | N26: =N13-N24 -> -849487.8 | O26: =O13-O24 -> -821195.6 | P26: =P13-P24 -> -959658.19 | Q26: =Q13-Q24 -> -960623.96 | R26: =R13-R24 -> -912434.95 | S26: =S13-S24 -> -1408084.2 | T26: =T13-T24 -> -1290101.5 | ... BT26: =BT13-BT24 -> 664376.18 | BV26: =BV13-BV24 -> -13531034 | BW26: =BW13-BW24 -> -23628560 | BX26: =BX13-BX24 -> -10202587 | BY26: =BY13-BY24 -> 8250753.9 | BZ26: =BZ13-BZ24 -> 1042775.4 | CB26: =BV26/BV$7 -> -2.3129972 | CC26: =BW26/BW$7 -> -0.62351066 | CD26: =BX26/BX$7 -> -0.097145289 | CE26: =BY26/BY$7 -> 0.049376145 | CF26: =BZ26/BZ$7 -> 0.0048956594
B27: EBITDA% | M27: =M26/M$7 -> -21.9445 | N27: =N26/N$7 -> -10.618598 | O27: =O26/O$7 -> -6.8432967 | P27: =P26/P$7 -> -5.3314344 | Q27: =Q26/Q$7 -> -4.0025998 | R27: =R26/R$7 -> -3.0414498 | S27: =S26/S$7 -> -3.2746144 | T27: =T26/T$7 -> -2.3037528 | ... BT27: =BT26/BT$7 -> 0.03400779 | BV27: =BV26/BV$7 -> -2.3129972 | BW27: =BW26/BW$7 -> -0.62351066 | BX27: =BX26/BX$7 -> -0.097145289 | BY27: =BY26/BY$7 -> 0.049376145 | BZ27: =BZ26/BZ$7 -> 0.0048956594
A29: [-] | B29: Depreciation and Amortization | BV29: =SUMIF($M$3:$BT$3,BV$3,$M29:$BT29) -> 0 | BW29: =SUMIF($M$3:$BT$3,BW$3,$M29:$BT29) -> 0 | BX29: =SUMIF($M$3:$BT$3,BX$3,$M29:$BT29) -> 0 | BY29: =SUMIF($M$3:$BT$3,BY$3,$M29:$BT29) -> 0 | BZ29: =SUMIF($M$3:$BT$3,BZ$3,$M29:$BT29) -> 0 | CB29: =BV29/BV$7 -> 0 | CC29: =BW29/BW$7 -> 0 | CD29: =BX29/BX$7 -> 0 | CE29: =BY29/BY$7 -> 0 | CF29: =BZ29/BZ$7 -> 0
A30: [-] | B30: Interest Expense | BV30: =SUMIF($M$3:$BT$3,BV$3,$M30:$BT30) -> 0 | BW30: =SUMIF($M$3:$BT$3,BW$3,$M30:$BT30) -> 0 | BX30: =SUMIF($M$3:$BT$3,BX$3,$M30:$BT30) -> 0 | BY30: =SUMIF($M$3:$BT$3,BY$3,$M30:$BT30) -> 0 | BZ30: =SUMIF($M$3:$BT$3,BZ$3,$M30:$BT30) -> 0 | CB30: =BV30/BV$7 -> 0 | CC30: =BW30/BW$7 -> 0 | CD30: =BX30/BX$7 -> 0 | CE30: =BY30/BY$7 -> 0 | CF30: =BZ30/BZ$7 -> 0
B32: EBT | M32: =M26-M29-M30 -> -877780 | N32: =N26-N29-N30 -> -849487.8 | O32: =O26-O29-O30 -> -821195.6 | P32: =P26-P29-P30 -> -959658.19 | Q32: =Q26-Q29-Q30 -> -960623.96 | R32: =R26-R29-R30 -> -912434.95 | S32: =S26-S29-S30 -> -1408084.2 | T32: =T26-T29-T30 -> -1290101.5 | ... BT32: =BT26-BT29-BT30 -> 664376.18 | BV32: =BV26-BV29-BV30 -> -13531034 | BW32: =BW26-BW29-BW30 -> -23628560 | BX32: =BX26-BX29-BX30 -> -10202587 | BY32: =BY26-BY29-BY30 -> 8250753.9 | BZ32: =BZ26-BZ29-BZ30 -> 1042775.4 | CB32: =BV32/BV$7 -> -2.3129972 | CC32: =BW32/BW$7 -> -0.62351066 | CD32: =BX32/BX$7 -> -0.097145289 | CE32: =BY32/BY$7 -> 0.049376145 | CF32: =BZ32/BZ$7 -> 0.0048956594
B33: EBT % | M33: =M32/M$7 -> -21.9445 | N33: =N32/N$7 -> -10.618598 | O33: =O32/O$7 -> -6.8432967 | P33: =P32/P$7 -> -5.3314344 | Q33: =Q32/Q$7 -> -4.0025998 | R33: =R32/R$7 -> -3.0414498 | S33: =S32/S$7 -> -3.2746144 | T33: =T32/T$7 -> -2.3037528 | ... BT33: =BT32/BT$7 -> 0.03400779 | BV33: =BV32/BV$7 -> -2.3129972 | BW33: =BW32/BW$7 -> -0.62351066 | BX33: =BX32/BX$7 -> -0.097145289 | BY33: =BY32/BY$7 -> 0.049376145 | BZ33: =BZ32/BZ$7 -> 0.0048956594
A34: [-] | B34: Tax Expense | F34: 0.25 | BV34: =SUMIF($M$3:$BT$3,BV$3,$M34:$BT34) -> 0 | BW34: =SUMIF($M$3:$BT$3,BW$3,$M34:$BT34) -> 0 | BX34: =SUMIF($M$3:$BT$3,BX$3,$M34:$BT34) -> 0 | BY34: =SUMIF($M$3:$BT$3,BY$3,$M34:$BT34) -> 0 | BZ34: =SUMIF($M$3:$BT$3,BZ$3,$M34:$BT34) -> 0 | CB34: =BV34/BV$7 -> 0 | CC34: =BW34/BW$7 -> 0 | CD34: =BX34/BX$7 -> 0 | CE34: =BY34/BY$7 -> 0 | CF34: =BZ34/BZ$7 -> 0
B36: EAT | M36: =M32-M34 -> -877780 | N36: =N32-N34 -> -849487.8 | O36: =O32-O34 -> -821195.6 | P36: =P32-P34 -> -959658.19 | Q36: =Q32-Q34 -> -960623.96 | R36: =R32-R34 -> -912434.95 | S36: =S32-S34 -> -1408084.2 | T36: =T32-T34 -> -1290101.5 | ... BT36: =BT32-BT34 -> 664376.18 | BV36: =BV32-BV34 -> -13531034 | BW36: =BW32-BW34 -> -23628560 | BX36: =BX32-BX34 -> -10202587 | BY36: =BY32-BY34 -> 8250753.9 | BZ36: =BZ32-BZ34 -> 1042775.4 | CB36: =BV36/BV$7 -> -2.3129972 | CC36: =BW36/BW$7 -> -0.62351066 | CD36: =BX36/BX$7 -> -0.097145289 | CE36: =BY36/BY$7 -> 0.049376145 | CF36: =BZ36/BZ$7 -> 0.0048956594
B37: EAT% | M37: =M36/M$7 -> -21.9445 | N37: =N36/N$7 -> -10.618598 | O37: =O36/O$7 -> -6.8432967 | P37: =P36/P$7 -> -5.3314344 | Q37: =Q36/Q$7 -> -4.0025998 | R37: =R36/R$7 -> -3.0414498 | S37: =S36/S$7 -> -3.2746144 | T37: =T36/T$7 -> -2.3037528 | ... BT37: =BT36/BT$7 -> 0.03400779 | BV37: =BV36/BV$7 -> -2.3129972 | BW37: =BW36/BW$7 -> -0.62351066 | BX37: =BX36/BX$7 -> -0.097145289 | BY37: =BY36/BY$7 -> 0.049376145 | BZ37: =BZ36/BZ$7 -> 0.0048956594
A40: Treatment of Tax
A41: Taxable Income
A42: Cumulative Taxable Imcome

Sheet BS
A1: Balance Sheet
A2: Cells in Orange are assumptions | M2: MONTHLY | BV2: YEARLY
A3: Year | M3: 1 | N3: 1 | O3: 1 | P3: 1 | Q3: 1 | R3: 1 | S3: 1 | T3: 1 | U3: 1 | V3: 1 | W3: 1 | X3: 1 | Y3: =X3+1 -> 2 | Z3: =Y3 -> 2 | AA3: =Z3 -> 2 | AB3: =AA3 -> 2 | AC3: =AB3 -> 2 | AD3: =AC3 -> 2 | AE3: =AD3 -> 2 | AF3: =AE3 -> 2 | AG3: =AF3 -> 2 | ... AJ3: =AI3 -> 2 | AK3: 3 | AL3: 3 | AM3: 3 | AN3: 3 | AO3: 3 | AP3: 3 | AQ3: 3 | AR3: 3 | AS3: 3 | AT3: 3 | AU3: 3 | AV3: 3 | AW3: 4 | AX3: 4 | AY3: 4 | AZ3: 4 | BA3: 4 | BB3: 4 | BC3: 4 | BD3: 4 | BE3: 4 | BF3: 4 | BG3: 4 | BH3: 4 | BI3: 5 | BJ3: 5 | BK3: 5 | BL3: 5 | BM3: 5 | BN3: 5 | BO3: 5 | BP3: 5 | BQ3: 5 | BR3: 5 | BS3: 5 | BT3: 5 | BV3: 1 | BW3: 2 | BX3: 3 | BY3: 4 | BZ3: 5
A4: Months | M4: 1 | N4: =M4+1 -> 2 | O4: =N4+1 -> 3 | P4: =O4+1 -> 4 | Q4: =P4+1 -> 5 | R4: =Q4+1 -> 6 | S4: =R4+1 -> 7 | T4: =S4+1 -> 8 | U4: =T4+1 -> 9 | ... BT4: =BS4+1 -> 60 | BV4: 12 | BW4: 24 | BX4: 36 | BY4: 48 | BZ4: 60
A5: I. Equity & Liabilities
A6: Shareholders' Fund
A7: [+] | B7: Share Capital
A8: [+] | B8: Reserves & Surplus | M8: =L8+IS!M36 -> -877780 | N8: =M8+IS!N36 -> -1727267.8 | O8: =N8+IS!O36 -> -2548463.4 | P8: =O8+IS!P36 -> -3508121.6 | Q8: =P8+IS!Q36 -> -4468745.5 | R8: =Q8+IS!R36 -> -5381180.5 | S8: =R8+IS!S36 -> -6789264.7 | T8: =S8+IS!T36 -> -8079366.2 | ... BT8: =BS8+IS!BT36 -> -38068651 | BV8: =INDEX($M8:$BT8,MATCH(BV$4,$M$4:$BT$4,0)) -> -13531034 | BW8: =INDEX($M8:$BT8,MATCH(BW$4,$M$4:$BT$4,0)) -> -37159594 | BX8: =INDEX($M8:$BT8,MATCH(BX$4,$M$4:$BT$4,0)) -> -47362180 | BY8: =INDEX($M8:$BT8,MATCH(BY$4,$M$4:$BT$4,0)) -> -39111427 | BZ8: =INDEX($M8:$BT8,MATCH(BZ$4,$M$4:$BT$4,0)) -> -38068651
B9: TOTAL Shareholders Funds | M9: =SUM(M7:M8) -> -877780 | N9: =SUM(N7:N8) -> -1727267.8 | O9: =SUM(O7:O8) -> -2548463.4 | P9: =SUM(P7:P8) -> -3508121.6 | Q9: =SUM(Q7:Q8) -> -4468745.5 | R9: =SUM(R7:R8) -> -5381180.5 | S9: =SUM(S7:S8) -> -6789264.7 | T9: =SUM(T7:T8) -> -8079366.2 | ... BT9: =SUM(BT7:BT8) -> -38068651 | BV9: =INDEX($M9:$BT9,MATCH(BV$4,$M$4:$BT$4,0)) -> -13531034 | BW9: =INDEX($M9:$BT9,MATCH(BW$4,$M$4:$BT$4,0)) -> -37159594 | BX9: =INDEX($M9:$BT9,MATCH(BX$4,$M$4:$BT$4,0)) -> -47362180 | BY9: =INDEX($M9:$BT9,MATCH(BY$4,$M$4:$BT$4,0)) -> -39111427 | BZ9: =INDEX($M9:$BT9,MATCH(BZ$4,$M$4:$BT$4,0)) -> -38068651
A11: Liabilities
A12: Non-current liabilities
B13: Long-term borrowings | BV13: =INDEX($M13:$BT13,MATCH(BV$4,$M$4:$BT$4,0)) -> 0 | BW13: =INDEX($M13:$BT13,MATCH(BW$4,$M$4:$BT$4,0)) -> 0 | BX13: =INDEX($M13:$BT13,MATCH(BX$4,$M$4:$BT$4,0)) -> 0 | BY13: =INDEX($M13:$BT13,MATCH(BY$4,$M$4:$BT$4,0)) -> 0 | BZ13: =INDEX($M13:$BT13,MATCH(BZ$4,$M$4:$BT$4,0)) -> 0
A14: Current Liabilities
A15: [+] | B15: Deferred Revenue | M15: ='Revenue Buildup'!M18-'Revenue Buildup'!M20 -> 440000 | N15: ='Revenue Buildup'!N18-'Revenue Buildup'!N20 -> 400000 | O15: ='Revenue Buildup'!O18-'Revenue Buildup'!O20 -> 360000 | P15: ='Revenue Buildup'!P18-'Revenue Buildup'!P20 -> 540000 | Q15: ='Revenue Buildup'!Q18-'Revenue Buildup'!Q20 -> 480000 | R15: ='Revenue Buildup'!R18-'Revenue Buildup'!R20 -> 420000 | S15: ='Revenue Buildup'!S18-'Revenue Buildup'!S20 -> 1130000 | T15: ='Revenue Buildup'!T18-'Revenue Buildup'!T20 -> 1000000 | ... BT15: ='Revenue Buildup'!BT18-'Revenue Buildup'!BT20 -> 816000
A16: [+] | B16: Trade Payables | BV16: =INDEX($M16:$BT16,MATCH(BV$4,$M$4:$BT$4,0)) -> 0 | BW16: =INDEX($M16:$BT16,MATCH(BW$4,$M$4:$BT$4,0)) -> 0 | BX16: =INDEX($M16:$BT16,MATCH(BX$4,$M$4:$BT$4,0)) -> 0 | BY16: =INDEX($M16:$BT16,MATCH(BY$4,$M$4:$BT$4,0)) -> 0 | BZ16: =INDEX($M16:$BT16,MATCH(BZ$4,$M$4:$BT$4,0)) -> 0
A17: [+] | B17: Other current liabilities | BV17: =INDEX($M17:$BT17,MATCH(BV$4,$M$4:$BT$4,0)) -> 0 | BW17: =INDEX($M17:$BT17,MATCH(BW$4,$M$4:$BT$4,0)) -> 0 | BX17: =INDEX($M17:$BT17,MATCH(BX$4,$M$4:$BT$4,0)) -> 0 | BY17: =INDEX($M17:$BT17,MATCH(BY$4,$M$4:$BT$4,0)) -> 0 | BZ17: =INDEX($M17:$BT17,MATCH(BZ$4,$M$4:$BT$4,0)) -> 0
B18: TOTAL Liabilities | M18: =SUM(M13,M16:M17) -> 0 | N18: =SUM(N13,N16:N17) -> 0 | O18: =SUM(O13,O16:O17) -> 0 | P18: =SUM(P13,P16:P17) -> 0 | Q18: =SUM(Q13,Q16:Q17) -> 0 | R18: =SUM(R13,R16:R17) -> 0 | S18: =SUM(S13,S16:S17) -> 0 | T18: =SUM(T13,T16:T17) -> 0 | ... BT18: =SUM(BT13,BT16:BT17) -> 0 | BV18: =INDEX($M18:$BT18,MATCH(BV$4,$M$4:$BT$4,0)) -> 0 | BW18: =INDEX($M18:$BT18,MATCH(BW$4,$M$4:$BT$4,0)) -> 0 | BX18: =INDEX($M18:$BT18,MATCH(BX$4,$M$4:$BT$4,0)) -> 0 | BY18: =INDEX($M18:$BT18,MATCH(BY$4,$M$4:$BT$4,0)) -> 0 | BZ18: =INDEX($M18:$BT18,MATCH(BZ$4,$M$4:$BT$4,0)) -> 0
B20: TOTAL Equity and Liabilities | M20: =M9+M18 -> -877780 | N20: =N9+N18 -> -1727267.8 | O20: =O9+O18 -> -2548463.4 | P20: =P9+P18 -> -3508121.6 | Q20: =Q9+Q18 -> -4468745.5 | R20: =R9+R18 -> -5381180.5 | S20: =S9+S18 -> -6789264.7 | T20: =T9+T18 -> -8079366.2 | ... BT20: =BT9+BT18 -> -38068651 | BV20: =BV9+BV18 -> -13531034 | BW20: =BW9+BW18 -> -37159594 | BX20: =BX9+BX18 -> -47362180 | BY20: =BY9+BY18 -> -39111427 | BZ20: =BZ9+BZ18 -> -38068651
A22: II. Assets
A23: Non-Current Assets
A24: Fixed Assets
A25: [+] | B25: Tangible assets | BV25: =INDEX($M25:$BT25,MATCH(BV$4,$M$4:$BT$4,0)) -> 0 | BW25: =INDEX($M25:$BT25,MATCH(BW$4,$M$4:$BT$4,0)) -> 0 | BX25: =INDEX($M25:$BT25,MATCH(BX$4,$M$4:$BT$4,0)) -> 0 | BY25: =INDEX($M25:$BT25,MATCH(BY$4,$M$4:$BT$4,0)) -> 0 | BZ25: =INDEX($M25:$BT25,MATCH(BZ$4,$M$4:$BT$4,0)) -> 0
A26: [+] | B26: Intangible assets | BV26: =INDEX($M26:$BT26,MATCH(BV$4,$M$4:$BT$4,0)) -> 0 | BW26: =INDEX($M26:$BT26,MATCH(BW$4,$M$4:$BT$4,0)) -> 0 | BX26: =INDEX($M26:$BT26,MATCH(BX$4,$M$4:$BT$4,0)) -> 0 | BY26: =INDEX($M26:$BT26,MATCH(BY$4,$M$4:$BT$4,0)) -> 0 | BZ26: =INDEX($M26:$BT26,MATCH(BZ$4,$M$4:$BT$4,0)) -> 0
A27: [+] | B27: Other Non Current Asset | BV27: =INDEX($M27:$BT27,MATCH(BV$4,$M$4:$BT$4,0)) -> 0 | BW27: =INDEX($M27:$BT27,MATCH(BW$4,$M$4:$BT$4,0)) -> 0 | BX27: =INDEX($M27:$BT27,MATCH(BX$4,$M$4:$BT$4,0)) -> 0 | BY27: =INDEX($M27:$BT27,MATCH(BY$4,$M$4:$BT$4,0)) -> 0 | BZ27: =INDEX($M27:$BT27,MATCH(BZ$4,$M$4:$BT$4,0)) -> 0
B28: Total Non Current Assets | M28: =SUM(M25:M27) -> 0 | N28: =SUM(N25:N27) -> 0 | O28: =SUM(O25:O27) -> 0 | P28: =SUM(P25:P27) -> 0 | Q28: =SUM(Q25:Q27) -> 0 | R28: =SUM(R25:R27) -> 0 | S28: =SUM(S25:S27) -> 0 | T28: =SUM(T25:T27) -> 0 | ... BT28: =SUM(BT25:BT27) -> 0 | BV28: =SUM(BV25:BV27) -> 0 | BW28: =SUM(BW25:BW27) -> 0 | BX28: =SUM(BX25:BX27) -> 0 | BY28: =SUM(BY25:BY27) -> 0 | BZ28: =SUM(BZ25:BZ27) -> 0
A30: Current Assets
A31: [+] | B31: Trade Receivables | BV31: =INDEX($M31:$BT31,MATCH(BV$4,$M$4:$BT$4,0)) -> 0 | BW31: =INDEX($M31:$BT31,MATCH(BW$4,$M$4:$BT$4,0)) -> 0 | BX31: =INDEX($M31:$BT31,MATCH(BX$4,$M$4:$BT$4,0)) -> 0 | BY31: =INDEX($M31:$BT31,MATCH(BY$4,$M$4:$BT$4,0)) -> 0 | BZ31: =INDEX($M31:$BT31,MATCH(BZ$4,$M$4:$BT$4,0)) -> 0
A32: [+] | B32: Inventory | BV32: =INDEX($M32:$BT32,MATCH(BV$4,$M$4:$BT$4,0)) -> 0 | BW32: =INDEX($M32:$BT32,MATCH(BW$4,$M$4:$BT$4,0)) -> 0 | BX32: =INDEX($M32:$BT32,MATCH(BX$4,$M$4:$BT$4,0)) -> 0 | BY32: =INDEX($M32:$BT32,MATCH(BY$4,$M$4:$BT$4,0)) -> 0 | BZ32: =INDEX($M32:$BT32,MATCH(BZ$4,$M$4:$BT$4,0)) -> 0
A33: [+] | B33: Cash and Cash Equivalents | M33: =CFS!M43 -> -437780 | N33: =CFS!N43 -> -1327267.8 | O33: =CFS!O43 -> -2188463.4 | P33: =CFS!P43 -> -2968121.6 | Q33: =CFS!Q43 -> -3988745.5 | R33: =CFS!R43 -> -4961180.5 | S33: =CFS!S43 -> -5659264.7 | T33: =CFS!T43 -> -7079366.2 | ... BT33: =CFS!BT43 -> -37252651 | BV33: =INDEX($M33:$BT33,MATCH(BV$4,$M$4:$BT$4,0)) -> -12511034 | BW33: =INDEX($M33:$BT33,MATCH(BW$4,$M$4:$BT$4,0)) -> -34261594 | BX33: =INDEX($M33:$BT33,MATCH(BX$4,$M$4:$BT$4,0)) -> -45250180 | BY33: =INDEX($M33:$BT33,MATCH(BY$4,$M$4:$BT$4,0)) -> -38343427 | BZ33: =INDEX($M33:$BT33,MATCH(BZ$4,$M$4:$BT$4,0)) -> -37252651
A34: [+] | B34: Short Term Loans and Advances | BV34: =INDEX($M34:$BT34,MATCH(BV$4,$M$4:$BT$4,0)) -> 0 | BW34: =INDEX($M34:$BT34,MATCH(BW$4,$M$4:$BT$4,0)) -> 0 | BX34: =INDEX($M34:$BT34,MATCH(BX$4,$M$4:$BT$4,0)) -> 0 | BY34: =INDEX($M34:$BT34,MATCH(BY$4,$M$4:$BT$4,0)) -> 0 | BZ34: =INDEX($M34:$BT34,MATCH(BZ$4,$M$4:$BT$4,0)) -> 0
B35: Total Current Assets | M35: =SUM(M31:M34) -> -437780 | N35: =SUM(N31:N34) -> -1327267.8 | O35: =SUM(O31:O34) -> -2188463.4 | P35: =SUM(P31:P34) -> -2968121.6 | Q35: =SUM(Q31:Q34) -> -3988745.5 | R35: =SUM(R31:R34) -> -4961180.5 | S35: =SUM(S31:S34) -> -5659264.7 | T35: =SUM(T31:T34) -> -7079366.2 | ... BT35: =SUM(BT31:BT34) -> -37252651 | BV35: =SUM(BV31:BV34) -> -12511034 | BW35: =SUM(BW31:BW34) -> -34261594 | BX35: =SUM(BX31:BX34) -> -45250180 | BY35: =SUM(BY31:BY34) -> -38343427 | BZ35: =SUM(BZ31:BZ34) -> -37252651
B37: Total Assets | M37: =M28+M35 -> -437780 | N37: =N28+N35 -> -1327267.8 | O37: =O28+O35 -> -2188463.4 | P37: =P28+P35 -> -2968121.6 | Q37: =Q28+Q35 -> -3988745.5 | R37: =R28+R35 -> -4961180.5 | S37: =S28+S35 -> -5659264.7 | T37: =T28+T35 -> -7079366.2 | ... BT37: =BT28+BT35 -> -37252651 | BV37: =BV28+BV35 -> -12511034 | BW37: =BW28+BW35 -> -34261594 | BX37: =BX28+BX35 -> -45250180 | BY37: =BY28+BY35 -> -38343427 | BZ37: =BZ28+BZ35 -> -37252651
A38: Check | M38: =M37-M20 -> 440000 | N38: =N37-N20 -> 400000 | O38: =O37-O20 -> 360000 | P38: =P37-P20 -> 540000 | Q38: =Q37-Q20 -> 480000 | R38: =R37-R20 -> 420000 | S38: =S37-S20 -> 1130000 | T38: =T37-T20 -> 1000000 | ... BT38: =BT37-BT20 -> 816000 | BV38: =BV37-BV20 -> 1020000 | BW38: =BW37-BW20 -> 2898000 | BX38: =BX37-BX20 -> 2112000 | BY38: =BY37-BY20 -> 768000 | BZ38: =BZ37-BZ20 -> 816000

Sheet CFS
A1: Cash Flow Statement
A2: Cells in Orange are assumptions | M2: MONTHLY | BV2: YEARLY
A3: Year | M3: 1 | N3: 1 | O3: 1 | P3: 1 | Q3: 1 | R3: 1 | S3: 1 | T3: 1 | U3: 1 | V3: 1 | W3: 1 | X3: 1 | Y3: =X3+1 -> 2 | Z3: =Y3 -> 2 | AA3: =Z3 -> 2 | AB3: =AA3 -> 2 | AC3: =AB3 -> 2 | AD3: =AC3 -> 2 | AE3: =AD3 -> 2 | AF3: =AE3 -> 2 | AG3: =AF3 -> 2 | ... AJ3: =AI3 -> 2 | AK3: 3 | AL3: 3 | AM3: 3 | AN3: 3 | AO3: 3 | AP3: 3 | AQ3: 3 | AR3: 3 | AS3: 3 | AT3: 3 | AU3: 3 | AV3: 3 | AW3: 4 | AX3: 4 | AY3: 4 | AZ3: 4 | BA3: 4 | BB3: 4 | BC3: 4 | BD3: 4 | BE3: 4 | BF3: 4 | BG3: 4 | BH3: 4 | BI3: 5 | BJ3: 5 | BK3: 5 | BL3: 5 | BM3: 5 | BN3: 5 | BO3: 5 | BP3: 5 | BQ3: 5 | BR3: 5 | BS3: 5 | BT3: 5 | BV3: 1 | BW3: 2 | BX3: 3 | BY3: 4 | BZ3: 5
A4: Months | M4: 1 | N4: =M4+1 -> 2 | O4: =N4+1 -> 3 | P4: =O4+1 -> 4 | Q4: =P4+1 -> 5 | R4: =Q4+1 -> 6 | S4: =R4+1 -> 7 | T4: =S4+1 -> 8 | U4: =T4+1 -> 9 | ... BT4: =BS4+1 -> 60 | BV4: 12 | BW4: 24 | BX4: 36 | BY4: 48 | BZ4: 60
A5: Cash Flow from Operations-
B6: Profit After Tax | M6: =IS!M36 -> -877780 | N6: =IS!N36 -> -849487.8 | O6: =IS!O36 -> -821195.6 | P6: =IS!P36 -> -959658.19 | Q6: =IS!Q36 -> -960623.96 | R6: =IS!R36 -> -912434.95 | S6: =IS!S36 -> -1408084.2 | T6: =IS!T36 -> -1290101.5 | ... BT6: =IS!BT36 -> 664376.18 | BV6: =SUMIF($M$3:$BT$3,BV$3,$M6:$BT6) -> -13531034 | BW6: =SUMIF($M$3:$BT$3,BW$3,$M6:$BT6) -> -23628560 | BX6: =SUMIF($M$3:$BT$3,BX$3,$M6:$BT6) -> -10202587 | BY6: =SUMIF($M$3:$BT$3,BY$3,$M6:$BT6) -> 8250753.9 | BZ6: =SUMIF($M$3:$BT$3,BZ$3,$M6:$BT6) -> 1042775.4
A8: [+] | B8: Depreciation and Amortization Expenses | M8: ='[1]P&L'!M32 -> 0 | N8: ='[1]P&L'!N32 -> 0 | O8: ='[1]P&L'!O32 -> 0 | P8: ='[1]P&L'!P32 -> 0 | Q8: ='[1]P&L'!Q32 -> 0 | R8: ='[1]P&L'!R32 -> 0 | S8: ='[1]P&L'!S32 -> 0 | T8: ='[1]P&L'!T32 -> 0 | ... BT8: ='[1]P&L'!BT32 -> 0 | BV8: =SUMIF($M$3:$BT$3,BV$3,$M8:$BT8) -> 0 | BW8: =SUMIF($M$3:$BT$3,BW$3,$M8:$BT8) -> 0 | BX8: =SUMIF($M$3:$BT$3,BX$3,$M8:$BT8) -> 0 | BY8: =SUMIF($M$3:$BT$3,BY$3,$M8:$BT8) -> 0 | BZ8: =SUMIF($M$3:$BT$3,BZ$3,$M8:$BT8) -> 0
A9: [+] | B9: Interest Expenses
A10: [+] | B10: Preliminary Expenses written off
A11: [+] | B11: Interest Received
A12: [+] | B12: Loss/Profit on Sale of Assets
A13: [+] | B13: Liabilities written off
B14: Operating Profit before Working Capital Changes | M14: =SUM(M6:M13) -> -877780 | N14: =SUM(N6:N13) -> -849487.8 | O14: =SUM(O6:O13) -> -821195.6 | P14: =SUM(P6:P13) -> -959658.19 | Q14: =SUM(Q6:Q13) -> -960623.96 | R14: =SUM(R6:R13) -> -912434.95 | S14: =SUM(S6:S13) -> -1408084.2 | T14: =SUM(T6:T13) -> -1290101.5 | ... BT14: =SUM(BT6:BT13) -> 664376.18 | BV14: =SUM(BV6:BV13) -> -13531034 | BW14: =SUM(BW6:BW13) -> -23628560 | BX14: =SUM(BX6:BX13) -> -10202587 | BY14: =SUM(BY6:BY13) -> 8250753.9 | BZ14: =SUM(BZ6:BZ13) -> 1042775.4
A15: Changes in working Capital | M15: =SUM(M16:M19,M21:M23) -> 440000 | N15: =SUM(N16:N19,N21:N23) -> -40000 | O15: =SUM(O16:O19,O21:O23) -> -40000 | P15: =SUM(P16:P19,P21:P23) -> 180000 | Q15: =SUM(Q16:Q19,Q21:Q23) -> -60000 | R15: =SUM(R16:R19,R21:R23) -> -60000 | S15: =SUM(S16:S19,S21:S23) -> 710000 | T15: =SUM(T16:T19,T21:T23) -> -130000 | ... BT15: =SUM(BT16:BT19,BT21:BT23) -> -326000 | BV15: =SUMIF($M$3:$BT$3,BV$3,$M15:$BT15) -> 1020000 | BW15: =SUMIF($M$3:$BT$3,BW$3,$M15:$BT15) -> 1878000 | BX15: =SUMIF($M$3:$BT$3,BX$3,$M15:$BT15) -> -786000 | BY15: =SUMIF($M$3:$BT$3,BY$3,$M15:$BT15) -> -1344000 | BZ15: =SUMIF($M$3:$BT$3,BZ$3,$M15:$BT15) -> 48000
A16: [-] | B16: Trade Receivables | BV16: =SUMIF($M$3:$BT$3,BV$3,$M16:$BT16) -> 0 | BW16: =SUMIF($M$3:$BT$3,BW$3,$M16:$BT16) -> 0 | BX16: =SUMIF($M$3:$BT$3,BX$3,$M16:$BT16) -> 0 | BY16: =SUMIF($M$3:$BT$3,BY$3,$M16:$BT16) -> 0 | BZ16: =SUMIF($M$3:$BT$3,BZ$3,$M16:$BT16) -> 0
A17: [-] | B17: Inventories | BV17: =SUMIF($M$3:$BT$3,BV$3,$M17:$BT17) -> 0 | BW17: =SUMIF($M$3:$BT$3,BW$3,$M17:$BT17) -> 0 | BX17: =SUMIF($M$3:$BT$3,BX$3,$M17:$BT17) -> 0 | BY17: =SUMIF($M$3:$BT$3,BY$3,$M17:$BT17) -> 0 | BZ17: =SUMIF($M$3:$BT$3,BZ$3,$M17:$BT17) -> 0
A18: [-] | B18: Short Term Loans and Advances | BV18: =SUMIF($M$3:$BT$3,BV$3,$M18:$BT18) -> 0 | BW18: =SUMIF($M$3:$BT$3,BW$3,$M18:$BT18) -> 0 | BX18: =SUMIF($M$3:$BT$3,BX$3,$M18:$BT18) -> 0 | BY18: =SUMIF($M$3:$BT$3,BY$3,$M18:$BT18) -> 0 | BZ18: =SUMIF($M$3:$BT$3,BZ$3,$M18:$BT18) -> 0
A19: [-] | B19: Other Current Assets | BV19: =SUMIF($M$3:$BT$3,BV$3,$M19:$BT19) -> 0 | BW19: =SUMIF($M$3:$BT$3,BW$3,$M19:$BT19) -> 0 | BX19: =SUMIF($M$3:$BT$3,BX$3,$M19:$BT19) -> 0 | BY19: =SUMIF($M$3:$BT$3,BY$3,$M19:$BT19) -> 0 | BZ19: =SUMIF($M$3:$BT$3,BZ$3,$M19:$BT19) -> 0
A21: [+] | B21: Deferred Revenue | M21: =BS!M15-BS!L15 -> 440000 | N21: =BS!N15-BS!M15 -> -40000 | O21: =BS!O15-BS!N15 -> -40000 | P21: =BS!P15-BS!O15 -> 180000 | Q21: =BS!Q15-BS!P15 -> -60000 | R21: =BS!R15-BS!Q15 -> -60000 | S21: =BS!S15-BS!R15 -> 710000 | T21: =BS!T15-BS!S15 -> -130000 | ... BT21: =BS!BT15-BS!BS15 -> -326000 | BV21: =SUMIF($M$3:$BT$3,BV$3,$M21:$BT21) -> 1020000 | BW21: =SUMIF($M$3:$BT$3,BW$3,$M21:$BT21) -> 1878000 | BX21: =SUMIF($M$3:$BT$3,BX$3,$M21:$BT21) -> -786000 | BY21: =SUMIF($M$3:$BT$3,BY$3,$M21:$BT21) -> -1344000 | BZ21: =SUMIF($M$3:$BT$3,BZ$3,$M21:$BT21) -> 48000
A22: [+] | B22: Trade Payables | BV22: =SUMIF($M$3:$BT$3,BV$3,$M22:$BT22) -> 0 | BW22: =SUMIF($M$3:$BT$3,BW$3,$M22:$BT22) -> 0 | BX22: =SUMIF($M$3:$BT$3,BX$3,$M22:$BT22) -> 0 | BY22: =SUMIF($M$3:$BT$3,BY$3,$M22:$BT22) -> 0 | BZ22: =SUMIF($M$3:$BT$3,BZ$3,$M22:$BT22) -> 0
A23: [+] | B23: Other Current Liabilities | BV23: =SUMIF($M$3:$BT$3,BV$3,$M23:$BT23) -> 0 | BW23: =SUMIF($M$3:$BT$3,BW$3,$M23:$BT23) -> 0 | BX23: =SUMIF($M$3:$BT$3,BX$3,$M23:$BT23) -> 0 | BY23: =SUMIF($M$3:$BT$3,BY$3,$M23:$BT23) -> 0 | BZ23: =SUMIF($M$3:$BT$3,BZ$3,$M23:$BT23) -> 0
B25: Change in Cash Flow from Operations | M25: =SUM(M14:M15) -> -437780 | N25: =SUM(N14:N15) -> -889487.8 | O25: =SUM(O14:O15) -> -861195.6 | P25: =SUM(P14:P15) -> -779658.19 | Q25: =SUM(Q14:Q15) -> -1020624 | R25: =SUM(R14:R15) -> -972434.95 | S25: =SUM(S14:S15) -> -698084.18 | T25: =SUM(T14:T15) -> -1420101.5 | ... BT25: =SUM(BT14:BT15) -> 338376.18 | BV25: =SUM(BV14,BV16:BV23) -> -12511034 | BW25: =SUM(BW14,BW16:BW23) -> -21750560 | BX25: =SUM(BX14,BX16:BX23) -> -10988587 | BY25: =SUM(BY14,BY16:BY23) -> 6906753.9 | BZ25: =SUM(BZ14,BZ16:BZ23) -> 1090775.4
A27: Cash Flow from Investing Activites-
B28: Purchase/sale of Non current Assets | BV28: =SUMIF($M$3:$BT$3,BV$3,$M28:$BT28) -> 0 | BW28: =SUMIF($M$3:$BT$3,BW$3,$M28:$BT28) -> 0 | BX28: =SUMIF($M$3:$BT$3,BX$3,$M28:$BT28) -> 0 | BY28: =SUMIF($M$3:$BT$3,BY$3,$M28:$BT28) -> 0 | BZ28: =SUMIF($M$3:$BT$3,BZ$3,$M28:$BT28) -> 0
A29: [+] | B29: Purchase/sale of Other Non Current Asset | BV29: =SUMIF($M$3:$BT$3,BV$3,$M29:$BT29) -> 0 | BW29: =SUMIF($M$3:$BT$3,BW$3,$M29:$BT29) -> 0 | BX29: =SUMIF($M$3:$BT$3,BX$3,$M29:$BT29) -> 0 | BY29: =SUMIF($M$3:$BT$3,BY$3,$M29:$BT29) -> 0 | BZ29: =SUMIF($M$3:$BT$3,BZ$3,$M29:$BT29) -> 0
B31: Changes in Cash Flow from Investing | M31: =SUM(M28:M29) -> 0 | N31: =SUM(N28:N29) -> 0 | O31: =SUM(O28:O29) -> 0 | P31: =SUM(P28:P29) -> 0 | Q31: =SUM(Q28:Q29) -> 0 | R31: =SUM(R28:R29) -> 0 | S31: =SUM(S28:S29) -> 0 | T31: =SUM(T28:T29) -> 0 | ... BT31: =SUM(BT28:BT29) -> 0 | BV31: =SUM(BV28:BV29) -> 0 | BW31: =SUM(BW28:BW29) -> 0 | BX31: =SUM(BX28:BX29) -> 0 | BY31: =SUM(BY28:BY29) -> 0 | BZ31: =SUM(BZ28:BZ29) -> 0
A33: Cash Flow from Financing Activities-
A34: [+] | B34: Increase/Decrease in Share Capital | BV34: =SUMIF($M$3:$BT$3,BV$3,$M34:$BT34) -> 0 | BW34: =SUMIF($M$3:$BT$3,BW$3,$M34:$BT34) -> 0 | BX34: =SUMIF($M$3:$BT$3,BX$3,$M34:$BT34) -> 0 | BY34: =SUMIF($M$3:$BT$3,BY$3,$M34:$BT34) -> 0 | BZ34: =SUMIF($M$3:$BT$3,BZ$3,$M34:$BT34) -> 0
A35: [+] | B35: Premium Collected on issue of Shares | BV35: =SUMIF($M$3:$BT$3,BV$3,$M35:$BT35) -> 0 | BW35: =SUMIF($M$3:$BT$3,BW$3,$M35:$BT35) -> 0 | BX35: =SUMIF($M$3:$BT$3,BX$3,$M35:$BT35) -> 0 | BY35: =SUMIF($M$3:$BT$3,BY$3,$M35:$BT35) -> 0 | BZ35: =SUMIF($M$3:$BT$3,BZ$3,$M35:$BT35) -> 0
A36: [-] | B36: Interest Expenses | BV36: =SUMIF($M$3:$BT$3,BV$3,$M36:$BT36) -> 0 | BW36: =SUMIF($M$3:$BT$3,BW$3,$M36:$BT36) -> 0 | BX36: =SUMIF($M$3:$BT$3,BX$3,$M36:$BT36) -> 0 | BY36: =SUMIF($M$3:$BT$3,BY$3,$M36:$BT36) -> 0 | BZ36: =SUMIF($M$3:$BT$3,BZ$3,$M36:$BT36) -> 0
A37: [+] | B37: Increase/Decrease in Long Term Borrowings | BV37: =SUMIF($M$3:$BT$3,BV$3,$M37:$BT37) -> 0 | BW37: =SUMIF($M$3:$BT$3,BW$3,$M37:$BT37) -> 0 | BX37: =SUMIF($M$3:$BT$3,BX$3,$M37:$BT37) -> 0 | BY37: =SUMIF($M$3:$BT$3,BY$3,$M37:$BT37) -> 0 | BZ37: =SUMIF($M$3:$BT$3,BZ$3,$M37:$BT37) -> 0
A38: [+] | B38: Increase/Decrease in Other Short Term Borrowings | BV38: =SUMIF($M$3:$BT$3,BV$3,$M38:$BT38) -> 0 | BW38: =SUMIF($M$3:$BT$3,BW$3,$M38:$BT38) -> 0 | BX38: =SUMIF($M$3:$BT$3,BX$3,$M38:$BT38) -> 0 | BY38: =SUMIF($M$3:$BT$3,BY$3,$M38:$BT38) -> 0 | BZ38: =SUMIF($M$3:$BT$3,BZ$3,$M38:$BT38) -> 0
B39: Changes in Cash Flow from Financing | M39: =SUM(M34:M38) -> 0 | N39: =SUM(N34:N38) -> 0 | O39: =SUM(O34:O38) -> 0 | P39: =SUM(P34:P38) -> 0 | Q39: =SUM(Q34:Q38) -> 0 | R39: =SUM(R34:R38) -> 0 | S39: =SUM(S34:S38) -> 0 | T39: =SUM(T34:T38) -> 0 | ... BT39: =SUM(BT34:BT38) -> 0 | BV39: =SUM(BV34:BV38) -> 0 | BW39: =SUM(BW34:BW38) -> 0 | BX39: =SUM(BX34:BX38) -> 0 | BY39: =SUM(BY34:BY38) -> 0 | BZ39: =SUM(BZ34:BZ38) -> 0
B41: Net Changes in Cash & Cash Equivalents | M41: =M39+M31+M25 -> -437780 | N41: =N39+N31+N25 -> -889487.8 | O41: =O39+O31+O25 -> -861195.6 | P41: =P39+P31+P25 -> -779658.19 | Q41: =Q39+Q31+Q25 -> -1020624 | R41: =R39+R31+R25 -> -972434.95 | S41: =S39+S31+S25 -> -698084.18 | T41: =T39+T31+T25 -> -1420101.5 | ... BT41: =BT39+BT31+BT25 -> 338376.18 | BV41: =BV39+BV31+BV25 -> -12511034 | BW41: =BW39+BW31+BW25 -> -21750560 | BX41: =BX39+BX31+BX25 -> -10988587 | BY41: =BY39+BY31+BY25 -> 6906753.9 | BZ41: =BZ39+BZ31+BZ25 -> 1090775.4
B42: Cash Opening balance | M42: 0 | N42: =M43 -> -437780 | O42: =N43 -> -1327267.8 | P42: =O43 -> -2188463.4 | Q42: =P43 -> -2968121.6 | R42: =Q43 -> -3988745.5 | S42: =R43 -> -4961180.5 | T42: =S43 -> -5659264.7 | U42: =T43 -> -7079366.2 | ... BT42: =BS43 -> -37591027 | BV42: =M42 -> 0 | BW42: =BV43 -> -12511034 | BX42: =BW43 -> -34261594 | BY42: =BX43 -> -45250180 | BZ42: =BY43 -> -38343427
B43: Cash Closing Balance | M43: =M42+M41 -> -437780 | N43: =N42+N41 -> -1327267.8 | O43: =O42+O41 -> -2188463.4 | P43: =P42+P41 -> -2968121.6 | Q43: =Q42+Q41 -> -3988745.5 | R43: =R42+R41 -> -4961180.5 | S43: =S42+S41 -> -5659264.7 | T43: =T42+T41 -> -7079366.2 | ... BT43: =BT42+BT41 -> -37252651 | BV43: =BV42+BV41 -> -12511034 | BW43: =BW42+BW41 -> -34261594 | BX43: =BX42+BX41 -> -45250180 | BY43: =BY42+BY41 -> -38343427 | BZ43: =BZ42+BZ41 -> -37252651
AF44: =SUM(AE41:BT41) -> -15441925
B45: Cash Burn 12 M | D45: =W43 -> -11072225
B46: Cash Burn 18 M | D46: =AC43 -> -20382754
B47: Cash Burn 24 M | D47: =AI43 -> -32192655

Sheet Valuation
A1: Venture Capital Method Valuation
A2: INR:USD | B2: 86
A3: Precedent Transaction Analysis
B5: S.No | C5: Name | D5: Founded Year | E5: Total Equity Funding (In Mn $) | F5: Date | G5: Funding Amount | H5: Round | I5: Valuation (In $ Mn) | J5: Revenue. (In $ Mn) | K5: Revenue Multiple
B6: 1 | C6: Sales assist.ai | F6: Nov 29, 2024 | G6: $201.2K | H6: Seed | I6: 2.9 | J6: -
C7: Sales assist.ai | F7: Mar 22, 2024 | G7: $120.3K | H7: Seed | I7: 1.8 | J7: =115.9/10^3 -> 0.1159 | K7: =I7/J7 -> 15.53063
C8: Sales assist.ai | F8: Dec 05, 2023 | G8: - | H8: Angel | I8: - | J8: =94.1/10^3 -> 0.0941
C9: Sales assist.ai | F9: May 15, 2021 | G9: $230.2K | H9: Seed | I9: 1.6 | J9: =2.7/10^3 -> 0.0027 | K9: =I9/J9 -> 592.59259
C10: Sales assist.ai | F10: Jan 02, 2021 | G10: $34.2K | H10: Seed | I10: =386.8/10^3 -> 0.3868 | J10: =2.3/10^3 -> 0.0023 | K10: =I10/J10 -> 168.17391
B12: 2 | C12: Instasell | F12: Mar 00, 2022 | G12: $525k | H12: Seed | I12: 2.6 | J12: NA
C13: Instasell | F13: DEC 00, 2021 | G13: $33.3k | H13: Seed | I13: 323 | J13: NA
B17: 3 | C17: Baaz | D17: 2019 | E17: 1.12 | F17: Feb 16, 2022 | G17: $700.0K | H17: Seed | I17: 3.7 | J17: 0.3904 | K17: =I17/J17 -> 9.477459
C18: Baaz | F18: May 31, 2021 | G18: $369.5K | H18: Seed | I18: 2.1 | J18: 0.0826 | K18: =I18/J18 -> 25.423729
C19: Baaz | F19: Feb 06, 2021 | G19: $23.3K | H19: Angel | I19: 1.1 | J19: 0.0131 | K19: =I19/J19 -> 83.969466
C20: Baaz | F20: Nov 30, 2020 | G20: $31.1K | H20: Angel | I20: =706.1/10^3 -> 0.7061 | J20: 0.0099 | K20: =I20/J20 -> 71.323232
C21: Baaz | F21: Oct 29, 2020 | G21: - | H21: Angel | I21: =474.7/10^3 -> 0.4747 | J21: 0.0089 | K21: =I21/J21 -> 53.337079
D23: EV/Revenue Multiple
C24: Industry Median | D24: =MEDIAN(K7,K17:K18) -> 15.53063
D26: (In INR Crore) | E26: (In $ Mn)
C27: Revenue | D27: =IS!BZ7/10^7 -> 21.3 | E27: =(D27*10)/$B$2 -> 2.4767442
C28: EV | D28: =D27*D24 -> 330.80242 | E28: =(D28*10)/$B$2 -> 38.465397
C30: Discount Rate | D30: 0.6 | E30: =D30 -> 0.6
C31: Post Money Valuation | D31: =(D28/(1+D30)^5) -> 31.547777 | E31: =(D31*10)/$B$2 -> 3.6683461
C32: Total Investment | D32: =ABS(CFS!AC43/10^7) -> 2.0382754 | E32: =(D32*10)/$B$2 -> 0.23700877
C33: Pre Money Valuation | D33: =D31-D32 -> 29.509501 | E33: =(D33*10)/$B$2 -> 3.4313374
C34: Funding Round Stake sale | D34: =D32/D31 -> 0.064609163 | E34: =E32/E31 -> 0.064609163

Sheet Sheet10
A1: Direct Costs (COGS) for a B2B SaaS Business
A3: COGS includes all direct costs required to deliver the software service. These typically include:
A5: Hosting & Infrastructure Costs
A7: Cloud services (AWS, Google Cloud, Azure)
A8: Database and storage (e.g., Amazon RDS, MongoDB Atlas)
A9: Content delivery networks (CDN)
A10: Load balancers and networking costs
A12: Third-Party Software & API Costs
A14: Payment gateway fees (e.g., Stripe, Razorpay)
A15: AI/ML APIs (e.g., OpenAI, Google Cloud APIs)
A16: Email/SMS services (e.g., SendGrid, Twilio)
A17: Security services (e.g., Cloudflare, Auth0)
... A37: Software licenses for development tools used in maintaining the SaaS product

Sheet Sheet1
A1: 1. Marketing Team Structure & Roles
A3: Role | B3: Responsibilities | C3: Headcount (Early, Growth, Scale)
A4: Chief Marketing Officer | B4: Owns marketing strategy, brand positioning & demand generation. | C4: 1 (Growth)
A5: Content Marketing Manager | B5: Creates blogs, case studies, whitepapers, and e-books. | C5: 1 (Early) → 3+ (Scale)
A6: SEO & Organic Growth Specialist | B6: Handles website traffic, keyword ranking & link-building. | C6: 1 (Growth) → 2+ (Scale)
A7: Performance Marketing Manager (PPC) | B7: Runs Google Ads, LinkedIn Ads & paid acquisition campaigns. | C7: 1 (Growth) → 3+ (Scale)
A8: Marketing Automation Specialist | B8: Manages email campaigns, drip sequences & CRM workflows. | C8: 1 (Growth) → 2+ (Scale)
A9: Social Media & Community Manager | B9: Builds brand presence on LinkedIn, Twitter & Slack communities. | C9: 1 (Early) → 2+ (Scale)
A10: PR & Media Relations Manager | B10: Handles press releases, thought leadership & industry outreach. | C10: 1 (Growth)
A11: Event & Webinar Marketing Manager | B11: Plans conferences, virtual events, and speaking engagements. | C11: 1 (Growth)
A12: Video Content Creator | B12: Produces product demos, testimonials & video ads. | C12: 1 (Growth) → 2+ (Scale)
A13: Partner & Affiliate Marketing Manager | B13: Develops strategic alliances & referral programs. | C13: 1 (Growth)
A16: Head of Marketing (1)
A17: ✔ Growth Team (2) → Growth Marketing Manager, SEO/Automation Specialist
A18: ✔ Brand & Community (2) → PR Manager, Social Media Manager
A19: ✔ Content & Creative (2) → Content Manager, Video Designer
